[{"caption":"Table 1. Comparison with state-of-the-art methods. Top-1, top-5 \nand top-10 accuracies (%) are reported. The best performance is \nbold. In the second column, \"g\" stands for global scale, \"g+l\" \nstands for global scale and local scale, \"m\" stands for full-scale \nrepresentations from coarse to fine. \"RVN\" stands for our pro-\nposed re-ranking by visual neighbors. \n","rows":["CMCE [ 12 ]","g","13 ]","Dual Path [ 30 ]","NAFS with RVN ( ours )","g+l","PMA [ 7 ]","CMPM+CMPC [ 26 ]","-","m","ViTAA [ 25 ]","MIA [ 19 ]","PWM+ATH [ 2 ]","NAFS ( ours )"],"columns":["Top10","Top5","Top1"],"mergedAllColumns":[],"numberCells":[{"number":"87.51","isBolded":true,"associatedRows":["NAFS with RVN ( ours )","m","-"],"associatedColumns":["Top10"],"associatedMergedColumns":[]},{"number":"81.23","isBolded":false,"associatedRows":["NAFS with RVN ( ours )","PMA [ 7 ]","g+l","-"],"associatedColumns":["Top10"],"associatedMergedColumns":[]},{"number":"27.14","isBolded":false,"associatedRows":["CMPM+CMPC [ 26 ]","PWM+ATH [ 2 ]","g"],"associatedColumns":["Top1"],"associatedMergedColumns":[]},{"number":"82.90","isBolded":false,"associatedRows":["CMPM+CMPC [ 26 ]","MIA [ 19 ]","g+l","-"],"associatedColumns":["Top10"],"associatedMergedColumns":[]},{"number":"53.10","isBolded":false,"associatedRows":["CMPM+CMPC [ 26 ]","MIA [ 19 ]","g+l"],"associatedColumns":["Top1"],"associatedMergedColumns":[]},{"number":"25.94","isBolded":false,"associatedRows":["CMPM+CMPC [ 26 ]","CMCE [ 12 ]","g"],"associatedColumns":["Top1"],"associatedMergedColumns":[]},{"number":"66.26","isBolded":false,"associatedRows":["CMPM+CMPC [ 26 ]","Dual Path [ 30 ]","g"],"associatedColumns":["Top5"],"associatedMergedColumns":[]},{"number":"79.27","isBolded":false,"associatedRows":["CMPM+CMPC [ 26 ]","g","-"],"associatedColumns":["Top10"],"associatedMergedColumns":[]},{"number":"49.45","isBolded":false,"associatedRows":["CMPM+CMPC [ 26 ]","PWM+ATH [ 2 ]","g"],"associatedColumns":["Top5"],"associatedMergedColumns":[]},{"number":"53.81","isBolded":false,"associatedRows":["NAFS with RVN ( ours )","PMA [ 7 ]","g+l"],"associatedColumns":["Top1"],"associatedMergedColumns":[]},{"number":"44.40","isBolded":false,"associatedRows":["CMPM+CMPC [ 26 ]","Dual Path [ 30 ]","g"],"associatedColumns":["Top1"],"associatedMergedColumns":[]},{"number":"73.54","isBolded":false,"associatedRows":["NAFS with RVN ( ours )","PMA [ 7 ]","g+l"],"associatedColumns":["Top5"],"associatedMergedColumns":[]},{"number":"49.37","isBolded":false,"associatedRows":["CMPM+CMPC [ 26 ]","g"],"associatedColumns":["Top1"],"associatedMergedColumns":[]},{"number":"55.97","isBolded":false,"associatedRows":["NAFS with RVN ( ours )","ViTAA [ 25 ]","g+l"],"associatedColumns":["Top1"],"associatedMergedColumns":[]},{"number":"60.48","isBolded":false,"associatedRows":["CMPM+CMPC [ 26 ]","CMCE [ 12 ]","g","-"],"associatedColumns":["Top10"],"associatedMergedColumns":[]},{"number":"75.00","isBolded":false,"associatedRows":["CMPM+CMPC [ 26 ]","MIA [ 19 ]","g+l"],"associatedColumns":["Top5"],"associatedMergedColumns":[]},{"number":"79.86","isBolded":false,"associatedRows":["NAFS with RVN ( ours )","NAFS ( ours )","m"],"associatedColumns":["Top5"],"associatedMergedColumns":[]},{"number":"19.05","isBolded":false,"associatedRows":["PWM+ATH [ 2 ]","13 ]","g"],"associatedColumns":["Top1"],"associatedMergedColumns":[]},{"number":"86.70","isBolded":false,"associatedRows":["NAFS with RVN ( ours )","NAFS ( ours )","m","-"],"associatedColumns":["Top10"],"associatedMergedColumns":[]},{"number":"61.02","isBolded":false,"associatedRows":["CMPM+CMPC [ 26 ]","PWM+ATH [ 2 ]","g","-"],"associatedColumns":["Top10"],"associatedMergedColumns":[]},{"number":"59.94","isBolded":false,"associatedRows":["NAFS with RVN ( ours )","NAFS ( ours )","m"],"associatedColumns":["Top1"],"associatedMergedColumns":[]},{"number":"53.64","isBolded":false,"associatedRows":["CMPM+CMPC [ 26 ]","13 ]","g","-"],"associatedColumns":["Top10"],"associatedMergedColumns":[]},{"number":"81.19","isBolded":true,"associatedRows":["NAFS with RVN ( ours )","m"],"associatedColumns":["Top5"],"associatedMergedColumns":[]},{"number":"61.50","isBolded":true,"associatedRows":["NAFS with RVN ( ours )","m"],"associatedColumns":["Top1"],"associatedMergedColumns":[]},{"number":"75.84","isBolded":false,"associatedRows":["NAFS with RVN ( ours )","ViTAA [ 25 ]","g+l"],"associatedColumns":["Top5"],"associatedMergedColumns":[]},{"number":"83.52","isBolded":false,"associatedRows":["NAFS with RVN ( ours )","ViTAA [ 25 ]","g+l","-"],"associatedColumns":["Top10"],"associatedMergedColumns":[]},{"number":"75.07","isBolded":false,"associatedRows":["CMPM+CMPC [ 26 ]","Dual Path [ 30 ]","g","-"],"associatedColumns":["Top10"],"associatedMergedColumns":[]}]},{"caption":"13] \ng \n19.05 \n-\n53.64 \nCMCE [12] \ng \n25.94 \n-\n60.48 \nPWM+ATH [2] \ng \n27.14 49.45 61.02 \nDual Path [30] \ng \n44.40 66.26 75.07 \nCMPM+CMPC [26] \ng \n49.37 \n-\n79.27 \nMIA [19] \ng+l \n53.10 75.00 82.90 \nPMA [7] \ng+l \n53.81 73.54 81.23 \nViTAA [25] \ng+l \n55.97 75.84 83.52 \nNAFS(ours) \nm \n59.94 79.86 86.70 \nNAFS with RVN (ours) \nm \n61.50 81.19 87.51 \n\nTable 2. Comparison with the methods using feature representa-\ntions at different scales. Top-1, top-5 and top-10 accuracies (%) \nare reported. \n\n","rows":["Local+Global","Global","Full Scale"],"columns":["Top5","Top10","Top1"],"mergedAllColumns":[],"numberCells":[{"number":"86.70","isBolded":false,"associatedRows":["Full Scale"],"associatedColumns":["Top10"],"associatedMergedColumns":[]},{"number":"84.36","isBolded":false,"associatedRows":["Global"],"associatedColumns":["Top10"],"associatedMergedColumns":[]},{"number":"59.94","isBolded":false,"associatedRows":["Full Scale"],"associatedColumns":["Top1"],"associatedMergedColumns":[]},{"number":"56.90","isBolded":false,"associatedRows":["Local+Global"],"associatedColumns":["Top1"],"associatedMergedColumns":[]},{"number":"77.92","isBolded":false,"associatedRows":["Local+Global"],"associatedColumns":["Top5"],"associatedMergedColumns":[]},{"number":"77.29","isBolded":false,"associatedRows":["Global"],"associatedColumns":["Top5"],"associatedMergedColumns":[]},{"number":"55.47","isBolded":false,"associatedRows":["Global"],"associatedColumns":["Top1"],"associatedMergedColumns":[]},{"number":"84.81","isBolded":false,"associatedRows":["Local+Global"],"associatedColumns":["Top10"],"associatedMergedColumns":[]},{"number":"79.86","isBolded":false,"associatedRows":["Full Scale"],"associatedColumns":["Top5"],"associatedMergedColumns":[]}]},{"caption":"Table 3. Performance Comparison of separate alignment and joint \nalignment. Top-1, top-5 and top-10 accuracies (%) are reported. \n\n","rows":["Separate Alignment","Joint Alignment"],"columns":["Top5","Top10","Top1"],"mergedAllColumns":[],"numberCells":[{"number":"85.43","isBolded":false,"associatedRows":["Separate Alignment"],"associatedColumns":["Top10"],"associatedMergedColumns":[]},{"number":"59.94","isBolded":false,"associatedRows":["Joint Alignment"],"associatedColumns":["Top1"],"associatedMergedColumns":[]},{"number":"78.22","isBolded":false,"associatedRows":["Separate Alignment"],"associatedColumns":["Top5"],"associatedMergedColumns":[]},{"number":"86.70","isBolded":false,"associatedRows":["Joint Alignment"],"associatedColumns":["Top10"],"associatedMergedColumns":[]},{"number":"57.98","isBolded":false,"associatedRows":["Separate Alignment"],"associatedColumns":["Top1"],"associatedMergedColumns":[]},{"number":"79.86","isBolded":false,"associatedRows":["Joint Alignment"],"associatedColumns":["Top5"],"associatedMergedColumns":[]}]},{"caption":"Table 4. Performance comparison of different components in our methods. Top-1, top-5 and top-10 accuracies (%) are reported. \n\n","rows":["×"],"columns":["Top5","Top10","√","Top1"],"mergedAllColumns":["√"],"numberCells":[{"number":"79.86","isBolded":false,"associatedRows":["×","×","×","×"],"associatedColumns":["Top5","√","√"],"associatedMergedColumns":["√"]},{"number":"85.71","isBolded":false,"associatedRows":["×","×","×","×"],"associatedColumns":["Top10"],"associatedMergedColumns":["√"]},{"number":"79.53","isBolded":false,"associatedRows":["×","×","×","×"],"associatedColumns":["Top5","√"],"associatedMergedColumns":["√"]},{"number":"84.36","isBolded":false,"associatedRows":["×","×","×","×"],"associatedColumns":["Top10"],"associatedMergedColumns":[]},{"number":"84.86","isBolded":false,"associatedRows":["×","×","×","×","×"],"associatedColumns":["Top10"],"associatedMergedColumns":[]},{"number":"87.51","isBolded":false,"associatedRows":["×","×","×","×"],"associatedColumns":["Top10","√","√","√"],"associatedMergedColumns":["√"]},{"number":"77.10","isBolded":false,"associatedRows":["×","×","×","×","×"],"associatedColumns":["Top5"],"associatedMergedColumns":[]},{"number":"78.22","isBolded":false,"associatedRows":["×","×","×","×"],"associatedColumns":["Top5"],"associatedMergedColumns":["√"]},{"number":"57.59","isBolded":false,"associatedRows":["×","×","×","×"],"associatedColumns":["Top1"],"associatedMergedColumns":["√"]},{"number":"86.70","isBolded":false,"associatedRows":["×","×","×","×"],"associatedColumns":["Top10","√","√"],"associatedMergedColumns":["√"]},{"number":"86.42","isBolded":false,"associatedRows":["×","×","×","×"],"associatedColumns":["Top10","√"],"associatedMergedColumns":["√"]},{"number":"81.19","isBolded":false,"associatedRows":["×","×","×","×"],"associatedColumns":["Top5","√","√","√"],"associatedMergedColumns":["√"]},{"number":"54.76","isBolded":false,"associatedRows":["×","×","×","×","×"],"associatedColumns":["Top1"],"associatedMergedColumns":[]},{"number":"77.29","isBolded":false,"associatedRows":["×","×","×","×"],"associatedColumns":["Top5"],"associatedMergedColumns":[]},{"number":"59.94","isBolded":false,"associatedRows":["×","×","×","×"],"associatedColumns":["Top1","√","√"],"associatedMergedColumns":["√"]},{"number":"61.50","isBolded":false,"associatedRows":["×","×","×","×"],"associatedColumns":["Top1","√","√","√"],"associatedMergedColumns":["√"]},{"number":"59.63","isBolded":false,"associatedRows":["×","×","×","×"],"associatedColumns":["Top1","√"],"associatedMergedColumns":["√"]},{"number":"55.47","isBolded":false,"associatedRows":["×","×","×","×"],"associatedColumns":["Top1"],"associatedMergedColumns":[]}]}]