[{"caption":"Table 1: Dataset description with the number of \nsentences(#S.) and number of aspect terms(#A.) \n\n","rows":[],"columns":[],"mergedAllColumns":[],"numberCells":[]},{"caption":"Table 2: Comparison results in F 1 score: numbers \nin the third group are averaged scores of 5 runs. * \nindicates the result is statistical significant at the \nlevel of 0.05. \n\n","rows":["CMLA","LSTM","WDEmb","DE - LSTM","-","Domain - CNN","MaxPool - DE - CNN","IHS RD","NLANGP","RNCRF","MIN","DE - CNN","BiLSTM - CNN - CRF","DE - CNN - CRF","CRF","DE - Google - CNN","DE - OOD - CNN","GloVe - CNN"],"columns":["Laptop","Restaurant"],"mergedAllColumns":["-"],"numberCells":[{"number":"78.8","isBolded":false,"associatedRows":["DE - Google - CNN"],"associatedColumns":["Laptop"],"associatedMergedColumns":["-"]},{"number":"74.55","isBolded":false,"associatedRows":["IHS RD"],"associatedColumns":["Laptop"],"associatedMergedColumns":[]},{"number":"71.75","isBolded":false,"associatedRows":["Domain - CNN"],"associatedColumns":["Restaurant"],"associatedMergedColumns":["-"]},{"number":"77.45","isBolded":false,"associatedRows":["MaxPool - DE - CNN"],"associatedColumns":["Laptop"],"associatedMergedColumns":["-"]},{"number":"77.80","isBolded":false,"associatedRows":["CMLA"],"associatedColumns":["Laptop"],"associatedMergedColumns":["-"]},{"number":"77.8","isBolded":false,"associatedRows":["BiLSTM - CNN - CRF"],"associatedColumns":["Laptop"],"associatedMergedColumns":["-"]},{"number":"72.1","isBolded":false,"associatedRows":["DE - Google - CNN"],"associatedColumns":["Restaurant"],"associatedMergedColumns":["-"]},{"number":"80.21","isBolded":false,"associatedRows":["DE - OOD - CNN"],"associatedColumns":["Laptop"],"associatedMergedColumns":["-"]},{"number":"69.56","isBolded":false,"associatedRows":["CRF"],"associatedColumns":["Restaurant"],"associatedMergedColumns":[]},{"number":"74.37*","isBolded":true,"associatedRows":["DE - CNN"],"associatedColumns":["Restaurant"],"associatedMergedColumns":["-"]},{"number":"78.73","isBolded":false,"associatedRows":["DE - LSTM"],"associatedColumns":["Laptop"],"associatedMergedColumns":["-"]},{"number":"71.26","isBolded":false,"associatedRows":["LSTM"],"associatedColumns":["Restaurant"],"associatedMergedColumns":["-"]},{"number":"72.34","isBolded":false,"associatedRows":["NLANGP","-"],"associatedColumns":["Restaurant"],"associatedMergedColumns":["-"]},{"number":"80.8","isBolded":false,"associatedRows":["DE - CNN - CRF"],"associatedColumns":["Laptop"],"associatedMergedColumns":["-"]},{"number":"81.59*","isBolded":true,"associatedRows":["DE - CNN"],"associatedColumns":["Laptop"],"associatedMergedColumns":["-"]},{"number":"73.44","isBolded":false,"associatedRows":["MIN"],"associatedColumns":["Restaurant"],"associatedMergedColumns":["-"]},{"number":"72.08","isBolded":false,"associatedRows":["GloVe - CNN"],"associatedColumns":["Restaurant"],"associatedMergedColumns":["-"]},{"number":"74.1","isBolded":false,"associatedRows":["DE - CNN - CRF"],"associatedColumns":["Restaurant"],"associatedMergedColumns":["-"]},{"number":"77.58","isBolded":false,"associatedRows":["MIN"],"associatedColumns":["Laptop"],"associatedMergedColumns":["-"]},{"number":"74.01","isBolded":false,"associatedRows":["CRF"],"associatedColumns":["Laptop"],"associatedMergedColumns":[]},{"number":"71.12","isBolded":false,"associatedRows":["MaxPool - DE - CNN"],"associatedColumns":["Restaurant"],"associatedMergedColumns":["-"]},{"number":"75.25","isBolded":false,"associatedRows":["LSTM"],"associatedColumns":["Laptop"],"associatedMergedColumns":["-"]},{"number":"74.2","isBolded":false,"associatedRows":["DE - OOD - CNN"],"associatedColumns":["Restaurant"],"associatedMergedColumns":["-"]},{"number":"72.94","isBolded":false,"associatedRows":["DE - LSTM"],"associatedColumns":["Restaurant"],"associatedMergedColumns":["-"]},{"number":"72.5","isBolded":false,"associatedRows":["BiLSTM - CNN - CRF"],"associatedColumns":["Restaurant"],"associatedMergedColumns":["-"]},{"number":"78.12","isBolded":false,"associatedRows":["Domain - CNN"],"associatedColumns":["Laptop"],"associatedMergedColumns":["-"]},{"number":"78.42","isBolded":false,"associatedRows":["RNCRF"],"associatedColumns":["Laptop"],"associatedMergedColumns":["-"]},{"number":"77.67","isBolded":false,"associatedRows":["GloVe - CNN"],"associatedColumns":["Laptop"],"associatedMergedColumns":["-"]},{"number":"75.16","isBolded":false,"associatedRows":["WDEmb"],"associatedColumns":["Laptop"],"associatedMergedColumns":["-"]}]}]