[{"caption":"Table 1. Test accuracy (%) on eight text classification datasets. The methods with * indicate using fine-tuning, -means the results are not reported on their \npapers. The best results are bold. \n\n","rows":["DPCNN * [ 12 ]","BERT - Large * [ 24 ]","ULMFiT * [ 10 ]","Ours","BERT - FiT * [ 23 ]","Region Emb . [ 18 ]","-","XLNet * [ 25 ]"],"columns":["DBP","Sogou","AG","Yah . A","Yelp . F","Amz . P","Amz . F","Yelp . P","-"],"mergedAllColumns":[],"numberCells":[{"number":"70.02","isBolded":false,"associatedRows":["ULMFiT * [ 10 ]","-","-"],"associatedColumns":["Yelp . F"],"associatedMergedColumns":[]},{"number":"93.13","isBolded":false,"associatedRows":["DPCNN * [ 12 ]"],"associatedColumns":["AG"],"associatedMergedColumns":[]},{"number":"77.58","isBolded":true,"associatedRows":["BERT - FiT * [ 23 ]"],"associatedColumns":["Yah . A","-"],"associatedMergedColumns":[]},{"number":"69.42","isBolded":false,"associatedRows":["DPCNN * [ 12 ]","-","-"],"associatedColumns":["Yelp . F"],"associatedMergedColumns":[]},{"number":"60.90","isBolded":false,"associatedRows":["Region Emb . [ 18 ]","-","-"],"associatedColumns":["Amz . F","-"],"associatedMergedColumns":[]},{"number":"76.10","isBolded":false,"associatedRows":["DPCNN * [ 12 ]"],"associatedColumns":["Yah . A"],"associatedMergedColumns":[]},{"number":"97.84","isBolded":false,"associatedRows":["ULMFiT * [ 10 ]","-","-"],"associatedColumns":["Yelp . P"],"associatedMergedColumns":[]},{"number":"99.20","isBolded":false,"associatedRows":["ULMFiT * [ 10 ]"],"associatedColumns":["DBP"],"associatedMergedColumns":[]},{"number":"73.70","isBolded":false,"associatedRows":["Region Emb . [ 18 ]"],"associatedColumns":["Yah . A","-"],"associatedMergedColumns":[]},{"number":"65.83","isBolded":false,"associatedRows":["BERT - Large * [ 24 ]","-","-","-"],"associatedColumns":["Amz . F","-","-"],"associatedMergedColumns":[]},{"number":"97.60","isBolded":true,"associatedRows":["Region Emb . [ 18 ]","-"],"associatedColumns":["Sogou","-"],"associatedMergedColumns":[]},{"number":"70.68","isBolded":false,"associatedRows":["BERT - Large * [ 24 ]","-","-","-"],"associatedColumns":["Yelp . F","-","-"],"associatedMergedColumns":[]},{"number":"99.12","isBolded":false,"associatedRows":["DPCNN * [ 12 ]"],"associatedColumns":["DBP"],"associatedMergedColumns":[]},{"number":"65.19","isBolded":false,"associatedRows":["DPCNN * [ 12 ]","-","-"],"associatedColumns":["Amz . F"],"associatedMergedColumns":[]},{"number":"94.75","isBolded":false,"associatedRows":["BERT - FiT * [ 23 ]"],"associatedColumns":["AG","-"],"associatedMergedColumns":[]},{"number":"98.11","isBolded":false,"associatedRows":["BERT - Large * [ 24 ]","-","-","-"],"associatedColumns":["Yelp . P","-","-"],"associatedMergedColumns":[]},{"number":"94.96","isBolded":false,"associatedRows":["Ours","-","-"],"associatedColumns":["Amz . P","-","-"],"associatedMergedColumns":[]},{"number":"96.68","isBolded":false,"associatedRows":["DPCNN * [ 12 ]","-","-"],"associatedColumns":["Amz . P"],"associatedMergedColumns":[]},{"number":"92.80","isBolded":false,"associatedRows":["Region Emb . [ 18 ]"],"associatedColumns":["AG","-"],"associatedMergedColumns":[]},{"number":"98.72","isBolded":false,"associatedRows":["Ours"],"associatedColumns":["DBP","-","-"],"associatedMergedColumns":[]},{"number":"99.40","isBolded":true,"associatedRows":["XLNet * [ 25 ]"],"associatedColumns":["DBP","-","-"],"associatedMergedColumns":[]},{"number":"96.40","isBolded":false,"associatedRows":["Region Emb . [ 18 ]","-","-"],"associatedColumns":["Yelp . P","-"],"associatedMergedColumns":[]},{"number":"99.29","isBolded":false,"associatedRows":["BERT - FiT * [ 23 ]"],"associatedColumns":["DBP","-"],"associatedMergedColumns":[]},{"number":"64.90","isBolded":false,"associatedRows":["Region Emb . [ 18 ]","-","-"],"associatedColumns":["Yelp . F","-"],"associatedMergedColumns":[]},{"number":"69.94","isBolded":false,"associatedRows":["BERT - FiT * [ 23 ]","-","-"],"associatedColumns":["Yelp . F","-"],"associatedMergedColumns":[]},{"number":"60.95","isBolded":false,"associatedRows":["Ours","-","-"],"associatedColumns":["Amz . F","-","-"],"associatedMergedColumns":[]},{"number":"97.72","isBolded":false,"associatedRows":["BERT - FiT * [ 23 ]","-","-"],"associatedColumns":["Yelp . P","-"],"associatedMergedColumns":[]},{"number":"65.85","isBolded":false,"associatedRows":["Ours","-","-"],"associatedColumns":["Yelp . F","-","-"],"associatedMergedColumns":[]},{"number":"97.37","isBolded":false,"associatedRows":["BERT - Large * [ 24 ]","-","-","-"],"associatedColumns":["Amz . P","-","-"],"associatedMergedColumns":[]},{"number":"73.85","isBolded":false,"associatedRows":["Ours"],"associatedColumns":["Yah . A","-","-"],"associatedMergedColumns":[]},{"number":"97.57","isBolded":false,"associatedRows":["BERT - FiT * [ 23 ]","-"],"associatedColumns":["Sogou","-"],"associatedMergedColumns":[]},{"number":"95.55","isBolded":true,"associatedRows":["XLNet * [ 25 ]"],"associatedColumns":["AG","-","-"],"associatedMergedColumns":[]},{"number":"96.52","isBolded":false,"associatedRows":["DPCNN * [ 12 ]","-"],"associatedColumns":["Sogou"],"associatedMergedColumns":[]},{"number":"97.25","isBolded":false,"associatedRows":["Ours","-"],"associatedColumns":["Sogou","-","-"],"associatedMergedColumns":[]},{"number":"98.90","isBolded":false,"associatedRows":["Region Emb . [ 18 ]"],"associatedColumns":["DBP","-"],"associatedMergedColumns":[]},{"number":"99.36","isBolded":false,"associatedRows":["BERT - Large * [ 24 ]","-"],"associatedColumns":["DBP","-","-"],"associatedMergedColumns":[]},{"number":"97.36","isBolded":false,"associatedRows":["DPCNN * [ 12 ]","-","-"],"associatedColumns":["Yelp . P"],"associatedMergedColumns":[]},{"number":"92.39","isBolded":false,"associatedRows":["Ours"],"associatedColumns":["AG","-","-"],"associatedMergedColumns":[]},{"number":"72.95","isBolded":true,"associatedRows":["XLNet * [ 25 ]","-","-"],"associatedColumns":["Yelp . F","-","-"],"associatedMergedColumns":[]},{"number":"68.33","isBolded":true,"associatedRows":["XLNet * [ 25 ]","-","-"],"associatedColumns":["Amz . F","-","-"],"associatedMergedColumns":[]},{"number":"96.48","isBolded":false,"associatedRows":["Ours","-","-"],"associatedColumns":["Yelp . P","-","-"],"associatedMergedColumns":[]},{"number":"95.10","isBolded":false,"associatedRows":["Region Emb . [ 18 ]","-","-"],"associatedColumns":["Amz . P","-"],"associatedMergedColumns":[]},{"number":"98.63","isBolded":true,"associatedRows":["XLNet * [ 25 ]","-","-"],"associatedColumns":["Yelp . P","-","-"],"associatedMergedColumns":[]},{"number":"97.89","isBolded":true,"associatedRows":["XLNet * [ 25 ]","-","-"],"associatedColumns":["Amz . P","-","-"],"associatedMergedColumns":[]},{"number":"94.99","isBolded":false,"associatedRows":["ULMFiT * [ 10 ]"],"associatedColumns":["AG"],"associatedMergedColumns":[]}]},{"caption":"Method \nAG \nDBP Yah.A Sogou Yelp.P Yelp.F Amz.P Amz.F \n\nDPCNN* [12] \n93.13 99.12 76.10 96.52 \n97.36 \n69.42 \n96.68 \n65.19 \nULMFiT* [10] \n94.99 99.20 \n-\n-\n97.84 \n70.02 \n-\n-\nRegion Emb. [18] \n92.80 98.90 73.70 97.60 \n96.40 \n64.90 \n95.10 \n60.90 \nBERT-FiT* [23] \n94.75 99.29 77.58 97.57 \n97.72 \n69.94 \n-\n-\nBERT-Large* [24] \n-\n99.36 \n-\n-\n98.11 \n70.68 \n97.37 \n65.83 \nXLNet* [25] \n95.55 99.40 \n-\n-\n98.63 \n72.95 \n97.89 \n68.33 \n\nOurs \n92.39 98.72 73.85 97.25 \n96.48 \n65.85 \n94.96 \n60.95 \n\nTable 2. The number of model parameters (M) on eight text classification datasets. The minimum number of model parameters are bold. \n\n","rows":["1 , 059 . 23","Ours","1 , 082 . 84","BERT - Large [ 24 ]","XLNet [ 25 ]","Region Emb . [ 18 ]","DPCNN [ 12 ]","ULMFiT [ 10 ]","BERT - FiT [ 23 ]"],"columns":["DBP","Sogou","AG","Yah . A","Yelp . F","Amz . P","Amz . F","Yelp . P"],"mergedAllColumns":[],"numberCells":[{"number":"672.47","isBolded":false,"associatedRows":["BERT - FiT [ 23 ]","1 , 059 . 23"],"associatedColumns":["Amz . F"],"associatedMergedColumns":[]},{"number":"667.11","isBolded":false,"associatedRows":["BERT - Large [ 24 ]"],"associatedColumns":["DBP"],"associatedMergedColumns":[]},{"number":"127.26","isBolded":false,"associatedRows":["Region Emb . [ 18 ]"],"associatedColumns":["Yelp . F"],"associatedMergedColumns":[]},{"number":"370.61","isBolded":false,"associatedRows":["Region Emb . [ 18 ]"],"associatedColumns":["Yah . A"],"associatedMergedColumns":[]},{"number":"59.84","isBolded":false,"associatedRows":["DPCNN [ 12 ]"],"associatedColumns":["Amz . P"],"associatedMergedColumns":[]},{"number":"4.24","isBolded":false,"associatedRows":["DPCNN [ 12 ]"],"associatedColumns":["AG"],"associatedMergedColumns":[]},{"number":"233.33","isBolded":false,"associatedRows":["Region Emb . [ 18 ]"],"associatedColumns":["DBP"],"associatedMergedColumns":[]},{"number":"118.07","isBolded":false,"associatedRows":["Region Emb . [ 18 ]"],"associatedColumns":["Yelp . P"],"associatedMergedColumns":[]},{"number":"214.55","isBolded":false,"associatedRows":["BERT - Large [ 24 ]"],"associatedColumns":["Sogou"],"associatedMergedColumns":[]},{"number":"169.65","isBolded":false,"associatedRows":["BERT - Large [ 24 ]"],"associatedColumns":["AG"],"associatedMergedColumns":[]},{"number":"197.21","isBolded":false,"associatedRows":["BERT - FiT [ 23 ]"],"associatedColumns":["Yelp . F"],"associatedMergedColumns":[]},{"number":"26.80","isBolded":true,"associatedRows":["Ours"],"associatedColumns":["DBP"],"associatedMergedColumns":[]},{"number":"184.77","isBolded":false,"associatedRows":["BERT - FiT [ 23 ]"],"associatedColumns":["Yelp . P"],"associatedMergedColumns":[]},{"number":"30.45","isBolded":false,"associatedRows":["ULMFiT [ 10 ]"],"associatedColumns":["Yelp . F"],"associatedMergedColumns":[]},{"number":"9.14","isBolded":true,"associatedRows":["Ours"],"associatedColumns":["Yelp . F"],"associatedMergedColumns":[]},{"number":"29.41","isBolded":false,"associatedRows":["ULMFiT [ 10 ]"],"associatedColumns":["Yelp . P"],"associatedMergedColumns":[]},{"number":"14.13","isBolded":false,"associatedRows":["DPCNN [ 12 ]"],"associatedColumns":["Yelp . F"],"associatedMergedColumns":[]},{"number":"895.95","isBolded":false,"associatedRows":["BERT - Large [ 24 ]"],"associatedColumns":["Yah . A"],"associatedMergedColumns":[]},{"number":"311.22","isBolded":false,"associatedRows":["BERT - Large [ 24 ]"],"associatedColumns":["Yelp . P"],"associatedMergedColumns":[]},{"number":"690.72","isBolded":false,"associatedRows":["XLNet [ 25 ]"],"associatedColumns":["DBP"],"associatedMergedColumns":[]},{"number":"745.78","isBolded":false,"associatedRows":["BERT - FiT [ 23 ]"],"associatedColumns":["Amz . P"],"associatedMergedColumns":[]},{"number":"451.69","isBolded":false,"associatedRows":["BERT - FiT [ 23 ]"],"associatedColumns":["DBP"],"associatedMergedColumns":[]},{"number":"961.49","isBolded":false,"associatedRows":["BERT - Large [ 24 ]","1 , 059 . 23"],"associatedColumns":["Amz . F"],"associatedMergedColumns":[]},{"number":"2.46","isBolded":true,"associatedRows":["Ours"],"associatedColumns":["AG"],"associatedMergedColumns":[]},{"number":"101.78","isBolded":false,"associatedRows":["Region Emb . [ 18 ]"],"associatedColumns":["Sogou"],"associatedMergedColumns":[]},{"number":"65.96","isBolded":false,"associatedRows":["ULMFiT [ 10 ]"],"associatedColumns":["Yah . A"],"associatedMergedColumns":[]},{"number":"43.81","isBolded":false,"associatedRows":["Region Emb . [ 18 ]"],"associatedColumns":["AG"],"associatedMergedColumns":[]},{"number":"13.09","isBolded":false,"associatedRows":["DPCNN [ 12 ]"],"associatedColumns":["Yelp . P"],"associatedMergedColumns":[]},{"number":"20.56","isBolded":false,"associatedRows":["ULMFiT [ 10 ]"],"associatedColumns":["AG"],"associatedMergedColumns":[]},{"number":"238.16","isBolded":false,"associatedRows":["XLNet [ 25 ]"],"associatedColumns":["Sogou"],"associatedMergedColumns":[]},{"number":"327.80","isBolded":false,"associatedRows":["BERT - Large [ 24 ]"],"associatedColumns":["Yelp . F"],"associatedMergedColumns":[]},{"number":"8.48","isBolded":true,"associatedRows":["Ours"],"associatedColumns":["Yelp . P"],"associatedMergedColumns":[]},{"number":"351.42","isBolded":false,"associatedRows":["XLNet [ 25 ]"],"associatedColumns":["Yelp . F"],"associatedMergedColumns":[]},{"number":"623.32","isBolded":false,"associatedRows":["BERT - FiT [ 23 ]"],"associatedColumns":["Yah . A"],"associatedMergedColumns":[]},{"number":"70.05","isBolded":false,"associatedRows":["ULMFiT [ 10 ]","1 , 059 . 23"],"associatedColumns":["Amz . F"],"associatedMergedColumns":[]},{"number":"112.27","isBolded":false,"associatedRows":["BERT - FiT [ 23 ]"],"associatedColumns":["Sogou"],"associatedMergedColumns":[]},{"number":"403.85","isBolded":false,"associatedRows":["Region Emb . [ 18 ]"],"associatedColumns":["Amz . P"],"associatedMergedColumns":[]},{"number":"49.64","isBolded":false,"associatedRows":["DPCNN [ 12 ]"],"associatedColumns":["Yah . A"],"associatedMergedColumns":[]},{"number":"334.83","isBolded":false,"associatedRows":["XLNet [ 25 ]"],"associatedColumns":["Yelp . P"],"associatedMergedColumns":[]},{"number":"7.05","isBolded":false,"associatedRows":["DPCNN [ 12 ]"],"associatedColumns":["Sogou"],"associatedMergedColumns":[]},{"number":"4.71","isBolded":true,"associatedRows":["Ours"],"associatedColumns":["Sogou"],"associatedMergedColumns":[]},{"number":"985.10","isBolded":false,"associatedRows":["XLNet [ 25 ]","1 , 082 . 84"],"associatedColumns":["Amz . F"],"associatedMergedColumns":[]},{"number":"45.15","isBolded":true,"associatedRows":["Ours"],"associatedColumns":["Amz . P"],"associatedMergedColumns":[]},{"number":"35.34","isBolded":false,"associatedRows":["DPCNN [ 12 ]"],"associatedColumns":["DBP"],"associatedMergedColumns":[]},{"number":"76.16","isBolded":false,"associatedRows":["ULMFiT [ 10 ]"],"associatedColumns":["Amz . P"],"associatedMergedColumns":[]},{"number":"364.86","isBolded":false,"associatedRows":["Region Emb . [ 18 ]","1 , 059 . 23"],"associatedColumns":["Amz . F"],"associatedMergedColumns":[]},{"number":"919.57","isBolded":false,"associatedRows":["XLNet [ 25 ]"],"associatedColumns":["Yah . A"],"associatedMergedColumns":[]},{"number":"23.37","isBolded":false,"associatedRows":["ULMFiT [ 10 ]"],"associatedColumns":["Sogou"],"associatedMergedColumns":[]},{"number":"40.58","isBolded":true,"associatedRows":["Ours","1 , 082 . 84"],"associatedColumns":["Amz . F"],"associatedMergedColumns":[]},{"number":"53.73","isBolded":false,"associatedRows":["DPCNN [ 12 ]","1 , 059 . 23"],"associatedColumns":["Amz . F"],"associatedMergedColumns":[]},{"number":"51.65","isBolded":false,"associatedRows":["ULMFiT [ 10 ]"],"associatedColumns":["DBP"],"associatedMergedColumns":[]},{"number":"78.59","isBolded":false,"associatedRows":["BERT - FiT [ 23 ]"],"associatedColumns":["AG"],"associatedMergedColumns":[]},{"number":"193.26","isBolded":false,"associatedRows":["XLNet [ 25 ]"],"associatedColumns":["AG"],"associatedMergedColumns":[]},{"number":"37.52","isBolded":true,"associatedRows":["Ours"],"associatedColumns":["Yah . A"],"associatedMergedColumns":[]}]},{"caption":"Method \nAG \nDBP \nYah.A Sogou Yelp.P Yelp.F \nAmz.P \nAmz.F \n\nDPCNN [12] \n4.24 \n35.34 \n49.64 \n7.05 \n13.09 \n14.13 \n59.84 \n53.73 \nULMFiT [10] \n20.56 \n51.65 \n65.96 \n23.37 \n29.41 \n30.45 \n76.16 \n70.05 \nRegion Emb. [18] 43.81 233.33 370.61 101.78 118.07 127.26 \n403.85 \n364.86 \nBERT-FiT [23] \n78.59 451.69 623.32 112.27 184.77 197.21 \n745.78 \n672.47 \nBERT-Large [24] 169.65 667.11 895.95 214.55 311.22 327.80 1,059.23 961.49 \nXLNet [25] \n193.26 690.72 919.57 238.16 334.83 351.42 1,082.84 985.10 \n\nOurs \n2.46 \n26.80 \n37.52 \n4.71 \n8.48 \n9.14 \n45.15 \n40.58 \n\nTable 3. Statistics of the benchmark text classification datasets. \n\n","rows":["1 , 059 . 23","Ours","1 , 082 . 84","BERT - Large [ 24 ]","4","XLNet [ 25 ]","Region Emb . [ 18 ]","AG","120k","DPCNN [ 12 ]","ULMFiT [ 10 ]","BERT - FiT [ 23 ]"],"columns":["DBP","Sogou","AG","Yah . A","Yelp . F","Amz . P","Amz . F","# Test","Yelp . P"],"mergedAllColumns":["Table 3 . Statistics of the benchmark text classification datasets ."],"numberCells":[{"number":"76.16","isBolded":false,"associatedRows":["ULMFiT [ 10 ]"],"associatedColumns":["Amz . P"],"associatedMergedColumns":[]},{"number":"70.05","isBolded":false,"associatedRows":["ULMFiT [ 10 ]","1 , 059 . 23"],"associatedColumns":["Amz . F"],"associatedMergedColumns":[]},{"number":"667.11","isBolded":false,"associatedRows":["BERT - Large [ 24 ]"],"associatedColumns":["DBP"],"associatedMergedColumns":[]},{"number":"14.13","isBolded":false,"associatedRows":["DPCNN [ 12 ]"],"associatedColumns":["Yelp . F"],"associatedMergedColumns":[]},{"number":"403.85","isBolded":false,"associatedRows":["Region Emb . [ 18 ]"],"associatedColumns":["Amz . P"],"associatedMergedColumns":[]},{"number":"451.69","isBolded":false,"associatedRows":["BERT - FiT [ 23 ]"],"associatedColumns":["DBP"],"associatedMergedColumns":[]},{"number":"351.42","isBolded":false,"associatedRows":["XLNet [ 25 ]"],"associatedColumns":["Yelp . F"],"associatedMergedColumns":[]},{"number":"65.96","isBolded":false,"associatedRows":["ULMFiT [ 10 ]"],"associatedColumns":["Yah . A"],"associatedMergedColumns":[]},{"number":"2.46","isBolded":true,"associatedRows":["Ours"],"associatedColumns":["AG"],"associatedMergedColumns":[]},{"number":"127.26","isBolded":false,"associatedRows":["Region Emb . [ 18 ]"],"associatedColumns":["Yelp . F"],"associatedMergedColumns":[]},{"number":"985.10","isBolded":false,"associatedRows":["XLNet [ 25 ]","1 , 082 . 84"],"associatedColumns":["Amz . F"],"associatedMergedColumns":[]},{"number":"30.45","isBolded":false,"associatedRows":["ULMFiT [ 10 ]"],"associatedColumns":["Yelp . F"],"associatedMergedColumns":[]},{"number":"49.64","isBolded":false,"associatedRows":["DPCNN [ 12 ]"],"associatedColumns":["Yah . A"],"associatedMergedColumns":[]},{"number":"78.59","isBolded":false,"associatedRows":["BERT - FiT [ 23 ]"],"associatedColumns":["AG"],"associatedMergedColumns":[]},{"number":"311.22","isBolded":false,"associatedRows":["BERT - Large [ 24 ]"],"associatedColumns":["Yelp . P"],"associatedMergedColumns":[]},{"number":"623.32","isBolded":false,"associatedRows":["BERT - FiT [ 23 ]"],"associatedColumns":["Yah . A"],"associatedMergedColumns":[]},{"number":"745.78","isBolded":false,"associatedRows":["BERT - FiT [ 23 ]"],"associatedColumns":["Amz . P"],"associatedMergedColumns":[]},{"number":"895.95","isBolded":false,"associatedRows":["BERT - Large [ 24 ]"],"associatedColumns":["Yah . A"],"associatedMergedColumns":[]},{"number":"20.56","isBolded":false,"associatedRows":["ULMFiT [ 10 ]"],"associatedColumns":["AG"],"associatedMergedColumns":[]},{"number":"43.81","isBolded":false,"associatedRows":["Region Emb . [ 18 ]"],"associatedColumns":["AG"],"associatedMergedColumns":[]},{"number":"233.33","isBolded":false,"associatedRows":["Region Emb . [ 18 ]"],"associatedColumns":["DBP"],"associatedMergedColumns":[]},{"number":"7.05","isBolded":false,"associatedRows":["DPCNN [ 12 ]"],"associatedColumns":["Sogou"],"associatedMergedColumns":[]},{"number":"193.26","isBolded":false,"associatedRows":["XLNet [ 25 ]"],"associatedColumns":["AG"],"associatedMergedColumns":[]},{"number":"53.73","isBolded":false,"associatedRows":["DPCNN [ 12 ]","1 , 059 . 23"],"associatedColumns":["Amz . F"],"associatedMergedColumns":[]},{"number":"334.83","isBolded":false,"associatedRows":["XLNet [ 25 ]"],"associatedColumns":["Yelp . P"],"associatedMergedColumns":[]},{"number":"45.15","isBolded":true,"associatedRows":["Ours"],"associatedColumns":["Amz . P"],"associatedMergedColumns":[]},{"number":"40.58","isBolded":true,"associatedRows":["Ours","1 , 082 . 84"],"associatedColumns":["Amz . F"],"associatedMergedColumns":[]},{"number":"169.65","isBolded":false,"associatedRows":["BERT - Large [ 24 ]"],"associatedColumns":["AG"],"associatedMergedColumns":[]},{"number":"51.65","isBolded":false,"associatedRows":["ULMFiT [ 10 ]"],"associatedColumns":["DBP"],"associatedMergedColumns":[]},{"number":"919.57","isBolded":false,"associatedRows":["XLNet [ 25 ]"],"associatedColumns":["Yah . A"],"associatedMergedColumns":[]},{"number":"4.71","isBolded":true,"associatedRows":["Ours"],"associatedColumns":["Sogou"],"associatedMergedColumns":[]},{"number":"13.09","isBolded":false,"associatedRows":["DPCNN [ 12 ]"],"associatedColumns":["Yelp . P"],"associatedMergedColumns":[]},{"number":"118.07","isBolded":false,"associatedRows":["Region Emb . [ 18 ]"],"associatedColumns":["Yelp . P"],"associatedMergedColumns":[]},{"number":"672.47","isBolded":false,"associatedRows":["BERT - FiT [ 23 ]","1 , 059 . 23"],"associatedColumns":["Amz . F"],"associatedMergedColumns":[]},{"number":"690.72","isBolded":false,"associatedRows":["XLNet [ 25 ]"],"associatedColumns":["DBP"],"associatedMergedColumns":[]},{"number":"8.48","isBolded":true,"associatedRows":["Ours"],"associatedColumns":["Yelp . P"],"associatedMergedColumns":[]},{"number":"370.61","isBolded":false,"associatedRows":["Region Emb . [ 18 ]"],"associatedColumns":["Yah . A"],"associatedMergedColumns":[]},{"number":"101.78","isBolded":false,"associatedRows":["Region Emb . [ 18 ]"],"associatedColumns":["Sogou"],"associatedMergedColumns":[]},{"number":"197.21","isBolded":false,"associatedRows":["BERT - FiT [ 23 ]"],"associatedColumns":["Yelp . F"],"associatedMergedColumns":[]},{"number":"9.14","isBolded":true,"associatedRows":["Ours"],"associatedColumns":["Yelp . F"],"associatedMergedColumns":[]},{"number":"35.34","isBolded":false,"associatedRows":["DPCNN [ 12 ]"],"associatedColumns":["DBP"],"associatedMergedColumns":[]},{"number":"29.41","isBolded":false,"associatedRows":["ULMFiT [ 10 ]"],"associatedColumns":["Yelp . P"],"associatedMergedColumns":[]},{"number":"238.16","isBolded":false,"associatedRows":["XLNet [ 25 ]"],"associatedColumns":["Sogou"],"associatedMergedColumns":[]},{"number":"7.6k","isBolded":false,"associatedRows":["AG","4","120k"],"associatedColumns":["AG","# Test"],"associatedMergedColumns":["Table 3 . Statistics of the benchmark text classification datasets ."]},{"number":"37.52","isBolded":true,"associatedRows":["Ours"],"associatedColumns":["Yah . A"],"associatedMergedColumns":[]},{"number":"327.80","isBolded":false,"associatedRows":["BERT - Large [ 24 ]"],"associatedColumns":["Yelp . F"],"associatedMergedColumns":[]},{"number":"112.27","isBolded":false,"associatedRows":["BERT - FiT [ 23 ]"],"associatedColumns":["Sogou"],"associatedMergedColumns":[]},{"number":"4.24","isBolded":false,"associatedRows":["DPCNN [ 12 ]"],"associatedColumns":["AG"],"associatedMergedColumns":[]},{"number":"26.80","isBolded":true,"associatedRows":["Ours"],"associatedColumns":["DBP"],"associatedMergedColumns":[]},{"number":"214.55","isBolded":false,"associatedRows":["BERT - Large [ 24 ]"],"associatedColumns":["Sogou"],"associatedMergedColumns":[]},{"number":"961.49","isBolded":false,"associatedRows":["BERT - Large [ 24 ]","1 , 059 . 23"],"associatedColumns":["Amz . F"],"associatedMergedColumns":[]},{"number":"184.77","isBolded":false,"associatedRows":["BERT - FiT [ 23 ]"],"associatedColumns":["Yelp . P"],"associatedMergedColumns":[]},{"number":"59.84","isBolded":false,"associatedRows":["DPCNN [ 12 ]"],"associatedColumns":["Amz . P"],"associatedMergedColumns":[]},{"number":"364.86","isBolded":false,"associatedRows":["Region Emb . [ 18 ]","1 , 059 . 23"],"associatedColumns":["Amz . F"],"associatedMergedColumns":[]},{"number":"23.37","isBolded":false,"associatedRows":["ULMFiT [ 10 ]"],"associatedColumns":["Sogou"],"associatedMergedColumns":[]}]},{"caption":"Table 4. Ablation studies for the three loss functions: cross entropy loss \n(L c ), focal loss (L f ) and margin loss (L m ) on AG\u0027s News dataset. The best \ntest accuracy (%) are bold. \n\n","rows":[],"columns":["m"],"mergedAllColumns":[],"numberCells":[{"number":"92.13","isBolded":false,"associatedRows":[],"associatedColumns":["m"],"associatedMergedColumns":[]},{"number":"92.09","isBolded":false,"associatedRows":[],"associatedColumns":["m"],"associatedMergedColumns":[]},{"number":"92.37","isBolded":false,"associatedRows":[],"associatedColumns":["m"],"associatedMergedColumns":[]},{"number":"91.95","isBolded":false,"associatedRows":[],"associatedColumns":["m"],"associatedMergedColumns":[]},{"number":"92.64","isBolded":true,"associatedRows":[],"associatedColumns":["m"],"associatedMergedColumns":[]},{"number":"92.38","isBolded":false,"associatedRows":[],"associatedColumns":["m"],"associatedMergedColumns":[]},{"number":"92.05","isBolded":false,"associatedRows":[],"associatedColumns":["m"],"associatedMergedColumns":[]}]},{"caption":"m \n\n92.05 92.13 92.37 \n92.09 \n91.95 \n92.64 \n92.38 \n\nTable 5. Ablation studies for routing algorithms on eight text classification \ndatasets. The best test accuracy (%) are bold. \n\n","rows":["Dynamic","K - means"],"columns":["DBP","Sogou","AG","Yah . A","Yelp . F","Amz . P","Amz . F","Yelp . P"],"mergedAllColumns":[],"numberCells":[{"number":"94.87","isBolded":false,"associatedRows":["Dynamic"],"associatedColumns":["Amz . P"],"associatedMergedColumns":[]},{"number":"96.48","isBolded":true,"associatedRows":["K - means"],"associatedColumns":["Yelp . P"],"associatedMergedColumns":[]},{"number":"65.85","isBolded":true,"associatedRows":["K - means"],"associatedColumns":["Yelp . F"],"associatedMergedColumns":[]},{"number":"94.96","isBolded":true,"associatedRows":["K - means"],"associatedColumns":["Amz . P"],"associatedMergedColumns":[]},{"number":"60.95","isBolded":true,"associatedRows":["K - means"],"associatedColumns":["Amz . F"],"associatedMergedColumns":[]},{"number":"92.14","isBolded":false,"associatedRows":["Dynamic"],"associatedColumns":["AG"],"associatedMergedColumns":[]},{"number":"98.70","isBolded":false,"associatedRows":["Dynamic"],"associatedColumns":["DBP"],"associatedMergedColumns":[]},{"number":"73.85","isBolded":false,"associatedRows":["K - means"],"associatedColumns":["Yah . A"],"associatedMergedColumns":[]},{"number":"97.25","isBolded":true,"associatedRows":["K - means"],"associatedColumns":["Sogou"],"associatedMergedColumns":[]},{"number":"73.98","isBolded":true,"associatedRows":["Dynamic"],"associatedColumns":["Yah . A"],"associatedMergedColumns":[]},{"number":"92.39","isBolded":true,"associatedRows":["K - means"],"associatedColumns":["AG"],"associatedMergedColumns":[]},{"number":"97.23","isBolded":false,"associatedRows":["Dynamic"],"associatedColumns":["Sogou"],"associatedMergedColumns":[]},{"number":"98.72","isBolded":true,"associatedRows":["K - means"],"associatedColumns":["DBP"],"associatedMergedColumns":[]},{"number":"60.90","isBolded":false,"associatedRows":["Dynamic"],"associatedColumns":["Amz . F"],"associatedMergedColumns":[]},{"number":"65.81","isBolded":false,"associatedRows":["Dynamic"],"associatedColumns":["Yelp . F"],"associatedMergedColumns":[]},{"number":"96.34","isBolded":false,"associatedRows":["Dynamic"],"associatedColumns":["Yelp . P"],"associatedMergedColumns":[]}]},{"caption":"Table 6. Ablation studies for the components of our proposal on eight text classification datasets. The model contains a conventional embedding layer, a \nBiGRU layer and a fully connected layer is used as our baseline. The best test accuracy (%) are bold. \n\n","rows":["1","2","3","4","5","6","-"],"columns":["DBP","Sogou","AG","Yah . A","Yelp . F","Amz . P","Amz . F","Yelp . P"],"mergedAllColumns":[],"numberCells":[{"number":"73.85","isBolded":false,"associatedRows":["6","-","-","-"],"associatedColumns":["Yah . A"],"associatedMergedColumns":[]},{"number":"97.25","isBolded":false,"associatedRows":["6","-","-","-"],"associatedColumns":["Sogou"],"associatedMergedColumns":[]},{"number":"92.37","isBolded":false,"associatedRows":["2","-","-","-"],"associatedColumns":["Yelp . P"],"associatedMergedColumns":[]},{"number":"51.30","isBolded":false,"associatedRows":["2","-","-","-"],"associatedColumns":["Amz . F"],"associatedMergedColumns":[]},{"number":"95.20","isBolded":false,"associatedRows":["2","-","-","-"],"associatedColumns":["Sogou"],"associatedMergedColumns":[]},{"number":"96.35","isBolded":false,"associatedRows":["3","-","-","-"],"associatedColumns":["Yelp . P"],"associatedMergedColumns":[]},{"number":"95.09","isBolded":false,"associatedRows":["1","-","-","-"],"associatedColumns":["Amz . P"],"associatedMergedColumns":[]},{"number":"92.18","isBolded":false,"associatedRows":["4","-","-","-"],"associatedColumns":["AG"],"associatedMergedColumns":[]},{"number":"96.48","isBolded":false,"associatedRows":["6","-","-","-"],"associatedColumns":["Yelp . P"],"associatedMergedColumns":[]},{"number":"60.29","isBolded":false,"associatedRows":["3","-","-","-"],"associatedColumns":["Amz . F"],"associatedMergedColumns":[]},{"number":"84.05","isBolded":false,"associatedRows":["5","-","-","-"],"associatedColumns":["AG"],"associatedMergedColumns":[]},{"number":"59.48","isBolded":false,"associatedRows":["5","-","-","-"],"associatedColumns":["Yelp . F"],"associatedMergedColumns":[]},{"number":"92.82","isBolded":false,"associatedRows":["5","-","-","-"],"associatedColumns":["Yelp . P"],"associatedMergedColumns":[]},{"number":"56.66","isBolded":false,"associatedRows":["2","-","-","-"],"associatedColumns":["Yelp . F"],"associatedMergedColumns":[]},{"number":"97.52","isBolded":true,"associatedRows":["4","-","-","-"],"associatedColumns":["Sogou"],"associatedMergedColumns":[]},{"number":"96.56","isBolded":false,"associatedRows":["4","-","-","-"],"associatedColumns":["Yelp . P"],"associatedMergedColumns":[]},{"number":"95.18","isBolded":true,"associatedRows":["4","-","-","-"],"associatedColumns":["Amz . P"],"associatedMergedColumns":[]},{"number":"61.36","isBolded":true,"associatedRows":["4","-","-","-"],"associatedColumns":["Amz . F"],"associatedMergedColumns":[]},{"number":"92.39","isBolded":false,"associatedRows":["6","-","-","-"],"associatedColumns":["AG"],"associatedMergedColumns":[]},{"number":"97.37","isBolded":false,"associatedRows":["3","-","-","-"],"associatedColumns":["Sogou"],"associatedMergedColumns":[]},{"number":"66.23","isBolded":true,"associatedRows":["1","-","-","-"],"associatedColumns":["Yelp . F"],"associatedMergedColumns":[]},{"number":"89.07","isBolded":false,"associatedRows":["5","-","-","-"],"associatedColumns":["Amz . P"],"associatedMergedColumns":[]},{"number":"97.37","isBolded":false,"associatedRows":["1","-","-","-"],"associatedColumns":["Sogou"],"associatedMergedColumns":[]},{"number":"96.06","isBolded":false,"associatedRows":["2","-","-","-"],"associatedColumns":["DBP"],"associatedMergedColumns":[]},{"number":"98.83","isBolded":false,"associatedRows":["3","-","-","-"],"associatedColumns":["DBP"],"associatedMergedColumns":[]},{"number":"94.96","isBolded":false,"associatedRows":["6","-","-","-"],"associatedColumns":["Amz . P"],"associatedMergedColumns":[]},{"number":"96.00","isBolded":false,"associatedRows":["5","-","-","-"],"associatedColumns":["Sogou"],"associatedMergedColumns":[]},{"number":"65.85","isBolded":false,"associatedRows":["6","-","-","-"],"associatedColumns":["Yelp . F"],"associatedMergedColumns":[]},{"number":"91.93","isBolded":false,"associatedRows":["3","-","-","-"],"associatedColumns":["AG"],"associatedMergedColumns":[]},{"number":"52.06","isBolded":false,"associatedRows":["5","-","-","-"],"associatedColumns":["Amz . F"],"associatedMergedColumns":[]},{"number":"73.58","isBolded":false,"associatedRows":["3","-","-","-"],"associatedColumns":["Yah . A"],"associatedMergedColumns":[]},{"number":"94.90","isBolded":false,"associatedRows":["3","-","-","-"],"associatedColumns":["Amz . P"],"associatedMergedColumns":[]},{"number":"96.69","isBolded":true,"associatedRows":["1","-","-","-"],"associatedColumns":["Yelp . P"],"associatedMergedColumns":[]},{"number":"83.13","isBolded":false,"associatedRows":["2","-","-","-"],"associatedColumns":["AG"],"associatedMergedColumns":[]},{"number":"65.11","isBolded":false,"associatedRows":["3","-","-","-"],"associatedColumns":["Yelp . F"],"associatedMergedColumns":[]},{"number":"66.23","isBolded":true,"associatedRows":["4","-","-","-"],"associatedColumns":["Yelp . F"],"associatedMergedColumns":[]},{"number":"98.84","isBolded":false,"associatedRows":["1","-","-","-"],"associatedColumns":["DBP"],"associatedMergedColumns":[]},{"number":"96.27","isBolded":false,"associatedRows":["5","-","-","-"],"associatedColumns":["DBP"],"associatedMergedColumns":[]},{"number":"57.87","isBolded":false,"associatedRows":["2","-","-","-"],"associatedColumns":["Yah . A"],"associatedMergedColumns":[]},{"number":"74.13","isBolded":true,"associatedRows":["1","-","-","-"],"associatedColumns":["Yah . A"],"associatedMergedColumns":[]},{"number":"60.78","isBolded":false,"associatedRows":["1","-","-","-"],"associatedColumns":["Amz . F"],"associatedMergedColumns":[]},{"number":"98.72","isBolded":false,"associatedRows":["6","-","-","-"],"associatedColumns":["DBP"],"associatedMergedColumns":[]},{"number":"89.04","isBolded":false,"associatedRows":["2","-","-","-"],"associatedColumns":["Amz . P"],"associatedMergedColumns":[]},{"number":"98.86","isBolded":true,"associatedRows":["4","-","-","-"],"associatedColumns":["DBP"],"associatedMergedColumns":[]},{"number":"92.64","isBolded":true,"associatedRows":["1","-","-","-"],"associatedColumns":["AG"],"associatedMergedColumns":[]},{"number":"60.95","isBolded":false,"associatedRows":["6","-","-","-"],"associatedColumns":["Amz . F"],"associatedMergedColumns":[]},{"number":"74.12","isBolded":false,"associatedRows":["4","-","-","-"],"associatedColumns":["Yah . A"],"associatedMergedColumns":[]},{"number":"60.31","isBolded":false,"associatedRows":["5","-","-","-"],"associatedColumns":["Yah . A"],"associatedMergedColumns":[]}]},{"caption":"Exp CC CWC Capsule \nAG \nDBP Yah.A Sogou Yelp.P Yelp.F Amz.P Amz.F \n\n1 \n-\n-\n-\n92.64 98.84 74.13 97.37 \n96.69 \n66.23 \n95.09 \n60.78 \n2 \n-\n-\n83.13 96.06 57.87 95.20 \n92.37 \n56.66 \n89.04 \n51.30 \n3 \n-\n-\n91.93 98.83 73.58 97.37 \n96.35 \n65.11 \n94.90 \n60.29 \n4 \n-\n-\n92.18 98.86 74.12 97.52 \n96.56 \n66.23 \n95.18 \n61.36 \n5 \n-\n84.05 96.27 60.31 96.00 \n92.82 \n59.48 \n89.07 \n52.06 \n6 \n-\n92.39 98.72 73.85 97.25 \n96.48 \n65.85 \n94.96 \n60.95 \n\nTable 7. Ablation studies for the components of our proposal on eight text classification datasets. The model contains a conventional embedding layer, a \nBiGRU layer and a fully connected layer is used as our baseline. The minimum number of model parameters (M) are bold. \n\n","rows":["1","2","3","4","5","6","-"],"columns":["DBP","Sogou","AG","Yah . A","Yelp . F","Amz . P","Amz . F","Yelp . P"],"mergedAllColumns":[],"numberCells":[{"number":"52.06","isBolded":false,"associatedRows":["5","-","-","-"],"associatedColumns":["Amz . F"],"associatedMergedColumns":[]},{"number":"56.66","isBolded":false,"associatedRows":["2","-","-","-"],"associatedColumns":["Yelp . F"],"associatedMergedColumns":[]},{"number":"84.05","isBolded":false,"associatedRows":["5","-","-","-"],"associatedColumns":["AG"],"associatedMergedColumns":[]},{"number":"97.25","isBolded":false,"associatedRows":["6","-","-","-"],"associatedColumns":["Sogou"],"associatedMergedColumns":[]},{"number":"96.48","isBolded":false,"associatedRows":["6","-","-","-"],"associatedColumns":["Yelp . P"],"associatedMergedColumns":[]},{"number":"92.82","isBolded":false,"associatedRows":["5","-","-","-"],"associatedColumns":["Yelp . P"],"associatedMergedColumns":[]},{"number":"73.85","isBolded":false,"associatedRows":["6","-","-","-"],"associatedColumns":["Yah . A"],"associatedMergedColumns":[]},{"number":"97.37","isBolded":false,"associatedRows":["3","-","-","-"],"associatedColumns":["Sogou"],"associatedMergedColumns":[]},{"number":"96.35","isBolded":false,"associatedRows":["3","-","-","-"],"associatedColumns":["Yelp . P"],"associatedMergedColumns":[]},{"number":"97.37","isBolded":false,"associatedRows":["1","-","-","-"],"associatedColumns":["Sogou"],"associatedMergedColumns":[]},{"number":"94.96","isBolded":false,"associatedRows":["6","-","-","-"],"associatedColumns":["Amz . P"],"associatedMergedColumns":[]},{"number":"73.58","isBolded":false,"associatedRows":["3","-","-","-"],"associatedColumns":["Yah . A"],"associatedMergedColumns":[]},{"number":"96.06","isBolded":false,"associatedRows":["2","-","-","-"],"associatedColumns":["DBP"],"associatedMergedColumns":[]},{"number":"98.83","isBolded":false,"associatedRows":["3","-","-","-"],"associatedColumns":["DBP"],"associatedMergedColumns":[]},{"number":"60.29","isBolded":false,"associatedRows":["3","-","-","-"],"associatedColumns":["Amz . F"],"associatedMergedColumns":[]},{"number":"65.11","isBolded":false,"associatedRows":["3","-","-","-"],"associatedColumns":["Yelp . F"],"associatedMergedColumns":[]},{"number":"95.09","isBolded":false,"associatedRows":["1","-","-","-"],"associatedColumns":["Amz . P"],"associatedMergedColumns":[]},{"number":"96.27","isBolded":false,"associatedRows":["5","-","-","-"],"associatedColumns":["DBP"],"associatedMergedColumns":[]},{"number":"92.37","isBolded":false,"associatedRows":["2","-","-","-"],"associatedColumns":["Yelp . P"],"associatedMergedColumns":[]},{"number":"66.23","isBolded":true,"associatedRows":["1","-","-","-"],"associatedColumns":["Yelp . F"],"associatedMergedColumns":[]},{"number":"92.39","isBolded":false,"associatedRows":["6","-","-","-"],"associatedColumns":["AG"],"associatedMergedColumns":[]},{"number":"98.84","isBolded":false,"associatedRows":["1","-","-","-"],"associatedColumns":["DBP"],"associatedMergedColumns":[]},{"number":"98.86","isBolded":true,"associatedRows":["4","-","-","-"],"associatedColumns":["DBP"],"associatedMergedColumns":[]},{"number":"89.04","isBolded":false,"associatedRows":["2","-","-","-"],"associatedColumns":["Amz . P"],"associatedMergedColumns":[]},{"number":"65.85","isBolded":false,"associatedRows":["6","-","-","-"],"associatedColumns":["Yelp . F"],"associatedMergedColumns":[]},{"number":"60.95","isBolded":false,"associatedRows":["6","-","-","-"],"associatedColumns":["Amz . F"],"associatedMergedColumns":[]},{"number":"96.00","isBolded":false,"associatedRows":["5","-","-","-"],"associatedColumns":["Sogou"],"associatedMergedColumns":[]},{"number":"66.23","isBolded":true,"associatedRows":["4","-","-","-"],"associatedColumns":["Yelp . F"],"associatedMergedColumns":[]},{"number":"60.78","isBolded":false,"associatedRows":["1","-","-","-"],"associatedColumns":["Amz . F"],"associatedMergedColumns":[]},{"number":"61.36","isBolded":true,"associatedRows":["4","-","-","-"],"associatedColumns":["Amz . F"],"associatedMergedColumns":[]},{"number":"91.93","isBolded":false,"associatedRows":["3","-","-","-"],"associatedColumns":["AG"],"associatedMergedColumns":[]},{"number":"97.52","isBolded":true,"associatedRows":["4","-","-","-"],"associatedColumns":["Sogou"],"associatedMergedColumns":[]},{"number":"59.48","isBolded":false,"associatedRows":["5","-","-","-"],"associatedColumns":["Yelp . F"],"associatedMergedColumns":[]},{"number":"83.13","isBolded":false,"associatedRows":["2","-","-","-"],"associatedColumns":["AG"],"associatedMergedColumns":[]},{"number":"94.90","isBolded":false,"associatedRows":["3","-","-","-"],"associatedColumns":["Amz . P"],"associatedMergedColumns":[]},{"number":"95.18","isBolded":true,"associatedRows":["4","-","-","-"],"associatedColumns":["Amz . P"],"associatedMergedColumns":[]},{"number":"60.31","isBolded":false,"associatedRows":["5","-","-","-"],"associatedColumns":["Yah . A"],"associatedMergedColumns":[]},{"number":"51.30","isBolded":false,"associatedRows":["2","-","-","-"],"associatedColumns":["Amz . F"],"associatedMergedColumns":[]},{"number":"92.64","isBolded":true,"associatedRows":["1","-","-","-"],"associatedColumns":["AG"],"associatedMergedColumns":[]},{"number":"57.87","isBolded":false,"associatedRows":["2","-","-","-"],"associatedColumns":["Yah . A"],"associatedMergedColumns":[]},{"number":"95.20","isBolded":false,"associatedRows":["2","-","-","-"],"associatedColumns":["Sogou"],"associatedMergedColumns":[]},{"number":"96.56","isBolded":false,"associatedRows":["4","-","-","-"],"associatedColumns":["Yelp . P"],"associatedMergedColumns":[]},{"number":"74.13","isBolded":true,"associatedRows":["1","-","-","-"],"associatedColumns":["Yah . A"],"associatedMergedColumns":[]},{"number":"92.18","isBolded":false,"associatedRows":["4","-","-","-"],"associatedColumns":["AG"],"associatedMergedColumns":[]},{"number":"96.69","isBolded":true,"associatedRows":["1","-","-","-"],"associatedColumns":["Yelp . P"],"associatedMergedColumns":[]},{"number":"74.12","isBolded":false,"associatedRows":["4","-","-","-"],"associatedColumns":["Yah . A"],"associatedMergedColumns":[]},{"number":"98.72","isBolded":false,"associatedRows":["6","-","-","-"],"associatedColumns":["DBP"],"associatedMergedColumns":[]},{"number":"89.07","isBolded":false,"associatedRows":["5","-","-","-"],"associatedColumns":["Amz . P"],"associatedMergedColumns":[]}]}]