[{"caption":"Table 1: Shape classification. Overall accuracy (OA %) and \nclass average accuracy (AA, %). \n\n","rows":["Ours - 2048 pts ( 16 )","LeNet [ 27 ]","Ours - 1024 pts ( 16 )","PointNet++ [ 40 ]","NiN [ 32 ]","DGCNN [ 54 ]","Ours - Black points ( 16 )","MVCNN [ 47 ]","Subvolume [ 39 ]","PointNet [ 38 ]","KPConv [ 49 ]","Ours - Gray levels ( 16 )","PointCNN [ 29 ]"],"columns":["AA","( a ) MNIST","OA","Points","Mesh or voxels","Image - based methods","( b ) ModelNet 40","Point - based methods"],"mergedAllColumns":[],"numberCells":[{"number":"88.1","isBolded":false,"associatedRows":["Ours - Black points ( 16 )","PointCNN [ 29 ]"],"associatedColumns":["( b ) ModelNet 40","AA","Mesh or voxels","Points"],"associatedMergedColumns":[]},{"number":"91.8","isBolded":false,"associatedRows":["Ours - Black points ( 16 )","Ours - 1024 pts ( 16 )"],"associatedColumns":["( b ) ModelNet 40","OA","Mesh or voxels","Points"],"associatedMergedColumns":[]},{"number":"99.62","isBolded":true,"associatedRows":["Ours - Gray levels ( 16 )"],"associatedColumns":["( a ) MNIST","OA","Image - based methods","Point - based methods"],"associatedMergedColumns":[]},{"number":"99.49","isBolded":false,"associatedRows":["Ours - Black points ( 16 )"],"associatedColumns":["( a ) MNIST","OA","Image - based methods","Point - based methods"],"associatedMergedColumns":[]},{"number":"90.1","isBolded":false,"associatedRows":["NiN [ 32 ]","MVCNN [ 47 ]"],"associatedColumns":["( b ) ModelNet 40","OA","Mesh or voxels"],"associatedMergedColumns":[]},{"number":"92.9","isBolded":true,"associatedRows":["Ours - Black points ( 16 )","KPConv [ 49 ]"],"associatedColumns":["( b ) ModelNet 40","OA","Mesh or voxels","Points"],"associatedMergedColumns":[]},{"number":"90.2","isBolded":true,"associatedRows":["PointNet++ [ 40 ]","DGCNN [ 54 ]"],"associatedColumns":["( b ) ModelNet 40","AA","Mesh or voxels","Points"],"associatedMergedColumns":[]},{"number":"92.2","isBolded":false,"associatedRows":["PointNet++ [ 40 ]","DGCNN [ 54 ]"],"associatedColumns":["( b ) ModelNet 40","OA","Mesh or voxels","Points"],"associatedMergedColumns":[]},{"number":"99.49","isBolded":false,"associatedRows":["PointNet++ [ 40 ]"],"associatedColumns":["( a ) MNIST","OA","Image - based methods","Point - based methods"],"associatedMergedColumns":[]},{"number":"88.5","isBolded":false,"associatedRows":["Ours - Black points ( 16 )","Ours - 1024 pts ( 16 )"],"associatedColumns":["( b ) ModelNet 40","AA","Mesh or voxels","Points"],"associatedMergedColumns":[]},{"number":"90.7","isBolded":false,"associatedRows":["Ours - Gray levels ( 16 )","PointNet++ [ 40 ]"],"associatedColumns":["( b ) ModelNet 40","OA","Mesh or voxels","Points"],"associatedMergedColumns":[]},{"number":"92.5","isBolded":false,"associatedRows":["Ours - Black points ( 16 )","Ours - 2048 pts ( 16 )"],"associatedColumns":["( b ) ModelNet 40","OA","Mesh or voxels","Points"],"associatedMergedColumns":[]},{"number":"89.6","isBolded":false,"associatedRows":["Ours - Black points ( 16 )","Ours - 2048 pts ( 16 )"],"associatedColumns":["( b ) ModelNet 40","AA","Mesh or voxels","Points"],"associatedMergedColumns":[]},{"number":"89.2","isBolded":false,"associatedRows":["LeNet [ 27 ]","Subvolume [ 39 ]"],"associatedColumns":["( b ) ModelNet 40","OA","Mesh or voxels"],"associatedMergedColumns":[]},{"number":"99.53","isBolded":false,"associatedRows":["NiN [ 32 ]"],"associatedColumns":["( a ) MNIST","OA","Image - based methods"],"associatedMergedColumns":[]},{"number":"89.2","isBolded":false,"associatedRows":["PointCNN [ 29 ]","PointNet [ 38 ]"],"associatedColumns":["( b ) ModelNet 40","OA","Mesh or voxels","Points"],"associatedMergedColumns":[]},{"number":"92.2","isBolded":false,"associatedRows":["Ours - Black points ( 16 )","PointCNN [ 29 ]"],"associatedColumns":["( b ) ModelNet 40","OA","Mesh or voxels","Points"],"associatedMergedColumns":[]},{"number":"86.2","isBolded":false,"associatedRows":["PointCNN [ 29 ]","PointNet [ 38 ]"],"associatedColumns":["( b ) ModelNet 40","AA","Mesh or voxels","Points"],"associatedMergedColumns":[]},{"number":"99.54","isBolded":false,"associatedRows":["PointCNN [ 29 ]"],"associatedColumns":["( a ) MNIST","OA","Image - based methods","Point - based methods"],"associatedMergedColumns":[]},{"number":"99.20","isBolded":false,"associatedRows":["LeNet [ 27 ]"],"associatedColumns":["( a ) MNIST","OA","Image - based methods"],"associatedMergedColumns":[]}]},{"caption":"Table 2: ShapeNet \n\nMethod \nmcIoU \nmIoU \nSyncSpecCNN [58] \n82.0 \n84.7 \nPd-Network [25] \n82.7 \n85.5 \n3DmFV-Net [7] \n81.0 \n84.3 \nPointNet [38] \n80.4 \n83.7 \nPointNet++ [40] \n81.9 \n85.1 \nSubSparseCN [19] \n83.3 \n86.0 \nSPLATNet [46] \n83.7 \n85.4 \nSpiderCNN [56] \n81.7 \n85.3 \nSO-Net [28] \n81.0 \n84.9 \nPCNN [4] \n81.8 \n85.1 \nKCNet [43] \n82.2 \n83.7 \nSpecGCN [50] \n-\n85.4 \nRSNet [23] \n81.4 \n84.9 \nDGCNN [54] \n82.3 \n85.1 \nSGPN [53] \n82.8 \n85.8 \nPointCNN [29] \n84.6 \n86.1 \nKPConv [49] \n85.1 \n86.4 \nConvPoint (16) \n83.4 \n85.8 \nrank \n4 \n4 \n\n","rows":["SGPN [ 53 ]","SyncSpecCNN [ 58 ]","Pd - Network [ 25 ]","KCNet [ 43 ]","RSNet [ 23 ]","SubSparseCN [ 19 ]","ConvPoint ( 16 )","PointNet++ [ 40 ]","-","SpiderCNN [ 56 ]","PCNN [ 4 ]","DGCNN [ 54 ]","3DmFV - Net [ 7 ]","SpecGCN [ 50 ]","PointNet [ 38 ]","KPConv [ 49 ]","SPLATNet [ 46 ]","SO - Net [ 28 ]","PointCNN [ 29 ]"],"columns":["mIoU","Table 2 : ShapeNet","mcIoU"],"mergedAllColumns":[],"numberCells":[{"number":"81.9","isBolded":false,"associatedRows":["PointNet++ [ 40 ]"],"associatedColumns":["Table 2 : ShapeNet","mcIoU"],"associatedMergedColumns":[]},{"number":"84.7","isBolded":false,"associatedRows":["SyncSpecCNN [ 58 ]"],"associatedColumns":["Table 2 : ShapeNet","mIoU"],"associatedMergedColumns":[]},{"number":"83.3","isBolded":false,"associatedRows":["SubSparseCN [ 19 ]"],"associatedColumns":["Table 2 : ShapeNet","mcIoU"],"associatedMergedColumns":[]},{"number":"82.0","isBolded":false,"associatedRows":["SyncSpecCNN [ 58 ]"],"associatedColumns":["Table 2 : ShapeNet","mcIoU"],"associatedMergedColumns":[]},{"number":"84.3","isBolded":false,"associatedRows":["3DmFV - Net [ 7 ]"],"associatedColumns":["Table 2 : ShapeNet","mIoU"],"associatedMergedColumns":[]},{"number":"83.7","isBolded":false,"associatedRows":["KCNet [ 43 ]"],"associatedColumns":["Table 2 : ShapeNet","mIoU"],"associatedMergedColumns":[]},{"number":"83.7","isBolded":false,"associatedRows":["PointNet [ 38 ]"],"associatedColumns":["Table 2 : ShapeNet","mIoU"],"associatedMergedColumns":[]},{"number":"86.4","isBolded":true,"associatedRows":["KPConv [ 49 ]"],"associatedColumns":["Table 2 : ShapeNet","mIoU"],"associatedMergedColumns":[]},{"number":"81.0","isBolded":false,"associatedRows":["3DmFV - Net [ 7 ]"],"associatedColumns":["Table 2 : ShapeNet","mcIoU"],"associatedMergedColumns":[]},{"number":"84.9","isBolded":false,"associatedRows":["SO - Net [ 28 ]"],"associatedColumns":["Table 2 : ShapeNet","mIoU"],"associatedMergedColumns":[]},{"number":"85.1","isBolded":false,"associatedRows":["PCNN [ 4 ]"],"associatedColumns":["Table 2 : ShapeNet","mIoU"],"associatedMergedColumns":[]},{"number":"85.1","isBolded":false,"associatedRows":["DGCNN [ 54 ]"],"associatedColumns":["Table 2 : ShapeNet","mIoU"],"associatedMergedColumns":[]},{"number":"80.4","isBolded":false,"associatedRows":["PointNet [ 38 ]"],"associatedColumns":["Table 2 : ShapeNet","mcIoU"],"associatedMergedColumns":[]},{"number":"86.0","isBolded":false,"associatedRows":["SubSparseCN [ 19 ]"],"associatedColumns":["Table 2 : ShapeNet","mIoU"],"associatedMergedColumns":[]},{"number":"85.4","isBolded":false,"associatedRows":["SpecGCN [ 50 ]","-"],"associatedColumns":["Table 2 : ShapeNet","mIoU"],"associatedMergedColumns":[]},{"number":"85.8","isBolded":false,"associatedRows":["ConvPoint ( 16 )"],"associatedColumns":["Table 2 : ShapeNet","mIoU"],"associatedMergedColumns":[]},{"number":"82.7","isBolded":false,"associatedRows":["Pd - Network [ 25 ]"],"associatedColumns":["Table 2 : ShapeNet","mcIoU"],"associatedMergedColumns":[]},{"number":"85.4","isBolded":false,"associatedRows":["SPLATNet [ 46 ]"],"associatedColumns":["Table 2 : ShapeNet","mIoU"],"associatedMergedColumns":[]},{"number":"86.1","isBolded":false,"associatedRows":["PointCNN [ 29 ]"],"associatedColumns":["Table 2 : ShapeNet","mIoU"],"associatedMergedColumns":[]},{"number":"81.8","isBolded":false,"associatedRows":["PCNN [ 4 ]"],"associatedColumns":["Table 2 : ShapeNet","mcIoU"],"associatedMergedColumns":[]},{"number":"84.6","isBolded":false,"associatedRows":["PointCNN [ 29 ]"],"associatedColumns":["Table 2 : ShapeNet","mcIoU"],"associatedMergedColumns":[]},{"number":"84.9","isBolded":false,"associatedRows":["RSNet [ 23 ]"],"associatedColumns":["Table 2 : ShapeNet","mIoU"],"associatedMergedColumns":[]},{"number":"83.7","isBolded":false,"associatedRows":["SPLATNet [ 46 ]"],"associatedColumns":["Table 2 : ShapeNet","mcIoU"],"associatedMergedColumns":[]},{"number":"82.3","isBolded":false,"associatedRows":["DGCNN [ 54 ]"],"associatedColumns":["Table 2 : ShapeNet","mcIoU"],"associatedMergedColumns":[]},{"number":"81.0","isBolded":false,"associatedRows":["SO - Net [ 28 ]"],"associatedColumns":["Table 2 : ShapeNet","mcIoU"],"associatedMergedColumns":[]},{"number":"85.1","isBolded":true,"associatedRows":["KPConv [ 49 ]"],"associatedColumns":["Table 2 : ShapeNet","mcIoU"],"associatedMergedColumns":[]},{"number":"82.2","isBolded":false,"associatedRows":["KCNet [ 43 ]"],"associatedColumns":["Table 2 : ShapeNet","mcIoU"],"associatedMergedColumns":[]},{"number":"81.4","isBolded":false,"associatedRows":["RSNet [ 23 ]"],"associatedColumns":["Table 2 : ShapeNet","mcIoU"],"associatedMergedColumns":[]},{"number":"85.5","isBolded":false,"associatedRows":["Pd - Network [ 25 ]"],"associatedColumns":["Table 2 : ShapeNet","mIoU"],"associatedMergedColumns":[]},{"number":"81.7","isBolded":false,"associatedRows":["SpiderCNN [ 56 ]"],"associatedColumns":["Table 2 : ShapeNet","mcIoU"],"associatedMergedColumns":[]},{"number":"82.8","isBolded":false,"associatedRows":["SGPN [ 53 ]"],"associatedColumns":["Table 2 : ShapeNet","mcIoU"],"associatedMergedColumns":[]},{"number":"85.8","isBolded":false,"associatedRows":["SGPN [ 53 ]"],"associatedColumns":["Table 2 : ShapeNet","mIoU"],"associatedMergedColumns":[]},{"number":"83.4","isBolded":false,"associatedRows":["ConvPoint ( 16 )"],"associatedColumns":["Table 2 : ShapeNet","mcIoU"],"associatedMergedColumns":[]},{"number":"85.3","isBolded":false,"associatedRows":["SpiderCNN [ 56 ]"],"associatedColumns":["Table 2 : ShapeNet","mIoU"],"associatedMergedColumns":[]},{"number":"85.1","isBolded":false,"associatedRows":["PointNet++ [ 40 ]"],"associatedColumns":["Table 2 : ShapeNet","mIoU"],"associatedMergedColumns":[]}]},{"caption":"Table 3: Influence of the spatial sampling number, ShapeNet \ndataset. \n\n","rows":["mIoU"],"columns":["1","2","4","16","8"],"mergedAllColumns":[],"numberCells":[{"number":"83.9","isBolded":false,"associatedRows":["mIoU"],"associatedColumns":["1"],"associatedMergedColumns":[]},{"number":"85.8","isBolded":false,"associatedRows":["mIoU"],"associatedColumns":["16"],"associatedMergedColumns":[]},{"number":"85.4","isBolded":false,"associatedRows":["mIoU"],"associatedColumns":["4"],"associatedMergedColumns":[]},{"number":"84.8","isBolded":false,"associatedRows":["mIoU"],"associatedColumns":["2"],"associatedMergedColumns":[]},{"number":"85.7","isBolded":false,"associatedRows":["mIoU"],"associatedColumns":["8"],"associatedMergedColumns":[]}]},{"caption":"Table 4: Large scene semantic segmentation benchmarks. \n\n","rows":["PCCN [ 52 ]","HDGCN","RFMSSF","EdConvE","MSRRNetCRF","RSNet [ 23 ]","ConvPoint - Fusion","Pointnet [ 38 ]","PointNet++ [ 40 ]","-","TMLC - MS [ 22 ]","SPGraph [ 26 ]","SnapNet [ 12 ]","ConvPoint - RGB","KPConv [ 49 ]","ConvPoint - NoColor","MS3DVS","KP - FCNN [ 49 ]","PointCNN [ 29 ]","TML - PC [ 37 ]"],"columns":["Cars","Ground Building Pole Bollard Trash can Barrier Pedestrian","second best","ceil .","floor wall beam","col .","Natural","mIoU","OA","mAcc mIoU","Man made Natural High veg . Low veg . Buildings Hard scape Artefacts","wind . door chair table book . sofa board clut .","Car","and","third best .","Best score ,"],"mergedAllColumns":["( c ) NPM3D","( a ) S3DIS","( b ) Semantic8"],"numberCells":[{"number":"51.6","isBolded":false,"associatedRows":["Pointnet [ 38 ]","MSRRNetCRF","-","-"],"associatedColumns":["third best .","wind . door chair table book . sofa board clut ."],"associatedMergedColumns":["( a ) S3DIS"]},{"number":"0.058","isBolded":false,"associatedRows":["TML - PC [ 37 ]","MSRRNetCRF","-","-"],"associatedColumns":["third best .","wind . door chair table book . sofa board clut .","Cars"],"associatedMergedColumns":["( b ) Semantic8"]},{"number":"36.0","isBolded":false,"associatedRows":["ConvPoint - Fusion","ConvPoint - Fusion","MS3DVS","-"],"associatedColumns":["third best .","wind . door chair table book . sofa board clut .","Man made Natural High veg . Low veg . Buildings Hard scape Artefacts","Ground Building Pole Bollard Trash can Barrier Pedestrian"],"associatedMergedColumns":["( c ) NPM3D"]},{"number":"0.819","isBolded":false,"associatedRows":["PointNet++ [ 40 ]","MSRRNetCRF","-","-"],"associatedColumns":["Best score ,","ceil .","Man made Natural High veg . Low veg . Buildings Hard scape Artefacts"],"associatedMergedColumns":["( b ) Semantic8"]},{"number":"0.553","isBolded":false,"associatedRows":["TMLC - MS [ 22 ]","MSRRNetCRF","-","-"],"associatedColumns":["third best .","wind . door chair table book . sofa board clut .","Cars"],"associatedMergedColumns":["( b ) Semantic8"]},{"number":"88.8","isBolded":false,"associatedRows":["ConvPoint - Fusion","EdConvE"],"associatedColumns":["Best score ,","OA"],"associatedMergedColumns":["( a ) S3DIS"]},{"number":"47.1","isBolded":false,"associatedRows":["ConvPoint - Fusion","MSRRNetCRF","-","-"],"associatedColumns":["second best","floor wall beam"],"associatedMergedColumns":["( a ) S3DIS"]},{"number":"9.6","isBolded":false,"associatedRows":["Pointnet [ 38 ]","MSRRNetCRF","-","-"],"associatedColumns":["third best .","wind . door chair table book . sofa board clut ."],"associatedMergedColumns":["( a ) S3DIS"]},{"number":"51.7","isBolded":false,"associatedRows":["PointCNN [ 29 ]","MSRRNetCRF","-","-"],"associatedColumns":["and","col ."],"associatedMergedColumns":["( a ) S3DIS"]},{"number":"70.5","isBolded":false,"associatedRows":["ConvPoint - RGB","MSRRNetCRF","-","-"],"associatedColumns":["third best .","wind . door chair table book . sofa board clut ."],"associatedMergedColumns":["( a ) S3DIS"]},{"number":"0.124","isBolded":false,"associatedRows":["TML - PC [ 37 ]","MSRRNetCRF","-","-"],"associatedColumns":["third best .","wind . door chair table book . sofa board clut .","Man made Natural High veg . Low veg . Buildings Hard scape Artefacts"],"associatedMergedColumns":["( b ) Semantic8"]},{"number":"91.0","isBolded":false,"associatedRows":["ConvPoint - Fusion","ConvPoint - Fusion","EdConvE","-"],"associatedColumns":["Best score ,","floor wall beam","Man made Natural High veg . Low veg . Buildings Hard scape Artefacts","Ground Building Pole Bollard Trash can Barrier Pedestrian"],"associatedMergedColumns":["( c ) NPM3D"]},{"number":"71.8","isBolded":false,"associatedRows":["ConvPoint - Fusion","MSRRNetCRF","-","-"],"associatedColumns":["third best .","wind . door chair table book . sofa board clut ."],"associatedMergedColumns":["( a ) S3DIS"]},{"number":"49.3","isBolded":false,"associatedRows":["ConvPoint - NoColor","ConvPoint - Fusion","MS3DVS","-"],"associatedColumns":["third best .","wind . door chair table book . sofa board clut .","Man made Natural High veg . Low veg . Buildings Hard scape Artefacts","Ground Building Pole Bollard Trash can Barrier Pedestrian"],"associatedMergedColumns":["( c ) NPM3D"]},{"number":"0.956","isBolded":false,"associatedRows":["ConvPoint - Fusion","ConvPoint - Fusion","MSRRNetCRF","-"],"associatedColumns":["third best .","wind . door chair table book . sofa board clut .","Man made Natural High veg . Low veg . Buildings Hard scape Artefacts"],"associatedMergedColumns":["( b ) Semantic8"]},{"number":"52.4","isBolded":false,"associatedRows":["ConvPoint - Fusion","ConvPoint - Fusion","MS3DVS","-"],"associatedColumns":["second best","floor wall beam","Man made Natural High veg . Low veg . Buildings Hard scape Artefacts","Ground Building Pole Bollard Trash can Barrier Pedestrian"],"associatedMergedColumns":["( c ) NPM3D"]},{"number":"69.1","isBolded":false,"associatedRows":["PointCNN [ 29 ]","MSRRNetCRF","-","-"],"associatedColumns":["third best .","wind . door chair table book . sofa board clut ."],"associatedMergedColumns":["( a ) S3DIS"]},{"number":"70.6","isBolded":false,"associatedRows":["KPConv [ 49 ]","MSRRNetCRF","-","-"],"associatedColumns":["Best score ,","mAcc mIoU"],"associatedMergedColumns":["( a ) S3DIS"]},{"number":"99.4","isBolded":false,"associatedRows":["ConvPoint - Fusion","ConvPoint - Fusion","HDGCN","-"],"associatedColumns":["Best score ,","mAcc mIoU","Man made Natural High veg . Low veg . Buildings Hard scape Artefacts","Ground Building Pole Bollard Trash can Barrier Pedestrian"],"associatedMergedColumns":["( c ) NPM3D"]},{"number":"68.1","isBolded":false,"associatedRows":["RSNet [ 23 ]","MSRRNetCRF","-","-"],"associatedColumns":["third best .","wind . door chair table book . sofa board clut ."],"associatedMergedColumns":["( a ) S3DIS"]},{"number":"76.6","isBolded":false,"associatedRows":["KPConv [ 49 ]","MSRRNetCRF","-","-"],"associatedColumns":["third best .","wind . door chair table book . sofa board clut ."],"associatedMergedColumns":["( a ) S3DIS"]},{"number":"0.717","isBolded":false,"associatedRows":["SPGraph [ 26 ]","MSRRNetCRF","-","-"],"associatedColumns":["third best .","wind . door chair table book . sofa board clut .","Man made Natural High veg . Low veg . Buildings Hard scape Artefacts"],"associatedMergedColumns":["( b ) Semantic8"]},{"number":"95.0","isBolded":false,"associatedRows":["ConvPoint - NoColor","ConvPoint - Fusion","MSRRNetCRF","-"],"associatedColumns":["third best .","wind . door chair table book . sofa board clut .","Man made Natural High veg . Low veg . Buildings Hard scape Artefacts","Car"],"associatedMergedColumns":["( c ) NPM3D"]},{"number":"68.3","isBolded":false,"associatedRows":["ConvPoint - Fusion","ConvPoint - Fusion","HDGCN"],"associatedColumns":["Best score ,","mAcc mIoU","mIoU","mIoU"],"associatedMergedColumns":["( c ) NPM3D"]},{"number":"88.0","isBolded":false,"associatedRows":["Pointnet [ 38 ]","MSRRNetCRF","-","-"],"associatedColumns":["Best score ,","ceil ."],"associatedMergedColumns":["( a ) S3DIS"]},{"number":"60.3","isBolded":false,"associatedRows":["KPConv [ 49 ]","MSRRNetCRF","-","-"],"associatedColumns":["third best .","wind . door chair table book . sofa board clut ."],"associatedMergedColumns":["( a ) S3DIS"]},{"number":"67.8","isBolded":false,"associatedRows":["ConvPoint - RGB","MSRRNetCRF","-","-"],"associatedColumns":["third best .","wind . door chair table book . sofa board clut ."],"associatedMergedColumns":["( a ) S3DIS"]},{"number":"63.9","isBolded":false,"associatedRows":["KPConv [ 49 ]","MSRRNetCRF","-","-"],"associatedColumns":["second best","floor wall beam"],"associatedMergedColumns":["( a ) S3DIS"]},{"number":"71.3","isBolded":false,"associatedRows":["ConvPoint - Fusion","ConvPoint - Fusion","KP - FCNN [ 49 ]","-"],"associatedColumns":["second best","floor wall beam","Man made Natural High veg . Low veg . Buildings Hard scape Artefacts","Ground Building Pole Bollard Trash can Barrier Pedestrian"],"associatedMergedColumns":["( c ) NPM3D"]},{"number":"0.643","isBolded":false,"associatedRows":["PointNet++ [ 40 ]","MSRRNetCRF","-","-"],"associatedColumns":["second best","floor wall beam","Man made Natural High veg . Low veg . Buildings Hard scape Artefacts"],"associatedMergedColumns":["( b ) Semantic8"]},{"number":"58.4","isBolded":false,"associatedRows":["PointCNN [ 29 ]","MSRRNetCRF","-","-"],"associatedColumns":["third best .","wind . door chair table book . sofa board clut ."],"associatedMergedColumns":["( a ) S3DIS"]},{"number":"92.4","isBolded":false,"associatedRows":["KPConv [ 49 ]","MSRRNetCRF","-","-"],"associatedColumns":["Best score ,","floor wall beam"],"associatedMergedColumns":["( a ) S3DIS"]},{"number":"0.857","isBolded":false,"associatedRows":["PointNet++ [ 40 ]","MSRRNetCRF","-","-"],"associatedColumns":["Best score ,","mAcc mIoU","OA"],"associatedMergedColumns":["( b ) Semantic8"]},{"number":"51.6","isBolded":false,"associatedRows":["RSNet [ 23 ]","MSRRNetCRF","-","-"],"associatedColumns":["third best .","wind . door chair table book . sofa board clut ."],"associatedMergedColumns":["( a ) S3DIS"]},{"number":"56.5","isBolded":false,"associatedRows":["RSNet [ 23 ]","MSRRNetCRF","-","-"],"associatedColumns":["Best score ,","mAcc mIoU"],"associatedMergedColumns":["( a ) S3DIS"]},{"number":"39.1","isBolded":false,"associatedRows":["PointCNN [ 29 ]","MSRRNetCRF","-","-"],"associatedColumns":["third best .","wind . door chair table book . sofa board clut ."],"associatedMergedColumns":["( a ) S3DIS"]},{"number":"47.3","isBolded":false,"associatedRows":["PCCN [ 52 ]","MSRRNetCRF","-","-"],"associatedColumns":["third best .","wind . door chair table book . sofa board clut ."],"associatedMergedColumns":["( a ) S3DIS"]},{"number":"85.4","isBolded":false,"associatedRows":["ConvPoint - NoColor","ConvPoint - Fusion","-"],"associatedColumns":["third best .","wind . door chair table book . sofa board clut .","Man made Natural High veg . Low veg . Buildings Hard scape Artefacts","Natural"],"associatedMergedColumns":["( c ) NPM3D"]},{"number":"58.6","isBolded":false,"associatedRows":["PointCNN [ 29 ]","MSRRNetCRF","-","-"],"associatedColumns":["third best .","wind . door chair table book . sofa board clut ."],"associatedMergedColumns":["( a ) S3DIS"]},{"number":"0.772","isBolded":false,"associatedRows":["SnapNet [ 12 ]","MSRRNetCRF","-","-"],"associatedColumns":["third best .","wind . door chair table book . sofa board clut .","Cars"],"associatedMergedColumns":["( b ) Semantic8"]},{"number":"0.781","isBolded":false,"associatedRows":["PointNet++ [ 40 ]","MSRRNetCRF","-","-"],"associatedColumns":["second best","floor wall beam","Man made Natural High veg . Low veg . Buildings Hard scape Artefacts"],"associatedMergedColumns":["( b ) Semantic8"]},{"number":"0.529","isBolded":false,"associatedRows":["SPGraph [ 26 ]","MSRRNetCRF","-","-"],"associatedColumns":["third best .","wind . door chair table book . sofa board clut .","Man made Natural High veg . Low veg . Buildings Hard scape Artefacts"],"associatedMergedColumns":["( b ) Semantic8"]},{"number":"68.9","isBolded":false,"associatedRows":["PCCN [ 52 ]","MSRRNetCRF","-","-"],"associatedColumns":["third best .","wind . door chair table book . sofa board clut ."],"associatedMergedColumns":["( a ) S3DIS"]},{"number":"45.8","isBolded":false,"associatedRows":["ConvPoint - NoColor","ConvPoint - Fusion","MSRRNetCRF","-"],"associatedColumns":["second best","floor wall beam","Man made Natural High veg . Low veg . Buildings Hard scape Artefacts","Ground Building Pole Bollard Trash can Barrier Pedestrian"],"associatedMergedColumns":["( c ) NPM3D"]},{"number":"50.2","isBolded":false,"associatedRows":["RSNet [ 23 ]","MSRRNetCRF","-","-"],"associatedColumns":["third best .","wind . door chair table book . sofa board clut ."],"associatedMergedColumns":["( a ) S3DIS"]},{"number":"64.0","isBolded":false,"associatedRows":["KPConv [ 49 ]","MSRRNetCRF","-","-"],"associatedColumns":["third best .","wind . door chair table book . sofa board clut ."],"associatedMergedColumns":["( a ) S3DIS"]},{"number":"0.561","isBolded":false,"associatedRows":["SnapNet [ 12 ]","MSRRNetCRF","-","-"],"associatedColumns":["third best .","wind . door chair table book . sofa board clut .","Man made Natural High veg . Low veg . Buildings Hard scape Artefacts"],"associatedMergedColumns":["( b ) Semantic8"]},{"number":"44.7","isBolded":false,"associatedRows":["ConvPoint - NoColor","ConvPoint - Fusion","HDGCN","-"],"associatedColumns":["third best .","wind . door chair table book . sofa board clut .","Man made Natural High veg . Low veg . Buildings Hard scape Artefacts","Ground Building Pole Bollard Trash can Barrier Pedestrian"],"associatedMergedColumns":["( c ) NPM3D"]},{"number":"93.0","isBolded":false,"associatedRows":["ConvPoint - Fusion","ConvPoint - Fusion","HDGCN","-"],"associatedColumns":["Best score ,","floor wall beam","Man made Natural High veg . Low veg . Buildings Hard scape Artefacts","Ground Building Pole Bollard Trash can Barrier Pedestrian"],"associatedMergedColumns":["( c ) NPM3D"]},{"number":"36.8","isBolded":false,"associatedRows":["ConvPoint - NoColor","MSRRNetCRF","-","-"],"associatedColumns":["third best .","wind . door chair table book . sofa board clut ."],"associatedMergedColumns":["( a ) S3DIS"]},{"number":"63.2","isBolded":false,"associatedRows":["ConvPoint - Fusion","MSRRNetCRF","-","-"],"associatedColumns":["third best .","wind . door chair table book . sofa board clut ."],"associatedMergedColumns":["( a ) S3DIS"]},{"number":"0.719","isBolded":false,"associatedRows":["ConvPoint - Fusion","ConvPoint - Fusion","MSRRNetCRF","-"],"associatedColumns":["third best .","wind . door chair table book . sofa board clut .","Man made Natural High veg . Low veg . Buildings Hard scape Artefacts"],"associatedMergedColumns":["( b ) Semantic8"]},{"number":"65.9","isBolded":false,"associatedRows":["ConvPoint - NoColor","ConvPoint - Fusion","EdConvE","-"],"associatedColumns":["third best .","wind . door chair table book . sofa board clut .","Man made Natural High veg . Low veg . Buildings Hard scape Artefacts","Ground Building Pole Bollard Trash can Barrier Pedestrian"],"associatedMergedColumns":["( c ) NPM3D"]},{"number":"37.1","isBolded":false,"associatedRows":["ConvPoint - NoColor","ConvPoint - Fusion","HDGCN","-"],"associatedColumns":["third best .","wind . door chair table book . sofa board clut .","Man made Natural High veg . Low veg . Buildings Hard scape Artefacts","Ground Building Pole Bollard Trash can Barrier Pedestrian"],"associatedMergedColumns":["( c ) NPM3D"]},{"number":"0.216","isBolded":false,"associatedRows":["TMLC - MS [ 22 ]","MSRRNetCRF","-","-"],"associatedColumns":["third best .","wind . door chair table book . sofa board clut .","Man made Natural High veg . Low veg . Buildings Hard scape Artefacts"],"associatedMergedColumns":["( b ) Semantic8"]},{"number":"83.8","isBolded":false,"associatedRows":["ConvPoint - NoColor","ConvPoint - Fusion","EdConvE","-"],"associatedColumns":["third best .","wind . door chair table book . sofa board clut .","Man made Natural High veg . Low veg . Buildings Hard scape Artefacts","Natural"],"associatedMergedColumns":["( c ) NPM3D"]},{"number":"47.8","isBolded":false,"associatedRows":["ConvPoint - Fusion","ConvPoint - Fusion","RFMSSF","-"],"associatedColumns":["second best","floor wall beam","Man made Natural High veg . Low veg . Buildings Hard scape Artefacts","Ground Building Pole Bollard Trash can Barrier Pedestrian"],"associatedMergedColumns":["( c ) NPM3D"]},{"number":"51.2","isBolded":false,"associatedRows":["ConvPoint - NoColor","MSRRNetCRF","-","-"],"associatedColumns":["third best .","wind . door chair table book . sofa board clut ."],"associatedMergedColumns":["( a ) S3DIS"]},{"number":"49.9","isBolded":false,"associatedRows":["ConvPoint - NoColor","ConvPoint - Fusion","EdConvE","-"],"associatedColumns":["third best .","wind . door chair table book . sofa board clut .","Man made Natural High veg . Low veg . Buildings Hard scape Artefacts","Ground Building Pole Bollard Trash can Barrier Pedestrian"],"associatedMergedColumns":["( c ) NPM3D"]},{"number":"25.7","isBolded":false,"associatedRows":["ConvPoint - Fusion","ConvPoint - Fusion","HDGCN","-"],"associatedColumns":["third best .","wind . door chair table book . sofa board clut .","Man made Natural High veg . Low veg . Buildings Hard scape Artefacts","Ground Building Pole Bollard Trash can Barrier Pedestrian"],"associatedMergedColumns":["( c ) NPM3D"]},{"number":"89.6","isBolded":false,"associatedRows":["ConvPoint - NoColor","ConvPoint - Fusion","HDGCN","-"],"associatedColumns":["third best .","wind . door chair table book . sofa board clut .","Man made Natural High veg . Low veg . Buildings Hard scape Artefacts","Natural"],"associatedMergedColumns":["( c ) NPM3D"]},{"number":"0.759","isBolded":false,"associatedRows":["PointNet++ [ 40 ]","MSRRNetCRF","-","-"],"associatedColumns":["third best .","wind . door chair table book . sofa board clut .","Man made Natural High veg . Low veg . Buildings Hard scape Artefacts"],"associatedMergedColumns":["( b ) Semantic8"]},{"number":"75.9","isBolded":false,"associatedRows":["PCCN [ 52 ]","MSRRNetCRF","-","-"],"associatedColumns":["second best","floor wall beam"],"associatedMergedColumns":["( a ) S3DIS"]},{"number":"0.962","isBolded":false,"associatedRows":["ConvPoint - NoColor","ConvPoint - Fusion","MSRRNetCRF","-"],"associatedColumns":["third best .","wind . door chair table book . sofa board clut .","Man made Natural High veg . Low veg . Buildings Hard scape Artefacts"],"associatedMergedColumns":["( b ) Semantic8"]},{"number":"8.7","isBolded":false,"associatedRows":["SPGraph [ 26 ]","MSRRNetCRF","-","-"],"associatedColumns":["third best .","wind . door chair table book . sofa board clut ."],"associatedMergedColumns":["( a ) S3DIS"]},{"number":"45.9","isBolded":false,"associatedRows":["SPGraph [ 26 ]","MSRRNetCRF","-","-"],"associatedColumns":["third best .","wind . door chair table book . sofa board clut ."],"associatedMergedColumns":["( a ) S3DIS"]},{"number":"92.8","isBolded":false,"associatedRows":["ConvPoint - NoColor","MSRRNetCRF","-","-"],"associatedColumns":["Best score ,","ceil ."],"associatedMergedColumns":["( a ) S3DIS"]},{"number":"88.7","isBolded":false,"associatedRows":["ConvPoint - Fusion","ConvPoint - Fusion","-"],"associatedColumns":["and","floor wall beam","Man made Natural High veg . Low veg . Buildings Hard scape Artefacts","Ground Building Pole Bollard Trash can Barrier Pedestrian"],"associatedMergedColumns":["( c ) NPM3D"]},{"number":"0.674","isBolded":false,"associatedRows":["SnapNet [ 12 ]","MSRRNetCRF","-"],"associatedColumns":["Best score ,","OA","mIoU"],"associatedMergedColumns":["( b ) Semantic8"]},{"number":"57.2","isBolded":false,"associatedRows":["PointCNN [ 29 ]","MSRRNetCRF","-","-"],"associatedColumns":["third best .","wind . door chair table book . sofa board clut ."],"associatedMergedColumns":["( a ) S3DIS"]},{"number":"0.927","isBolded":false,"associatedRows":["ConvPoint - NoColor","ConvPoint - Fusion","MSRRNetCRF","-"],"associatedColumns":["Best score ,","mAcc mIoU","OA"],"associatedMergedColumns":["( b ) Semantic8"]},{"number":"0.750","isBolded":false,"associatedRows":["ConvPoint - RGB","MSRRNetCRF","-"],"associatedColumns":["Best score ,","OA","mIoU"],"associatedMergedColumns":["( b ) Semantic8"]},{"number":"71.0","isBolded":false,"associatedRows":["ConvPoint - NoColor","MSRRNetCRF","-","-"],"associatedColumns":["third best .","wind . door chair table book . sofa board clut ."],"associatedMergedColumns":["( a ) S3DIS"]},{"number":"65.0","isBolded":false,"associatedRows":["ConvPoint - Fusion","MSRRNetCRF","-","-"],"associatedColumns":["third best .","wind . door chair table book . sofa board clut ."],"associatedMergedColumns":["( a ) S3DIS"]},{"number":"63.2","isBolded":false,"associatedRows":["SPGraph [ 26 ]","MSRRNetCRF","-","-"],"associatedColumns":["third best .","wind . door chair table book . sofa board clut ."],"associatedMergedColumns":["( a ) S3DIS"]},{"number":"0.760","isBolded":false,"associatedRows":["ConvPoint - Fusion","ConvPoint - Fusion","MSRRNetCRF","-"],"associatedColumns":["second best","floor wall beam","Man made Natural High veg . Low veg . Buildings Hard scape Artefacts"],"associatedMergedColumns":["( b ) Semantic8"]},{"number":"47.6","isBolded":false,"associatedRows":["ConvPoint - RGB","MSRRNetCRF","-","-"],"associatedColumns":["third best .","wind . door chair table book . sofa board clut ."],"associatedMergedColumns":["( a ) S3DIS"]},{"number":"0.631","isBolded":false,"associatedRows":["PointNet++ [ 40 ]","MSRRNetCRF","-"],"associatedColumns":["Best score ,","OA","mIoU"],"associatedMergedColumns":["( b ) Semantic8"]},{"number":"98.2","isBolded":false,"associatedRows":["ConvPoint - Fusion","ConvPoint - Fusion","MSRRNetCRF","-"],"associatedColumns":["Best score ,","floor wall beam","Man made Natural High veg . Low veg . Buildings Hard scape Artefacts","Ground Building Pole Bollard Trash can Barrier Pedestrian"],"associatedMergedColumns":["( c ) NPM3D"]},{"number":"99.3","isBolded":false,"associatedRows":["ConvPoint - Fusion","ConvPoint - Fusion","RFMSSF","-"],"associatedColumns":["Best score ,","mAcc mIoU","Man made Natural High veg . Low veg . Buildings Hard scape Artefacts","Ground Building Pole Bollard Trash can Barrier Pedestrian"],"associatedMergedColumns":["( c ) NPM3D"]},{"number":"66.2","isBolded":false,"associatedRows":["Pointnet [ 38 ]","MSRRNetCRF","-"],"associatedColumns":["Best score ,","mAcc mIoU"],"associatedMergedColumns":["( a ) S3DIS"]},{"number":"44.9","isBolded":false,"associatedRows":["RSNet [ 23 ]","MSRRNetCRF","-","-"],"associatedColumns":["third best .","wind . door chair table book . sofa board clut ."],"associatedMergedColumns":["( a ) S3DIS"]},{"number":"79.1","isBolded":false,"associatedRows":["KPConv [ 49 ]","MSRRNetCRF","-"],"associatedColumns":["Best score ,","mAcc mIoU"],"associatedMergedColumns":["( a ) S3DIS"]},{"number":"43.8","isBolded":false,"associatedRows":["ConvPoint - NoColor","MSRRNetCRF","-","-"],"associatedColumns":["and","col ."],"associatedMergedColumns":["( a ) S3DIS"]},{"number":"0.412","isBolded":false,"associatedRows":["TML - PC [ 37 ]","MSRRNetCRF","-","-"],"associatedColumns":["third best .","wind . door chair table book . sofa board clut .","Man made Natural High veg . Low veg . Buildings Hard scape Artefacts"],"associatedMergedColumns":["( b ) Semantic8"]},{"number":"61.2","isBolded":false,"associatedRows":["PointCNN [ 29 ]","MSRRNetCRF","-","-"],"associatedColumns":["third best .","wind . door chair table book . sofa board clut ."],"associatedMergedColumns":["( a ) S3DIS"]},{"number":"74.9","isBolded":false,"associatedRows":["KPConv [ 49 ]","MSRRNetCRF","-","-"],"associatedColumns":["third best .","wind . door chair table book . sofa board clut ."],"associatedMergedColumns":["( a ) S3DIS"]},{"number":"0.442","isBolded":false,"associatedRows":["ConvPoint - NoColor","ConvPoint - Fusion","MSRRNetCRF","-"],"associatedColumns":["third best .","wind . door chair table book . sofa board clut .","Man made Natural High veg . Low veg . Buildings Hard scape Artefacts"],"associatedMergedColumns":["( b ) Semantic8"]},{"number":"92.3","isBolded":false,"associatedRows":["PCCN [ 52 ]","MSRRNetCRF","-","-"],"associatedColumns":["Best score ,","ceil ."],"associatedMergedColumns":["( a ) S3DIS"]},{"number":"83.1","isBolded":false,"associatedRows":["KPConv [ 49 ]","MSRRNetCRF","-","-"],"associatedColumns":["second best","floor wall beam"],"associatedMergedColumns":["( a ) S3DIS"]},{"number":"81.9","isBolded":false,"associatedRows":["ConvPoint - NoColor","ConvPoint - Fusion","HDGCN","-"],"associatedColumns":["third best .","wind . door chair table book . sofa board clut .","Man made Natural High veg . Low veg . Buildings Hard scape Artefacts","Car"],"associatedMergedColumns":["( c ) NPM3D"]},{"number":"0.647","isBolded":false,"associatedRows":["TML - PC [ 37 ]","MSRRNetCRF","-","-"],"associatedColumns":["third best .","wind . door chair table book . sofa board clut .","Man made Natural High veg . Low veg . Buildings Hard scape Artefacts"],"associatedMergedColumns":["( b ) Semantic8"]},{"number":"0.661","isBolded":false,"associatedRows":["TML - PC [ 37 ]","MSRRNetCRF","-","-"],"associatedColumns":["second best","floor wall beam","Man made Natural High veg . Low veg . Buildings Hard scape Artefacts"],"associatedMergedColumns":["( b ) Semantic8"]},{"number":"56.3","isBolded":false,"associatedRows":["ConvPoint - Fusion","ConvPoint - Fusion","RFMSSF"],"associatedColumns":["Best score ,","mAcc mIoU","mIoU","mIoU"],"associatedMergedColumns":["( c ) NPM3D"]},{"number":"85.5","isBolded":false,"associatedRows":["SPGraph [ 26 ]","EdConvE"],"associatedColumns":["Best score ,","OA"],"associatedMergedColumns":["( a ) S3DIS"]},{"number":"97.7","isBolded":false,"associatedRows":["ConvPoint - RGB","MSRRNetCRF","-","-"],"associatedColumns":["Best score ,","floor wall beam"],"associatedMergedColumns":["( a ) S3DIS"]},{"number":"75.7","isBolded":false,"associatedRows":["ConvPoint - Fusion","ConvPoint - Fusion","HDGCN","-"],"associatedColumns":["and","floor wall beam","Man made Natural High veg . Low veg . Buildings Hard scape Artefacts","Ground Building Pole Bollard Trash can Barrier Pedestrian"],"associatedMergedColumns":["( c ) NPM3D"]},{"number":"0.788","isBolded":false,"associatedRows":["ConvPoint - NoColor","ConvPoint - Fusion","MSRRNetCRF","-"],"associatedColumns":["second best","floor wall beam","Man made Natural High veg . Low veg . Buildings Hard scape Artefacts"],"associatedMergedColumns":["( b ) Semantic8"]},{"number":"0.494","isBolded":false,"associatedRows":["TMLC - MS [ 22 ]","MSRRNetCRF","-"],"associatedColumns":["Best score ,","OA","mIoU"],"associatedMergedColumns":["( b ) Semantic8"]},{"number":"67.3","isBolded":false,"associatedRows":["ConvPoint - Fusion","ConvPoint - Fusion","RFMSSF","-"],"associatedColumns":["and","floor wall beam","Man made Natural High veg . Low veg . Buildings Hard scape Artefacts","Ground Building Pole Bollard Trash can Barrier Pedestrian"],"associatedMergedColumns":["( c ) NPM3D"]},{"number":"62.1","isBolded":false,"associatedRows":["SPGraph [ 26 ]","MSRRNetCRF","-","-"],"associatedColumns":["Best score ,","mAcc mIoU"],"associatedMergedColumns":["( a ) S3DIS"]},{"number":"0.909","isBolded":false,"associatedRows":["SnapNet [ 12 ]","MSRRNetCRF","-","-"],"associatedColumns":["third best .","wind . door chair table book . sofa board clut .","Man made Natural High veg . Low veg . Buildings Hard scape Artefacts"],"associatedMergedColumns":["( b ) Semantic8"]},{"number":"0.611","isBolded":false,"associatedRows":["ConvPoint - Fusion","ConvPoint - Fusion","MSRRNetCRF","-"],"associatedColumns":["third best .","wind . door chair table book . sofa board clut .","Man made Natural High veg . Low veg . Buildings Hard scape Artefacts"],"associatedMergedColumns":["( b ) Semantic8"]},{"number":"52.6","isBolded":false,"associatedRows":["ConvPoint - NoColor","ConvPoint - Fusion","MS3DVS","-"],"associatedColumns":["third best .","wind . door chair table book . sofa board clut .","Man made Natural High veg . Low veg . Buildings Hard scape Artefacts","Ground Building Pole Bollard Trash can Barrier Pedestrian"],"associatedMergedColumns":["( c ) NPM3D"]},{"number":"82.0","isBolded":false,"associatedRows":["ConvPoint - Fusion","ConvPoint - Fusion","KP - FCNN [ 49 ]"],"associatedColumns":["Best score ,","mAcc mIoU","mIoU","mIoU"],"associatedMergedColumns":["( c ) NPM3D"]},{"number":"52.2","isBolded":false,"associatedRows":["PointCNN [ 29 ]","MSRRNetCRF","-","-"],"associatedColumns":["third best .","wind . door chair table book . sofa board clut ."],"associatedMergedColumns":["( a ) S3DIS"]},{"number":"0.726","isBolded":false,"associatedRows":["ConvPoint - NoColor","MSRRNetCRF","-"],"associatedColumns":["Best score ,","OA","mIoU"],"associatedMergedColumns":["( b ) Semantic8"]},{"number":"6.0","isBolded":false,"associatedRows":["PCCN [ 52 ]","MSRRNetCRF","-","-"],"associatedColumns":["and","col ."],"associatedMergedColumns":["( a ) S3DIS"]},{"number":"0.27","isBolded":false,"associatedRows":["PCCN [ 52 ]","MSRRNetCRF","-","-"],"associatedColumns":["second best","floor wall beam"],"associatedMergedColumns":["( a ) S3DIS"]},{"number":"52.9","isBolded":false,"associatedRows":["SPGraph [ 26 ]","MSRRNetCRF","-","-"],"associatedColumns":["third best .","wind . door chair table book . sofa board clut ."],"associatedMergedColumns":["( a ) S3DIS"]},{"number":"71.6","isBolded":false,"associatedRows":["PointCNN [ 29 ]","MSRRNetCRF","-","-"],"associatedColumns":["third best .","wind . door chair table book . sofa board clut ."],"associatedMergedColumns":["( a ) S3DIS"]},{"number":"88.7","isBolded":false,"associatedRows":["Pointnet [ 38 ]","MSRRNetCRF","-","-"],"associatedColumns":["Best score ,","floor wall beam"],"associatedMergedColumns":["( a ) S3DIS"]},{"number":"0.944","isBolded":false,"associatedRows":["SPGraph [ 26 ]","MSRRNetCRF","-","-"],"associatedColumns":["third best .","wind . door chair table book . sofa board clut .","Man made Natural High veg . Low veg . Buildings Hard scape Artefacts"],"associatedMergedColumns":["( b ) Semantic8"]},{"number":"73.2","isBolded":false,"associatedRows":["ConvPoint - Fusion","MSRRNetCRF","-","-"],"associatedColumns":["third best .","wind . door chair table book . sofa board clut ."],"associatedMergedColumns":["( a ) S3DIS"]},{"number":"64.7","isBolded":false,"associatedRows":["ConvPoint - RGB","MSRRNetCRF","-","-"],"associatedColumns":["Best score ,","mAcc mIoU"],"associatedMergedColumns":["( a ) S3DIS"]},{"number":"94.0","isBolded":false,"associatedRows":["ConvPoint - Fusion","ConvPoint - Fusion","KP - FCNN [ 49 ]","-"],"associatedColumns":["Best score ,","floor wall beam","Man made Natural High veg . Low veg . Buildings Hard scape Artefacts","Ground Building Pole Bollard Trash can Barrier Pedestrian"],"associatedMergedColumns":["( c ) NPM3D"]},{"number":"54.3","isBolded":false,"associatedRows":["KPConv [ 49 ]","MSRRNetCRF","-","-"],"associatedColumns":["and","col ."],"associatedMergedColumns":["( a ) S3DIS"]},{"number":"95.0","isBolded":false,"associatedRows":["ConvPoint - Fusion","MSRRNetCRF","-","-"],"associatedColumns":["Best score ,","ceil ."],"associatedMergedColumns":["( a ) S3DIS"]},{"number":"0.877","isBolded":false,"associatedRows":["ConvPoint - Fusion","ConvPoint - Fusion","MSRRNetCRF","-"],"associatedColumns":["third best .","wind . door chair table book . sofa board clut .","Cars"],"associatedMergedColumns":["( b ) Semantic8"]},{"number":"0.921","isBolded":false,"associatedRows":["ConvPoint - Fusion","ConvPoint - Fusion","MSRRNetCRF","-"],"associatedColumns":["Best score ,","ceil .","Man made Natural High veg . Low veg . Buildings Hard scape Artefacts"],"associatedMergedColumns":["( b ) Semantic8"]},{"number":"0.726","isBolded":false,"associatedRows":["PointNet++ [ 40 ]","MSRRNetCRF","-","-"],"associatedColumns":["third best .","wind . door chair table book . sofa board clut .","Cars"],"associatedMergedColumns":["( b ) Semantic8"]},{"number":"38.1","isBolded":false,"associatedRows":["ConvPoint - Fusion","ConvPoint - Fusion","MS3DVS","-"],"associatedColumns":["and","floor wall beam","Man made Natural High veg . Low veg . Buildings Hard scape Artefacts","Ground Building Pole Bollard Trash can Barrier Pedestrian"],"associatedMergedColumns":["( c ) NPM3D"]},{"number":"67.0","isBolded":false,"associatedRows":["PCCN [ 52 ]","MSRRNetCRF","-"],"associatedColumns":["Best score ,","mAcc mIoU"],"associatedMergedColumns":["( a ) S3DIS"]},{"number":"0.568","isBolded":false,"associatedRows":["SPGraph [ 26 ]","MSRRNetCRF","-","-"],"associatedColumns":["third best .","wind . door chair table book . sofa board clut .","Man made Natural High veg . Low veg . Buildings Hard scape Artefacts"],"associatedMergedColumns":["( b ) Semantic8"]},{"number":"92.5","isBolded":false,"associatedRows":["RSNet [ 23 ]","MSRRNetCRF","-","-"],"associatedColumns":["Best score ,","ceil ."],"associatedMergedColumns":["( a ) S3DIS"]},{"number":"47.6","isBolded":false,"associatedRows":["Pointnet [ 38 ]","MSRRNetCRF","-","-"],"associatedColumns":["Best score ,","mAcc mIoU"],"associatedMergedColumns":["( a ) S3DIS"]},{"number":"0.795","isBolded":false,"associatedRows":["SnapNet [ 12 ]","MSRRNetCRF","-","-"],"associatedColumns":["second best","floor wall beam","Man made Natural High veg . Low veg . Buildings Hard scape Artefacts"],"associatedMergedColumns":["( b ) Semantic8"]},{"number":"93.6","isBolded":false,"associatedRows":["KPConv [ 49 ]","MSRRNetCRF","-","-"],"associatedColumns":["Best score ,","ceil ."],"associatedMergedColumns":["( a ) S3DIS"]},{"number":"0.474","isBolded":false,"associatedRows":["ConvPoint - RGB","ConvPoint - Fusion","MSRRNetCRF","-"],"associatedColumns":["third best .","wind . door chair table book . sofa board clut .","Man made Natural High veg . Low veg . Buildings Hard scape Artefacts"],"associatedMergedColumns":["( b ) Semantic8"]},{"number":"57.8","isBolded":false,"associatedRows":["KPConv [ 49 ]","MSRRNetCRF","-","-"],"associatedColumns":["third best .","wind . door chair table book . sofa board clut ."],"associatedMergedColumns":["( a ) S3DIS"]},{"number":"47.1","isBolded":false,"associatedRows":["SPGraph [ 26 ]","MSRRNetCRF","-","-"],"associatedColumns":["and","col ."],"associatedMergedColumns":["( a ) S3DIS"]},{"number":"61.3","isBolded":false,"associatedRows":["KPConv [ 49 ]","MSRRNetCRF","-","-"],"associatedColumns":["third best .","wind . door chair table book . sofa board clut ."],"associatedMergedColumns":["( a ) S3DIS"]},{"number":"73.5","isBolded":false,"associatedRows":["SPGraph [ 26 ]","MSRRNetCRF","-","-"],"associatedColumns":["third best .","wind . door chair table book . sofa board clut ."],"associatedMergedColumns":["( a ) S3DIS"]},{"number":"0.806","isBolded":false,"associatedRows":["ConvPoint - Fusion","ConvPoint - Fusion","MSRRNetCRF","-"],"associatedColumns":["second best","floor wall beam","Man made Natural High veg . Low veg . Buildings Hard scape Artefacts"],"associatedMergedColumns":["( b ) Semantic8"]},{"number":"59.2","isBolded":false,"associatedRows":["ConvPoint - Fusion","MSRRNetCRF","-","-"],"associatedColumns":["third best .","wind . door chair table book . sofa board clut ."],"associatedMergedColumns":["( a ) S3DIS"]},{"number":"23.1","isBolded":false,"associatedRows":["Pointnet [ 38 ]","MSRRNetCRF","-","-"],"associatedColumns":["and","col ."],"associatedMergedColumns":["( a ) S3DIS"]},{"number":"89.5","isBolded":false,"associatedRows":["ConvPoint - NoColor","ConvPoint - Fusion","MSRRNetCRF","-"],"associatedColumns":["third best .","wind . door chair table book . sofa board clut .","Man made Natural High veg . Low veg . Buildings Hard scape Artefacts","Natural"],"associatedMergedColumns":["( c ) NPM3D"]},{"number":"0.000","isBolded":false,"associatedRows":["TML - PC [ 37 ]","MSRRNetCRF","-","-"],"associatedColumns":["third best .","wind . door chair table book . sofa board clut .","Man made Natural High veg . Low veg . Buildings Hard scape Artefacts"],"associatedMergedColumns":["( b ) Semantic8"]},{"number":"52.9","isBolded":false,"associatedRows":["ConvPoint - Fusion","ConvPoint - Fusion","-"],"associatedColumns":["third best .","wind . door chair table book . sofa board clut .","Man made Natural High veg . Low veg . Buildings Hard scape Artefacts","Ground Building Pole Bollard Trash can Barrier Pedestrian"],"associatedMergedColumns":["( c ) NPM3D"]},{"number":"35.2","isBolded":false,"associatedRows":["Pointnet [ 38 ]","MSRRNetCRF","-","-"],"associatedColumns":["third best .","wind . door chair table book . sofa board clut ."],"associatedMergedColumns":["( a ) S3DIS"]},{"number":"76.7","isBolded":false,"associatedRows":["ConvPoint - NoColor","MSRRNetCRF","-","-"],"associatedColumns":["second best","floor wall beam"],"associatedMergedColumns":["( a ) S3DIS"]},{"number":"81.7","isBolded":false,"associatedRows":["ConvPoint - Fusion","MSRRNetCRF","-","-"],"associatedColumns":["second best","floor wall beam"],"associatedMergedColumns":["( a ) S3DIS"]},{"number":"0.259","isBolded":false,"associatedRows":["TMLC - MS [ 22 ]","MSRRNetCRF","-","-"],"associatedColumns":["third best .","wind . door chair table book . sofa board clut .","Man made Natural High veg . Low veg . Buildings Hard scape Artefacts"],"associatedMergedColumns":["( b ) Semantic8"]},{"number":"0.391","isBolded":false,"associatedRows":["TML - PC [ 37 ]","MSRRNetCRF","-"],"associatedColumns":["Best score ,","OA","mIoU"],"associatedMergedColumns":["( b ) Semantic8"]},{"number":"66.9","isBolded":false,"associatedRows":["ConvPoint - Fusion","ConvPoint - Fusion","MS3DVS"],"associatedColumns":["Best score ,","mAcc mIoU","mIoU","mIoU"],"associatedMergedColumns":["( c ) NPM3D"]},{"number":"75.9","isBolded":false,"associatedRows":["ConvPoint - Fusion","ConvPoint - Fusion"],"associatedColumns":["Best score ,","mAcc mIoU","mIoU","mIoU"],"associatedMergedColumns":["( c ) NPM3D"]},{"number":"54.1","isBolded":false,"associatedRows":["Pointnet [ 38 ]","MSRRNetCRF","-","-"],"associatedColumns":["third best .","wind . door chair table book . sofa board clut ."],"associatedMergedColumns":["( a ) S3DIS"]},{"number":"87.9","isBolded":false,"associatedRows":["ConvPoint - RGB","EdConvE"],"associatedColumns":["Best score ,","OA"],"associatedMergedColumns":["( a ) S3DIS"]},{"number":"66.5","isBolded":false,"associatedRows":["RSNet [ 23 ]","MSRRNetCRF","-"],"associatedColumns":["Best score ,","mAcc mIoU"],"associatedMergedColumns":["( a ) S3DIS"]},{"number":"0.915","isBolded":false,"associatedRows":["SPGraph [ 26 ]","MSRRNetCRF","-","-"],"associatedColumns":["Best score ,","ceil .","Man made Natural High veg . Low veg . Buildings Hard scape Artefacts"],"associatedMergedColumns":["( b ) Semantic8"]},{"number":"0.934","isBolded":false,"associatedRows":["ConvPoint - Fusion","ConvPoint - Fusion","MSRRNetCRF","-"],"associatedColumns":["Best score ,","mAcc mIoU","OA"],"associatedMergedColumns":["( b ) Semantic8"]},{"number":"46.7","isBolded":false,"associatedRows":["ConvPoint - Fusion","ConvPoint - Fusion","-"],"associatedColumns":["third best .","wind . door chair table book . sofa board clut .","Man made Natural High veg . Low veg . Buildings Hard scape Artefacts","Ground Building Pole Bollard Trash can Barrier Pedestrian"],"associatedMergedColumns":["( c ) NPM3D"]},{"number":"0.748","isBolded":false,"associatedRows":["SnapNet [ 12 ]","MSRRNetCRF","-","-"],"associatedColumns":["second best","floor wall beam","Man made Natural High veg . Low veg . Buildings Hard scape Artefacts"],"associatedMergedColumns":["( b ) Semantic8"]},{"number":"99.5","isBolded":false,"associatedRows":["ConvPoint - Fusion","ConvPoint - Fusion","KP - FCNN [ 49 ]","-"],"associatedColumns":["Best score ,","mAcc mIoU","Man made Natural High veg . Low veg . Buildings Hard scape Artefacts","Ground Building Pole Bollard Trash can Barrier Pedestrian"],"associatedMergedColumns":["( c ) NPM3D"]},{"number":"91.3","isBolded":false,"associatedRows":["ConvPoint - NoColor","ConvPoint - Fusion","MS3DVS","-"],"associatedColumns":["third best .","wind . door chair table book . sofa board clut .","Man made Natural High veg . Low veg . Buildings Hard scape Artefacts","Car"],"associatedMergedColumns":["( c ) NPM3D"]},{"number":"74.8","isBolded":false,"associatedRows":["ConvPoint - NoColor","ConvPoint - Fusion","RFMSSF","-"],"associatedColumns":["third best .","wind . door chair table book . sofa board clut .","Man made Natural High veg . Low veg . Buildings Hard scape Artefacts","Car"],"associatedMergedColumns":["( c ) NPM3D"]},{"number":"58.3","isBolded":false,"associatedRows":["PCCN [ 52 ]","MSRRNetCRF","-","-"],"associatedColumns":["Best score ,","mAcc mIoU"],"associatedMergedColumns":["( a ) S3DIS"]},{"number":"42.0","isBolded":false,"associatedRows":["Pointnet [ 38 ]","MSRRNetCRF","-","-"],"associatedColumns":["third best .","wind . door chair table book . sofa board clut ."],"associatedMergedColumns":["( a ) S3DIS"]},{"number":"80.0","isBolded":false,"associatedRows":["ConvPoint - RGB","MSRRNetCRF","-","-"],"associatedColumns":["second best","floor wall beam"],"associatedMergedColumns":["( a ) S3DIS"]},{"number":"20.6","isBolded":false,"associatedRows":["ConvPoint - NoColor","ConvPoint - Fusion","RFMSSF","-"],"associatedColumns":["third best .","wind . door chair table book . sofa board clut .","Man made Natural High veg . Low veg . Buildings Hard scape Artefacts","Ground Building Pole Bollard Trash can Barrier Pedestrian"],"associatedMergedColumns":["( c ) NPM3D"]},{"number":"0.783","isBolded":false,"associatedRows":["SPGraph [ 26 ]","MSRRNetCRF","-","-"],"associatedColumns":["second best","floor wall beam","Man made Natural High veg . Low veg . Buildings Hard scape Artefacts"],"associatedMergedColumns":["( b ) Semantic8"]},{"number":"94.8","isBolded":false,"associatedRows":["ConvPoint - Fusion","ConvPoint - Fusion","MS3DVS","-"],"associatedColumns":["Best score ,","floor wall beam","Man made Natural High veg . Low veg . Buildings Hard scape Artefacts","Ground Building Pole Bollard Trash can Barrier Pedestrian"],"associatedMergedColumns":["( c ) NPM3D"]},{"number":"95.1","isBolded":false,"associatedRows":["SPGraph [ 26 ]","MSRRNetCRF","-","-"],"associatedColumns":["Best score ,","floor wall beam"],"associatedMergedColumns":["( a ) S3DIS"]},{"number":"64.9","isBolded":false,"associatedRows":["ConvPoint - Fusion","MSRRNetCRF","-","-"],"associatedColumns":["third best .","wind . door chair table book . sofa board clut ."],"associatedMergedColumns":["( a ) S3DIS"]},{"number":"0.748","isBolded":false,"associatedRows":["ConvPoint - NoColor","ConvPoint - Fusion","MSRRNetCRF","-"],"associatedColumns":["second best","floor wall beam","Man made Natural High veg . Low veg . Buildings Hard scape Artefacts"],"associatedMergedColumns":["( b ) Semantic8"]},{"number":"63.3","isBolded":false,"associatedRows":["PointCNN [ 29 ]","MSRRNetCRF","-","-"],"associatedColumns":["second best","floor wall beam"],"associatedMergedColumns":["( a ) S3DIS"]},{"number":"17.7","isBolded":false,"associatedRows":["ConvPoint - RGB","MSRRNetCRF","-","-"],"associatedColumns":["and","col ."],"associatedMergedColumns":["( a ) S3DIS"]},{"number":"97.3","isBolded":false,"associatedRows":["PointCNN [ 29 ]","MSRRNetCRF","-","-"],"associatedColumns":["Best score ,","floor wall beam"],"associatedMergedColumns":["( a ) S3DIS"]},{"number":"59.7","isBolded":false,"associatedRows":["RSNet [ 23 ]","MSRRNetCRF","-","-"],"associatedColumns":["third best .","wind . door chair table book . sofa board clut ."],"associatedMergedColumns":["( a ) S3DIS"]},{"number":"0.911","isBolded":false,"associatedRows":["TMLC - MS [ 22 ]","MSRRNetCRF","-","-"],"associatedColumns":["Best score ,","ceil .","Man made Natural High veg . Low veg . Buildings Hard scape Artefacts"],"associatedMergedColumns":["( b ) Semantic8"]},{"number":"0.910","isBolded":false,"associatedRows":["SnapNet [ 12 ]","MSRRNetCRF","-","-"],"associatedColumns":["Best score ,","mAcc mIoU","OA"],"associatedMergedColumns":["( b ) Semantic8"]},{"number":"64.8","isBolded":false,"associatedRows":["ConvPoint - NoColor","ConvPoint - Fusion","MSRRNetCRF","-"],"associatedColumns":["third best .","wind . door chair table book . sofa board clut .","Man made Natural High veg . Low veg . Buildings Hard scape Artefacts","Ground Building Pole Bollard Trash can Barrier Pedestrian"],"associatedMergedColumns":["( c ) NPM3D"]},{"number":"0.896","isBolded":false,"associatedRows":["SnapNet [ 12 ]","MSRRNetCRF","-","-"],"associatedColumns":["Best score ,","ceil .","Man made Natural High veg . Low veg . Buildings Hard scape Artefacts"],"associatedMergedColumns":["( b ) Semantic8"]},{"number":"53.5","isBolded":false,"associatedRows":["ConvPoint - Fusion","ConvPoint - Fusion","-"],"associatedColumns":["third best .","wind . door chair table book . sofa board clut .","Man made Natural High veg . Low veg . Buildings Hard scape Artefacts","Ground Building Pole Bollard Trash can Barrier Pedestrian"],"associatedMergedColumns":["( c ) NPM3D"]},{"number":"0.706","isBolded":false,"associatedRows":["ConvPoint - RGB","ConvPoint - Fusion","MSRRNetCRF","-"],"associatedColumns":["third best .","wind . door chair table book . sofa board clut .","Man made Natural High veg . Low veg . Buildings Hard scape Artefacts"],"associatedMergedColumns":["( b ) Semantic8"]},{"number":"42.4","isBolded":false,"associatedRows":["Pointnet [ 38 ]","MSRRNetCRF","-","-"],"associatedColumns":["second best","floor wall beam"],"associatedMergedColumns":["( a ) S3DIS"]},{"number":"75.8","isBolded":false,"associatedRows":["PointCNN [ 29 ]","MSRRNetCRF","-","-"],"associatedColumns":["second best","floor wall beam"],"associatedMergedColumns":["( a ) S3DIS"]},{"number":"0.745","isBolded":false,"associatedRows":["TML - PC [ 37 ]","MSRRNetCRF","-","-"],"associatedColumns":["Best score ,","mAcc mIoU","OA"],"associatedMergedColumns":["( b ) Semantic8"]},{"number":"0.365","isBolded":false,"associatedRows":["SnapNet [ 12 ]","MSRRNetCRF","-","-"],"associatedColumns":["third best .","wind . door chair table book . sofa board clut .","Man made Natural High veg . Low veg . Buildings Hard scape Artefacts"],"associatedMergedColumns":["( b ) Semantic8"]},{"number":"78.8","isBolded":false,"associatedRows":["ConvPoint - NoColor","ConvPoint - Fusion","RFMSSF","-"],"associatedColumns":["third best .","wind . door chair table book . sofa board clut .","Man made Natural High veg . Low veg . Buildings Hard scape Artefacts","Natural"],"associatedMergedColumns":["( c ) NPM3D"]},{"number":"88.1","isBolded":false,"associatedRows":["PointCNN [ 29 ]","EdConvE"],"associatedColumns":["Best score ,","OA"],"associatedMergedColumns":["( a ) S3DIS"]},{"number":"88.6","isBolded":false,"associatedRows":["ConvPoint - Fusion","ConvPoint - Fusion","RFMSSF","-"],"associatedColumns":["Best score ,","floor wall beam","Man made Natural High veg . Low veg . Buildings Hard scape Artefacts","Ground Building Pole Bollard Trash can Barrier Pedestrian"],"associatedMergedColumns":["( c ) NPM3D"]},{"number":"54.7","isBolded":false,"associatedRows":["ConvPoint - NoColor","MSRRNetCRF","-","-"],"associatedColumns":["third best .","wind . door chair table book . sofa board clut ."],"associatedMergedColumns":["( a ) S3DIS"]},{"number":"65.6","isBolded":false,"associatedRows":["PCCN [ 52 ]","MSRRNetCRF","-","-"],"associatedColumns":["third best .","wind . door chair table book . sofa board clut ."],"associatedMergedColumns":["( a ) S3DIS"]},{"number":"61.0","isBolded":false,"associatedRows":["ConvPoint - RGB","MSRRNetCRF","-","-"],"associatedColumns":["third best .","wind . door chair table book . sofa board clut ."],"associatedMergedColumns":["( a ) S3DIS"]},{"number":"73.0","isBolded":false,"associatedRows":["SPGraph [ 26 ]","MSRRNetCRF","-"],"associatedColumns":["Best score ,","mAcc mIoU"],"associatedMergedColumns":["( a ) S3DIS"]},{"number":"0.762","isBolded":false,"associatedRows":["SPGraph [ 26 ]","MSRRNetCRF","-"],"associatedColumns":["Best score ,","OA","mIoU"],"associatedMergedColumns":["( b ) Semantic8"]},{"number":"0.695","isBolded":false,"associatedRows":["TMLC - MS [ 22 ]","MSRRNetCRF","-","-"],"associatedColumns":["second best","floor wall beam","Man made Natural High veg . Low veg . Buildings Hard scape Artefacts"],"associatedMergedColumns":["( b ) Semantic8"]},{"number":"0.343","isBolded":false,"associatedRows":["SnapNet [ 12 ]","MSRRNetCRF","-","-"],"associatedColumns":["third best .","wind . door chair table book . sofa board clut .","Man made Natural High veg . Low veg . Buildings Hard scape Artefacts"],"associatedMergedColumns":["( b ) Semantic8"]},{"number":"69.3","isBolded":false,"associatedRows":["Pointnet [ 38 ]","MSRRNetCRF","-","-"],"associatedColumns":["second best","floor wall beam"],"associatedMergedColumns":["( a ) S3DIS"]},{"number":"78.2","isBolded":false,"associatedRows":["ConvPoint - NoColor","ConvPoint - Fusion","KP - FCNN [ 49 ]","-"],"associatedColumns":["third best .","wind . door chair table book . sofa board clut .","Man made Natural High veg . Low veg . Buildings Hard scape Artefacts","Ground Building Pole Bollard Trash can Barrier Pedestrian"],"associatedMergedColumns":["( c ) NPM3D"]},{"number":"69.5","isBolded":false,"associatedRows":["PCCN [ 52 ]","MSRRNetCRF","-","-"],"associatedColumns":["third best .","wind . door chair table book . sofa board clut ."],"associatedMergedColumns":["( a ) S3DIS"]},{"number":"62.8","isBolded":false,"associatedRows":["SPGraph [ 26 ]","MSRRNetCRF","-","-"],"associatedColumns":["second best","floor wall beam"],"associatedMergedColumns":["( a ) S3DIS"]},{"number":"65.4","isBolded":false,"associatedRows":["PointCNN [ 29 ]","MSRRNetCRF","-","-"],"associatedColumns":["Best score ,","mAcc mIoU"],"associatedMergedColumns":["( a ) S3DIS"]},{"number":"0.437","isBolded":false,"associatedRows":["PointNet++ [ 40 ]","MSRRNetCRF","-","-"],"associatedColumns":["third best .","wind . door chair table book . sofa board clut .","Man made Natural High veg . Low veg . Buildings Hard scape Artefacts"],"associatedMergedColumns":["( b ) Semantic8"]},{"number":"38.2","isBolded":false,"associatedRows":["ConvPoint - NoColor","ConvPoint - Fusion","EdConvE","-"],"associatedColumns":["third best .","wind . door chair table book . sofa board clut .","Man made Natural High veg . Low veg . Buildings Hard scape Artefacts","Ground Building Pole Bollard Trash can Barrier Pedestrian"],"associatedMergedColumns":["( c ) NPM3D"]},{"number":"0.113","isBolded":false,"associatedRows":["TMLC - MS [ 22 ]","MSRRNetCRF","-","-"],"associatedColumns":["third best .","wind . door chair table book . sofa board clut .","Man made Natural High veg . Low veg . Buildings Hard scape Artefacts"],"associatedMergedColumns":["( b ) Semantic8"]},{"number":"66.1","isBolded":false,"associatedRows":["KPConv [ 49 ]","MSRRNetCRF","-","-"],"associatedColumns":["third best .","wind . door chair table book . sofa board clut ."],"associatedMergedColumns":["( a ) S3DIS"]},{"number":"16.4","isBolded":false,"associatedRows":["RSNet [ 23 ]","MSRRNetCRF","-","-"],"associatedColumns":["third best .","wind . door chair table book . sofa board clut ."],"associatedMergedColumns":["( a ) S3DIS"]},{"number":"0.876","isBolded":false,"associatedRows":["TMLC - MS [ 22 ]","MSRRNetCRF","-","-"],"associatedColumns":["third best .","wind . door chair table book . sofa board clut .","Man made Natural High veg . Low veg . Buildings Hard scape Artefacts"],"associatedMergedColumns":["( b ) Semantic8"]},{"number":"54.8","isBolded":false,"associatedRows":["ConvPoint - NoColor","ConvPoint - Fusion","MSRRNetCRF","-"],"associatedColumns":["third best .","wind . door chair table book . sofa board clut .","Man made Natural High veg . Low veg . Buildings Hard scape Artefacts","Ground Building Pole Bollard Trash can Barrier Pedestrian"],"associatedMergedColumns":["( c ) NPM3D"]},{"number":"88.6","isBolded":false,"associatedRows":["ConvPoint - NoColor","ConvPoint - Fusion","MS3DVS","-"],"associatedColumns":["third best .","wind . door chair table book . sofa board clut .","Man made Natural High veg . Low veg . Buildings Hard scape Artefacts","Natural"],"associatedMergedColumns":["( c ) NPM3D"]},{"number":"0.517","isBolded":false,"associatedRows":["PointNet++ [ 40 ]","MSRRNetCRF","-","-"],"associatedColumns":["third best .","wind . door chair table book . sofa board clut .","Man made Natural High veg . Low veg . Buildings Hard scape Artefacts"],"associatedMergedColumns":["( b ) Semantic8"]},{"number":"78.7","isBolded":false,"associatedRows":["ConvPoint - Fusion","ConvPoint - Fusion","KP - FCNN [ 49 ]","-"],"associatedColumns":["third best .","wind . door chair table book . sofa board clut .","Man made Natural High veg . Low veg . Buildings Hard scape Artefacts","Ground Building Pole Bollard Trash can Barrier Pedestrian"],"associatedMergedColumns":["( c ) NPM3D"]},{"number":"0.765","isBolded":false,"associatedRows":["ConvPoint - Fusion","MSRRNetCRF","-"],"associatedColumns":["Best score ,","OA","mIoU"],"associatedMergedColumns":["( b ) Semantic8"]},{"number":"0.929","isBolded":false,"associatedRows":["SPGraph [ 26 ]","MSRRNetCRF","-","-"],"associatedColumns":["Best score ,","mAcc mIoU","OA"],"associatedMergedColumns":["( b ) Semantic8"]},{"number":"62.6","isBolded":false,"associatedRows":["ConvPoint - NoColor","MSRRNetCRF","-","-"],"associatedColumns":["Best score ,","mAcc mIoU"],"associatedMergedColumns":["( a ) S3DIS"]},{"number":"99.0","isBolded":false,"associatedRows":["ConvPoint - Fusion","ConvPoint - Fusion","MSRRNetCRF","-"],"associatedColumns":["Best score ,","mAcc mIoU","Man made Natural High veg . Low veg . Buildings Hard scape Artefacts","Ground Building Pole Bollard Trash can Barrier Pedestrian"],"associatedMergedColumns":["( c ) NPM3D"]},{"number":"32.8","isBolded":false,"associatedRows":["RSNet [ 23 ]","MSRRNetCRF","-","-"],"associatedColumns":["second best","floor wall beam"],"associatedMergedColumns":["( a ) S3DIS"]},{"number":"0.423","isBolded":false,"associatedRows":["TML - PC [ 37 ]","MSRRNetCRF","-","-"],"associatedColumns":["second best","floor wall beam","Man made Natural High veg . Low veg . Buildings Hard scape Artefacts"],"associatedMergedColumns":["( b ) Semantic8"]},{"number":"74.5","isBolded":false,"associatedRows":["ConvPoint - RGB","MSRRNetCRF","-","-"],"associatedColumns":["third best .","wind . door chair table book . sofa board clut ."],"associatedMergedColumns":["( a ) S3DIS"]},{"number":"0.756","isBolded":false,"associatedRows":["SPGraph [ 26 ]","MSRRNetCRF","-","-"],"associatedColumns":["second best","floor wall beam","Man made Natural High veg . Low veg . Buildings Hard scape Artefacts"],"associatedMergedColumns":["( b ) Semantic8"]},{"number":"47.5","isBolded":false,"associatedRows":["Pointnet [ 38 ]","MSRRNetCRF","-","-"],"associatedColumns":["third best .","wind . door chair table book . sofa board clut ."],"associatedMergedColumns":["( a ) S3DIS"]},{"number":"95.1","isBolded":false,"associatedRows":["ConvPoint - RGB","MSRRNetCRF","-","-"],"associatedColumns":["Best score ,","ceil ."],"associatedMergedColumns":["( a ) S3DIS"]},{"number":"46.2","isBolded":false,"associatedRows":["PCCN [ 52 ]","MSRRNetCRF","-","-"],"associatedColumns":["third best .","wind . door chair table book . sofa board clut ."],"associatedMergedColumns":["( a ) S3DIS"]},{"number":"77.8","isBolded":false,"associatedRows":["ConvPoint - NoColor","ConvPoint - Fusion","EdConvE","-"],"associatedColumns":["third best .","wind . door chair table book . sofa board clut .","Man made Natural High veg . Low veg . Buildings Hard scape Artefacts","Car"],"associatedMergedColumns":["( c ) NPM3D"]},{"number":"69.2","isBolded":false,"associatedRows":["SPGraph [ 26 ]","MSRRNetCRF","-","-"],"associatedColumns":["third best .","wind . door chair table book . sofa board clut ."],"associatedMergedColumns":["( a ) S3DIS"]},{"number":"69.3","isBolded":false,"associatedRows":["KPConv [ 49 ]","MSRRNetCRF","-","-"],"associatedColumns":["third best .","wind . door chair table book . sofa board clut ."],"associatedMergedColumns":["( a ) S3DIS"]},{"number":"68.9","isBolded":false,"associatedRows":["ConvPoint - NoColor","MSRRNetCRF","-","-"],"associatedColumns":["third best .","wind . door chair table book . sofa board clut ."],"associatedMergedColumns":["( a ) S3DIS"]},{"number":"0.934","isBolded":false,"associatedRows":["ConvPoint - RGB","ConvPoint - Fusion","MSRRNetCRF","-"],"associatedColumns":["Best score ,","ceil .","Man made Natural High veg . Low veg . Buildings Hard scape Artefacts"],"associatedMergedColumns":["( b ) Semantic8"]},{"number":"94.4","isBolded":false,"associatedRows":["ConvPoint - NoColor","ConvPoint - Fusion","KP - FCNN [ 49 ]","-"],"associatedColumns":["third best .","wind . door chair table book . sofa board clut .","Man made Natural High veg . Low veg . Buildings Hard scape Artefacts","Car"],"associatedMergedColumns":["( c ) NPM3D"]},{"number":"0.850","isBolded":false,"associatedRows":["TMLC - MS [ 22 ]","MSRRNetCRF","-","-"],"associatedColumns":["Best score ,","mAcc mIoU","OA"],"associatedMergedColumns":["( b ) Semantic8"]},{"number":"0.918","isBolded":false,"associatedRows":["ConvPoint - NoColor","ConvPoint - Fusion","MSRRNetCRF","-"],"associatedColumns":["Best score ,","ceil .","Man made Natural High veg . Low veg . Buildings Hard scape Artefacts"],"associatedMergedColumns":["( b ) Semantic8"]},{"number":"34.6","isBolded":false,"associatedRows":["ConvPoint - Fusion","MSRRNetCRF","-","-"],"associatedColumns":["and","col ."],"associatedMergedColumns":["( a ) S3DIS"]},{"number":"75.3","isBolded":false,"associatedRows":["ConvPoint - Fusion","MSRRNetCRF","-","-"],"associatedColumns":["third best .","wind . door chair table book . sofa board clut ."],"associatedMergedColumns":["( a ) S3DIS"]},{"number":"0.758","isBolded":false,"associatedRows":["ConvPoint - RGB","ConvPoint - Fusion","MSRRNetCRF","-"],"associatedColumns":["second best","floor wall beam","Man made Natural High veg . Low veg . Buildings Hard scape Artefacts"],"associatedMergedColumns":["( b ) Semantic8"]},{"number":"85.2","isBolded":false,"associatedRows":["ConvPoint - NoColor","EdConvE"],"associatedColumns":["Best score ,","OA"],"associatedMergedColumns":["( a ) S3DIS"]},{"number":"0.847","isBolded":false,"associatedRows":["ConvPoint - RGB","ConvPoint - Fusion","MSRRNetCRF","-"],"associatedColumns":["second best","floor wall beam","Man made Natural High veg . Low veg . Buildings Hard scape Artefacts"],"associatedMergedColumns":["( b ) Semantic8"]},{"number":"29.9","isBolded":false,"associatedRows":["ConvPoint - NoColor","ConvPoint - Fusion","MSRRNetCRF","-"],"associatedColumns":["third best .","wind . door chair table book . sofa board clut .","Man made Natural High veg . Low veg . Buildings Hard scape Artefacts","Ground Building Pole Bollard Trash can Barrier Pedestrian"],"associatedMergedColumns":["( c ) NPM3D"]},{"number":"66.9","isBolded":false,"associatedRows":["PCCN [ 52 ]","MSRRNetCRF","-","-"],"associatedColumns":["third best .","wind . door chair table book . sofa board clut ."],"associatedMergedColumns":["( a ) S3DIS"]},{"number":"52.0","isBolded":false,"associatedRows":["RSNet [ 23 ]","MSRRNetCRF","-","-"],"associatedColumns":["third best .","wind . door chair table book . sofa board clut ."],"associatedMergedColumns":["( a ) S3DIS"]},{"number":"27.1","isBolded":false,"associatedRows":["ConvPoint - NoColor","ConvPoint - Fusion","RFMSSF","-"],"associatedColumns":["third best .","wind . door chair table book . sofa board clut .","Man made Natural High veg . Low veg . Buildings Hard scape Artefacts","Ground Building Pole Bollard Trash can Barrier Pedestrian"],"associatedMergedColumns":["( c ) NPM3D"]},{"number":"0.432","isBolded":false,"associatedRows":["ConvPoint - RGB","ConvPoint - Fusion","MSRRNetCRF","-"],"associatedColumns":["third best .","wind . door chair table book . sofa board clut .","Man made Natural High veg . Low veg . Buildings Hard scape Artefacts"],"associatedMergedColumns":["( b ) Semantic8"]},{"number":"68.4","isBolded":false,"associatedRows":["SPGraph [ 26 ]","MSRRNetCRF","-","-"],"associatedColumns":["third best .","wind . door chair table book . sofa board clut ."],"associatedMergedColumns":["( a ) S3DIS"]},{"number":"92.8","isBolded":false,"associatedRows":["RSNet [ 23 ]","MSRRNetCRF","-","-"],"associatedColumns":["Best score ,","floor wall beam"],"associatedMergedColumns":["( a ) S3DIS"]},{"number":"15.5","isBolded":false,"associatedRows":["ConvPoint - NoColor","ConvPoint - Fusion","MSRRNetCRF","-"],"associatedColumns":["and","floor wall beam","Man made Natural High veg . Low veg . Buildings Hard scape Artefacts","Ground Building Pole Bollard Trash can Barrier Pedestrian"],"associatedMergedColumns":["( c ) NPM3D"]},{"number":"66.4","isBolded":false,"associatedRows":["ConvPoint - Fusion","ConvPoint - Fusion","EdConvE"],"associatedColumns":["Best score ,","mAcc mIoU","mIoU","mIoU"],"associatedMergedColumns":["( c ) NPM3D"]},{"number":"91.4","isBolded":false,"associatedRows":["ConvPoint - NoColor","ConvPoint - Fusion","KP - FCNN [ 49 ]","-"],"associatedColumns":["third best .","wind . door chair table book . sofa board clut .","Man made Natural High veg . Low veg . Buildings Hard scape Artefacts","Natural"],"associatedMergedColumns":["( c ) NPM3D"]},{"number":"75.6","isBolded":false,"associatedRows":["PointCNN [ 29 ]","MSRRNetCRF","-"],"associatedColumns":["Best score ,","mAcc mIoU"],"associatedMergedColumns":["( a ) S3DIS"]},{"number":"55.3","isBolded":false,"associatedRows":["SPGraph [ 26 ]","MSRRNetCRF","-","-"],"associatedColumns":["third best .","wind . door chair table book . sofa board clut ."],"associatedMergedColumns":["( a ) S3DIS"]},{"number":"0.856","isBolded":false,"associatedRows":["ConvPoint - NoColor","ConvPoint - Fusion","MSRRNetCRF","-"],"associatedColumns":["third best .","wind . door chair table book . sofa board clut .","Cars"],"associatedMergedColumns":["( b ) Semantic8"]},{"number":"0.646","isBolded":false,"associatedRows":["ConvPoint - NoColor","ConvPoint - Fusion","MSRRNetCRF","-"],"associatedColumns":["third best .","wind . door chair table book . sofa board clut .","Man made Natural High veg . Low veg . Buildings Hard scape Artefacts"],"associatedMergedColumns":["( b ) Semantic8"]},{"number":"0.473","isBolded":false,"associatedRows":["ConvPoint - Fusion","ConvPoint - Fusion","MSRRNetCRF","-"],"associatedColumns":["third best .","wind . door chair table book . sofa board clut .","Man made Natural High veg . Low veg . Buildings Hard scape Artefacts"],"associatedMergedColumns":["( b ) Semantic8"]},{"number":"83.1","isBolded":false,"associatedRows":["ConvPoint - Fusion","ConvPoint - Fusion","KP - FCNN [ 49 ]","-"],"associatedColumns":["and","floor wall beam","Man made Natural High veg . Low veg . Buildings Hard scape Artefacts","Ground Building Pole Bollard Trash can Barrier Pedestrian"],"associatedMergedColumns":["( c ) NPM3D"]},{"number":"60.1","isBolded":false,"associatedRows":["RSNet [ 23 ]","MSRRNetCRF","-","-"],"associatedColumns":["third best .","wind . door chair table book . sofa board clut ."],"associatedMergedColumns":["( a ) S3DIS"]},{"number":"56.7","isBolded":false,"associatedRows":["ConvPoint - NoColor","MSRRNetCRF","-","-"],"associatedColumns":["third best .","wind . door chair table book . sofa board clut ."],"associatedMergedColumns":["( a ) S3DIS"]},{"number":"0.328","isBolded":false,"associatedRows":["TMLC - MS [ 22 ]","MSRRNetCRF","-","-"],"associatedColumns":["second best","floor wall beam","Man made Natural High veg . Low veg . Buildings Hard scape Artefacts"],"associatedMergedColumns":["( b ) Semantic8"]},{"number":"2.3","isBolded":false,"associatedRows":["ConvPoint - NoColor","ConvPoint - Fusion","RFMSSF","-"],"associatedColumns":["third best .","wind . door chair table book . sofa board clut .","Man made Natural High veg . Low veg . Buildings Hard scape Artefacts","Ground Building Pole Bollard Trash can Barrier Pedestrian"],"associatedMergedColumns":["( c ) NPM3D"]},{"number":"0.884","isBolded":false,"associatedRows":["SPGraph [ 26 ]","MSRRNetCRF","-","-"],"associatedColumns":["third best .","wind . door chair table book . sofa board clut .","Cars"],"associatedMergedColumns":["( b ) Semantic8"]},{"number":"67.7","isBolded":false,"associatedRows":["ConvPoint - Fusion","ConvPoint - Fusion","HDGCN","-"],"associatedColumns":["second best","floor wall beam","Man made Natural High veg . Low veg . Buildings Hard scape Artefacts","Ground Building Pole Bollard Trash can Barrier Pedestrian"],"associatedMergedColumns":["( c ) NPM3D"]},{"number":"99.5","isBolded":false,"associatedRows":["ConvPoint - Fusion","ConvPoint - Fusion","-"],"associatedColumns":["Best score ,","mAcc mIoU","Man made Natural High veg . Low veg . Buildings Hard scape Artefacts","Ground Building Pole Bollard Trash can Barrier Pedestrian"],"associatedMergedColumns":["( c ) NPM3D"]},{"number":"57.6","isBolded":false,"associatedRows":["ConvPoint - Fusion","MSRRNetCRF","-","-"],"associatedColumns":["third best .","wind . door chair table book . sofa board clut ."],"associatedMergedColumns":["( a ) S3DIS"]},{"number":"0.938","isBolded":false,"associatedRows":["ConvPoint - RGB","ConvPoint - Fusion","MSRRNetCRF","-"],"associatedColumns":["Best score ,","mAcc mIoU","OA"],"associatedMergedColumns":["( b ) Semantic8"]},{"number":"99.0","isBolded":false,"associatedRows":["ConvPoint - Fusion","ConvPoint - Fusion","MS3DVS","-"],"associatedColumns":["Best score ,","mAcc mIoU","Man made Natural High veg . Low veg . Buildings Hard scape Artefacts","Ground Building Pole Bollard Trash can Barrier Pedestrian"],"associatedMergedColumns":["( c ) NPM3D"]},{"number":"62.9","isBolded":false,"associatedRows":["ConvPoint - RGB","MSRRNetCRF","-","-"],"associatedColumns":["third best .","wind . door chair table book . sofa board clut ."],"associatedMergedColumns":["( a ) S3DIS"]},{"number":"50.8","isBolded":false,"associatedRows":["ConvPoint - NoColor","ConvPoint - Fusion","EdConvE","-"],"associatedColumns":["and","floor wall beam","Man made Natural High veg . Low veg . Buildings Hard scape Artefacts","Ground Building Pole Bollard Trash can Barrier Pedestrian"],"associatedMergedColumns":["( c ) NPM3D"]},{"number":"0.364","isBolded":false,"associatedRows":["PointNet++ [ 40 ]","MSRRNetCRF","-","-"],"associatedColumns":["third best .","wind . door chair table book . sofa board clut .","Man made Natural High veg . Low veg . Buildings Hard scape Artefacts"],"associatedMergedColumns":["( b ) Semantic8"]},{"number":"63.5","isBolded":false,"associatedRows":["PCCN [ 52 ]","MSRRNetCRF","-","-"],"associatedColumns":["third best .","wind . door chair table book . sofa board clut ."],"associatedMergedColumns":["( a ) S3DIS"]},{"number":"68.2","isBolded":false,"associatedRows":["ConvPoint - Fusion","MSRRNetCRF","-","-"],"associatedColumns":["Best score ,","mAcc mIoU"],"associatedMergedColumns":["( a ) S3DIS"]},{"number":"34.4","isBolded":false,"associatedRows":["RSNet [ 23 ]","MSRRNetCRF","-","-"],"associatedColumns":["and","col ."],"associatedMergedColumns":["( a ) S3DIS"]},{"number":"29.4","isBolded":false,"associatedRows":["Pointnet [ 38 ]","MSRRNetCRF","-","-"],"associatedColumns":["third best .","wind . door chair table book . sofa board clut ."],"associatedMergedColumns":["( a ) S3DIS"]},{"number":"61.3","isBolded":false,"associatedRows":["ConvPoint - NoColor","MSRRNetCRF","-","-"],"associatedColumns":["third best .","wind . door chair table book . sofa board clut ."],"associatedMergedColumns":["( a ) S3DIS"]},{"number":"94.2","isBolded":false,"associatedRows":["ConvPoint - NoColor","MSRRNetCRF","-","-"],"associatedColumns":["Best score ,","floor wall beam"],"associatedMergedColumns":["( a ) S3DIS"]},{"number":"63.1","isBolded":false,"associatedRows":["ConvPoint - NoColor","MSRRNetCRF","-","-"],"associatedColumns":["third best .","wind . door chair table book . sofa board clut ."],"associatedMergedColumns":["( a ) S3DIS"]},{"number":"95.1","isBolded":false,"associatedRows":["ConvPoint - Fusion","ConvPoint - Fusion","-"],"associatedColumns":["Best score ,","floor wall beam","Man made Natural High veg . Low veg . Buildings Hard scape Artefacts","Ground Building Pole Bollard Trash can Barrier Pedestrian"],"associatedMergedColumns":["( c ) NPM3D"]},{"number":"0.902","isBolded":false,"associatedRows":["ConvPoint - RGB","ConvPoint - Fusion","MSRRNetCRF","-"],"associatedColumns":["third best .","wind . door chair table book . sofa board clut .","Cars"],"associatedMergedColumns":["( b ) Semantic8"]},{"number":"99.2","isBolded":false,"associatedRows":["ConvPoint - Fusion","ConvPoint - Fusion","EdConvE","-"],"associatedColumns":["Best score ,","mAcc mIoU","Man made Natural High veg . Low veg . Buildings Hard scape Artefacts","Ground Building Pole Bollard Trash can Barrier Pedestrian"],"associatedMergedColumns":["( c ) NPM3D"]},{"number":"89.4","isBolded":false,"associatedRows":["ConvPoint - NoColor","ConvPoint - Fusion","-"],"associatedColumns":["third best .","wind . door chair table book . sofa board clut .","Man made Natural High veg . Low veg . Buildings Hard scape Artefacts","Car"],"associatedMergedColumns":["( c ) NPM3D"]},{"number":"89.9","isBolded":false,"associatedRows":["SPGraph [ 26 ]","MSRRNetCRF","-","-"],"associatedColumns":["Best score ,","ceil ."],"associatedMergedColumns":["( a ) S3DIS"]},{"number":"94.8","isBolded":false,"associatedRows":["PointCNN [ 29 ]","MSRRNetCRF","-","-"],"associatedColumns":["Best score ,","ceil ."],"associatedMergedColumns":["( a ) S3DIS"]},{"number":"57.3","isBolded":false,"associatedRows":["ConvPoint - RGB","MSRRNetCRF","-","-"],"associatedColumns":["third best .","wind . door chair table book . sofa board clut ."],"associatedMergedColumns":["( a ) S3DIS"]},{"number":"71.6","isBolded":false,"associatedRows":["ConvPoint - Fusion","ConvPoint - Fusion","-"],"associatedColumns":["second best","floor wall beam","Man made Natural High veg . Low veg . Buildings Hard scape Artefacts","Ground Building Pole Bollard Trash can Barrier Pedestrian"],"associatedMergedColumns":["( c ) NPM3D"]},{"number":"0.950","isBolded":false,"associatedRows":["ConvPoint - RGB","ConvPoint - Fusion","MSRRNetCRF","-"],"associatedColumns":["third best .","wind . door chair table book . sofa board clut .","Man made Natural High veg . Low veg . Buildings Hard scape Artefacts"],"associatedMergedColumns":["( b ) Semantic8"]},{"number":"0.451","isBolded":false,"associatedRows":["ConvPoint - NoColor","ConvPoint - Fusion","MSRRNetCRF","-"],"associatedColumns":["third best .","wind . door chair table book . sofa board clut .","Man made Natural High veg . Low veg . Buildings Hard scape Artefacts"],"associatedMergedColumns":["( b ) Semantic8"]},{"number":"41.3","isBolded":false,"associatedRows":["ConvPoint - Fusion","ConvPoint - Fusion","EdConvE","-"],"associatedColumns":["second best","floor wall beam","Man made Natural High veg . Low veg . Buildings Hard scape Artefacts","Ground Building Pole Bollard Trash can Barrier Pedestrian"],"associatedMergedColumns":["( c ) NPM3D"]},{"number":"59.1","isBolded":false,"associatedRows":["PCCN [ 52 ]","MSRRNetCRF","-","-"],"associatedColumns":["third best .","wind . door chair table book . sofa board clut ."],"associatedMergedColumns":["( a ) S3DIS"]},{"number":"47.7","isBolded":false,"associatedRows":["ConvPoint - Fusion","ConvPoint - Fusion","KP - FCNN [ 49 ]","-"],"associatedColumns":["third best .","wind . door chair table book . sofa board clut .","Man made Natural High veg . Low veg . Buildings Hard scape Artefacts","Ground Building Pole Bollard Trash can Barrier Pedestrian"],"associatedMergedColumns":["( c ) NPM3D"]},{"number":"97.3","isBolded":false,"associatedRows":["ConvPoint - Fusion","MSRRNetCRF","-","-"],"associatedColumns":["Best score ,","floor wall beam"],"associatedMergedColumns":["( a ) S3DIS"]},{"number":"43.0","isBolded":false,"associatedRows":["ConvPoint - NoColor","MSRRNetCRF","-","-"],"associatedColumns":["second best","floor wall beam"],"associatedMergedColumns":["( a ) S3DIS"]},{"number":"76.4","isBolded":false,"associatedRows":["SPGraph [ 26 ]","MSRRNetCRF","-","-"],"associatedColumns":["second best","floor wall beam"],"associatedMergedColumns":["( a ) S3DIS"]},{"number":"44.7","isBolded":false,"associatedRows":["ConvPoint - RGB","MSRRNetCRF","-","-"],"associatedColumns":["second best","floor wall beam"],"associatedMergedColumns":["( a ) S3DIS"]},{"number":"0.804","isBolded":false,"associatedRows":["TML - PC [ 37 ]","MSRRNetCRF","-","-"],"associatedColumns":["Best score ,","ceil .","Man made Natural High veg . Low veg . Buildings Hard scape Artefacts"],"associatedMergedColumns":["( b ) Semantic8"]},{"number":"78.5","isBolded":false,"associatedRows":["Pointnet [ 38 ]","EdConvE"],"associatedColumns":["Best score ,","OA"],"associatedMergedColumns":["( a ) S3DIS"]},{"number":"63.5","isBolded":false,"associatedRows":["ConvPoint - RGB","MSRRNetCRF","-","-"],"associatedColumns":["third best .","wind . door chair table book . sofa board clut ."],"associatedMergedColumns":["( a ) S3DIS"]},{"number":"65.8","isBolded":false,"associatedRows":["ConvPoint - Fusion","ConvPoint - Fusion","MSRRNetCRF"],"associatedColumns":["Best score ,","mAcc mIoU","mIoU","mIoU"],"associatedMergedColumns":["( c ) NPM3D"]},{"number":"38.2","isBolded":false,"associatedRows":["Pointnet [ 38 ]","MSRRNetCRF","-","-"],"associatedColumns":["third best .","wind . door chair table book . sofa board clut ."],"associatedMergedColumns":["( a ) S3DIS"]},{"number":"96.2","isBolded":false,"associatedRows":["PCCN [ 52 ]","MSRRNetCRF","-","-"],"associatedColumns":["Best score ,","floor wall beam"],"associatedMergedColumns":["( a ) S3DIS"]},{"number":"78.6","isBolded":false,"associatedRows":["RSNet [ 23 ]","MSRRNetCRF","-","-"],"associatedColumns":["second best","floor wall beam"],"associatedMergedColumns":["( a ) S3DIS"]}]},{"caption":"Table 5: ModelNet40 classification scores with a variation of \nneighborhood sizes k at test time. \n\n","rows":["/ 2","?1"],"columns":["First layer ( default k \u003d 32 )"],"mergedAllColumns":["?2","4 th layer ( default k \u003d 16 )"],"numberCells":[{"number":"91.9","isBolded":false,"associatedRows":["/ 2","?1"],"associatedColumns":["First layer ( default k \u003d 32 )"],"associatedMergedColumns":["?2"]},{"number":"/1.5","isBolded":false,"associatedRows":["/ 2"],"associatedColumns":["First layer ( default k \u003d 32 )"],"associatedMergedColumns":[]},{"number":"?1.5","isBolded":true,"associatedRows":["/ 2","?1"],"associatedColumns":["First layer ( default k \u003d 32 )"],"associatedMergedColumns":["4 th layer ( default k \u003d 16 )"]},{"number":"92.5","isBolded":false,"associatedRows":["/ 2"],"associatedColumns":["First layer ( default k \u003d 32 )"],"associatedMergedColumns":["?2"]},{"number":"91.6","isBolded":false,"associatedRows":["/ 2","?1"],"associatedColumns":["First layer ( default k \u003d 32 )"],"associatedMergedColumns":["?2"]},{"number":"91.2","isBolded":false,"associatedRows":["/ 2"],"associatedColumns":["First layer ( default k \u003d 32 )"],"associatedMergedColumns":["?2"]},{"number":"92.2","isBolded":false,"associatedRows":["/ 2"],"associatedColumns":["First layer ( default k \u003d 32 )"],"associatedMergedColumns":["?2"]},{"number":"91.4","isBolded":false,"associatedRows":["/ 2","?1"],"associatedColumns":["First layer ( default k \u003d 32 )"],"associatedMergedColumns":["?2"]},{"number":"/1.5","isBolded":false,"associatedRows":["/ 2"],"associatedColumns":["First layer ( default k \u003d 32 )"],"associatedMergedColumns":["4 th layer ( default k \u003d 16 )"]},{"number":"90.9","isBolded":false,"associatedRows":[],"associatedColumns":["First layer ( default k \u003d 32 )"],"associatedMergedColumns":["?2"]},{"number":"92.5","isBolded":false,"associatedRows":["/ 2"],"associatedColumns":["First layer ( default k \u003d 32 )"],"associatedMergedColumns":["?2"]},{"number":"90.2","isBolded":false,"associatedRows":["/ 2","?1"],"associatedColumns":["First layer ( default k \u003d 32 )"],"associatedMergedColumns":["?2"]},{"number":"91.0","isBolded":false,"associatedRows":[],"associatedColumns":["First layer ( default k \u003d 32 )"],"associatedMergedColumns":["?2"]},{"number":"?1.5","isBolded":true,"associatedRows":["/ 2","?1"],"associatedColumns":["First layer ( default k \u003d 32 )"],"associatedMergedColumns":[]}]},{"caption":"Table 6: Training and inference timings. \n\n","rows":["Config . 1","Point Batch","7 s","8 s","120 s","Config . 2","185 s","Training","155","Config . 1 : Middle - end configuration . Intel Xeon E5 - 1620 v3 ,","2048","Test","Batch size","116 s","Dataset","ModelNet40 1024","-","1320 s","1","2","4","ShapeNet","128","8","255 s"],"columns":["( a ) Comparison with PointCNN [ 29 ] on ModelNet40 and ShapeNet ,","PointCNN","ings are given in milliseconds .","fusion architecture , computed on the S3DIS dataset . Tim -","( b ) Comparison between large segmentation network and","Config . 1","num . size","Config . 2","ConvPoint","-","computed with Config . 1","( epoch )"],"mergedAllColumns":["Segmentation network","8 s","9 s"],"numberCells":[{"number":"39","isBolded":false,"associatedRows":["Config . 1 : Middle - end configuration . Intel Xeon E5 - 1620 v3 ,","ModelNet40 1024","8 s","7 s","Config . 1","155"],"associatedColumns":["( b ) Comparison between large segmentation network and","fusion architecture , computed on the S3DIS dataset . Tim -","ings are given in milliseconds .","( epoch )"],"associatedMergedColumns":["Segmentation network"]},{"number":"11s","isBolded":false,"associatedRows":["ModelNet40 1024","2048","1320 s","-"],"associatedColumns":["( a ) Comparison with PointCNN [ 29 ] on ModelNet40 and ShapeNet ,","computed with Config . 1","PointCNN","( epoch )"],"associatedMergedColumns":["Segmentation network"]},{"number":"16","isBolded":false,"associatedRows":["Config . 1 : Middle - end configuration . Intel Xeon E5 - 1620 v3 ,","Dataset","Point Batch","Training","Test","Training","Test","Batch size","1","2","4","8"],"associatedColumns":["( b ) Comparison between large segmentation network and","fusion architecture , computed on the S3DIS dataset . Tim -","ings are given in milliseconds ."],"associatedMergedColumns":[]},{"number":"32","isBolded":false,"associatedRows":["ModelNet40 1024","2048"],"associatedColumns":["( a ) Comparison with PointCNN [ 29 ] on ModelNet40 and ShapeNet ,","computed with Config . 1","PointCNN","num . size"],"associatedMergedColumns":["Segmentation network"]},{"number":"38","isBolded":false,"associatedRows":["Config . 1 : Middle - end configuration . Intel Xeon E5 - 1620 v3 ,","ModelNet40 1024","8 s","7 s","Config . 1","155"],"associatedColumns":["( b ) Comparison between large segmentation network and","fusion architecture , computed on the S3DIS dataset . Tim -","ings are given in milliseconds .","( epoch )"],"associatedMergedColumns":["Segmentation network"]},{"number":"81","isBolded":false,"associatedRows":["Config . 1 : Middle - end configuration . Intel Xeon E5 - 1620 v3 ,","128","7 s","7 s","Config . 2","155"],"associatedColumns":["( b ) Comparison between large segmentation network and","fusion architecture , computed on the S3DIS dataset . Tim -","ings are given in milliseconds .","( epoch )"],"associatedMergedColumns":["Segmentation network"]},{"number":"37s","isBolded":false,"associatedRows":["ModelNet40 1024","8","1320 s","-","120 s","185 s"],"associatedColumns":["( a ) Comparison with PointCNN [ 29 ] on ModelNet40 and ShapeNet ,","fusion architecture , computed on the S3DIS dataset . Tim -","ConvPoint","( epoch )","-","Config . 1"],"associatedMergedColumns":["8 s"]},{"number":"32","isBolded":false,"associatedRows":["Config . 1 : Middle - end configuration . Intel Xeon E5 - 1620 v3 ,","Dataset","Point Batch","Training","Test","Training","Test","Batch size","1","2","4","8"],"associatedColumns":["( b ) Comparison between large segmentation network and","fusion architecture , computed on the S3DIS dataset . Tim -","ings are given in milliseconds ."],"associatedMergedColumns":[]},{"number":"46","isBolded":false,"associatedRows":["Config . 1 : Middle - end configuration . Intel Xeon E5 - 1620 v3 ,","ModelNet40 1024","8 s","7 s","Config . 1","155"],"associatedColumns":["( b ) Comparison between large segmentation network and","fusion architecture , computed on the S3DIS dataset . Tim -","ings are given in milliseconds .","( epoch )"],"associatedMergedColumns":["Segmentation network"]},{"number":"95","isBolded":false,"associatedRows":["Config . 1 : Middle - end configuration . Intel Xeon E5 - 1620 v3 ,","128","7 s","7 s","Config . 2","155"],"associatedColumns":["( b ) Comparison between large segmentation network and","fusion architecture , computed on the S3DIS dataset . Tim -","ings are given in milliseconds .","( epoch )"],"associatedMergedColumns":["Segmentation network"]},{"number":"93","isBolded":false,"associatedRows":["Config . 1 : Middle - end configuration . Intel Xeon E5 - 1620 v3 ,","ModelNet40 1024","8 s","7 s","Config . 1"],"associatedColumns":["( b ) Comparison between large segmentation network and","fusion architecture , computed on the S3DIS dataset . Tim -","ings are given in milliseconds .","( epoch )"],"associatedMergedColumns":["Segmentation network"]},{"number":"89","isBolded":false,"associatedRows":["Config . 1 : Middle - end configuration . Intel Xeon E5 - 1620 v3 ,","128","7 s","7 s","Config . 2","155"],"associatedColumns":["( b ) Comparison between large segmentation network and","fusion architecture , computed on the S3DIS dataset . Tim -","ings are given in milliseconds .","( epoch )"],"associatedMergedColumns":["Segmentation network"]},{"number":"32","isBolded":false,"associatedRows":["ModelNet40 1024","2048"],"associatedColumns":["( a ) Comparison with PointCNN [ 29 ] on ModelNet40 and ShapeNet ,","computed with Config . 1","PointCNN","num . size"],"associatedMergedColumns":[]},{"number":"41s","isBolded":false,"associatedRows":["ShapeNet","2048","4","1320 s","-","120 s","255 s"],"associatedColumns":["( a ) Comparison with PointCNN [ 29 ] on ModelNet40 and ShapeNet ,","fusion architecture , computed on the S3DIS dataset . Tim -","ConvPoint","( epoch )","-"],"associatedMergedColumns":["8 s"]},{"number":"40","isBolded":false,"associatedRows":["Config . 1 : Middle - end configuration . Intel Xeon E5 - 1620 v3 ,","ModelNet40 1024","8 s","7 s","Config . 1","155"],"associatedColumns":["( b ) Comparison between large segmentation network and","fusion architecture , computed on the S3DIS dataset . Tim -","ings are given in milliseconds .","( epoch )"],"associatedMergedColumns":["Segmentation network"]},{"number":"35s","isBolded":false,"associatedRows":["ModelNet40 1024","128","Training","-","7 s"],"associatedColumns":["( a ) Comparison with PointCNN [ 29 ] on ModelNet40 and ShapeNet ,","fusion architecture , computed on the S3DIS dataset . Tim -","ConvPoint","( epoch )"],"associatedMergedColumns":["Segmentation network"]},{"number":"29s","isBolded":false,"associatedRows":["ModelNet40 1024","128","1320 s","-","120 s","116 s"],"associatedColumns":["( a ) Comparison with PointCNN [ 29 ] on ModelNet40 and ShapeNet ,","fusion architecture , computed on the S3DIS dataset . Tim -","ConvPoint","( epoch )","-","Config . 1","Config . 2"],"associatedMergedColumns":["8 s"]},{"number":"69","isBolded":false,"associatedRows":["Config . 1 : Middle - end configuration . Intel Xeon E5 - 1620 v3 ,","ModelNet40 1024","8 s","7 s","Config . 1","155"],"associatedColumns":["( b ) Comparison between large segmentation network and","fusion architecture , computed on the S3DIS dataset . Tim -","ings are given in milliseconds .","( epoch )"],"associatedMergedColumns":["Segmentation network"]},{"number":"51s","isBolded":false,"associatedRows":["ModelNet40 1024","128"],"associatedColumns":["( a ) Comparison with PointCNN [ 29 ] on ModelNet40 and ShapeNet ,","computed with Config . 1","PointCNN","( epoch )"],"associatedMergedColumns":["Segmentation network"]},{"number":"80s","isBolded":false,"associatedRows":["ModelNet40 1024","2048"],"associatedColumns":["( a ) Comparison with PointCNN [ 29 ] on ModelNet40 and ShapeNet ,","computed with Config . 1","PointCNN","( epoch )"],"associatedMergedColumns":["Segmentation network"]},{"number":"58s","isBolded":false,"associatedRows":["ModelNet40 1024","Point Batch"],"associatedColumns":["( a ) Comparison with PointCNN [ 29 ] on ModelNet40 and ShapeNet ,","computed with Config . 1","PointCNN","( epoch )"],"associatedMergedColumns":[]},{"number":"64","isBolded":false,"associatedRows":["ShapeNet","2048"],"associatedColumns":["( a ) Comparison with PointCNN [ 29 ] on ModelNet40 and ShapeNet ,","computed with Config . 1","PointCNN","num . size","-","Config . 1","Config . 2"],"associatedMergedColumns":["8 s"]},{"number":"42s","isBolded":false,"associatedRows":["ModelNet40 1024","Point Batch","Training","-","8 s"],"associatedColumns":["( a ) Comparison with PointCNN [ 29 ] on ModelNet40 and ShapeNet ,","fusion architecture , computed on the S3DIS dataset . Tim -","ConvPoint","( epoch )"],"associatedMergedColumns":[]},{"number":"3.50GHz,8cores,8threads+NvidiaGTX10708Gb","isBolded":false,"associatedRows":["Config . 1 : Middle - end configuration . Intel Xeon E5 - 1620 v3 ,"],"associatedColumns":["( b ) Comparison between large segmentation network and","fusion architecture , computed on the S3DIS dataset . Tim -","ings are given in milliseconds .","( epoch )","-","-","-"],"associatedMergedColumns":["8 s"]},{"number":"53s","isBolded":false,"associatedRows":["ModelNet40 1024","2048","1320 s","-","120 s"],"associatedColumns":["( a ) Comparison with PointCNN [ 29 ] on ModelNet40 and ShapeNet ,","fusion architecture , computed on the S3DIS dataset . Tim -","ConvPoint","( epoch )"],"associatedMergedColumns":["Segmentation network"]},{"number":"45s","isBolded":false,"associatedRows":["ModelNet40 1024","128","1320 s","-","120 s"],"associatedColumns":["( a ) Comparison with PointCNN [ 29 ] on ModelNet40 and ShapeNet ,","fusion architecture , computed on the S3DIS dataset . Tim -","ConvPoint","( epoch )","-"],"associatedMergedColumns":["9 s"]}]}]