[{"caption":"Method \n\nDetector Training \nCOCO Generalized (48+17) \nBackbone \nRPN pretrained \nNovel \nBase \nAll \n\nBase-only (CLIP) \n-\n-\n1.3 \n48.7 \n39.3 \nWSDDN [2] \n-\n-\n20.5 \n23.4 \n24.6 \nCap2Det [47] \n-\n-\n20.3 \n20.1 \n20.1 \nPL [33] \nRN50-FPN COCO Base (48) \n4.12 \n35.9 \n27.9 \nOVR-CNN [49] \nRN50-C4 COCO Base (48) \n22.8 \n46.0 \n39.9 \nHierKD [25] \nRN50-C4 COCO Base (48) \n20.3 \n51.3 \n43.2 \nViLD [14] \nRN50-FPN COCO Base (48) \n27.6 \n59.5 \n51.3 \nRegionCLIP [51] \nRN50-C4 \nLVIS (1203) \n26.8 \n54.8 \n47.5 \nDetic [53] (reproduced) RN50-C4 COCO Base (48) 28.7 ?0.4 | 29.1 52.0 ?0.4 | 52.4 45.9 ?0.3 | 46.2 \n\nMEDet (Ours) \nRN50-C4 COCO Base (48) 32.2 ?0.4 | 32.6 53.3 ?0.2 | 53.5 47.8 ?0.2 | 48.0 \n\nTable 1: Results (mean ? variation | best) of OVD on COCO dataset [1]. MEDet outperforms the others on \nthe Novel categories. The results of MEDet are the average of five experiments. \n\n","rows":["LVIS ( 1203 )","RN50 - FPN","Detic [ 53 ] ( reproduced )","COCO Base ( 48 )","MEDet ( Ours )","-","RN50 - C4"],"columns":["All","Novel","COCO Generalized ( 48+17 )","Base"],"mergedAllColumns":[],"numberCells":[{"number":"20.5","isBolded":false,"associatedRows":["Detic [ 53 ] ( reproduced )","RN50 - FPN","RN50 - C4","-","COCO Base ( 48 )","COCO Base ( 48 )","-"],"associatedColumns":["Novel"],"associatedMergedColumns":[]},{"number":"26.8","isBolded":false,"associatedRows":["Detic [ 53 ] ( reproduced )","RN50 - C4","LVIS ( 1203 )"],"associatedColumns":["Novel"],"associatedMergedColumns":[]},{"number":"39.9","isBolded":false,"associatedRows":["Detic [ 53 ] ( reproduced )","RN50 - FPN","RN50 - C4","COCO Base ( 48 )"],"associatedColumns":["All"],"associatedMergedColumns":[]},{"number":"20.1","isBolded":false,"associatedRows":["Detic [ 53 ] ( reproduced )","RN50 - FPN","-","COCO Base ( 48 )","-"],"associatedColumns":["All"],"associatedMergedColumns":[]},{"number":"28.7","isBolded":false,"associatedRows":["Detic [ 53 ] ( reproduced )","RN50 - C4","COCO Base ( 48 )"],"associatedColumns":["Novel"],"associatedMergedColumns":[]},{"number":"46.2","isBolded":false,"associatedRows":["Detic [ 53 ] ( reproduced )","RN50 - C4","COCO Base ( 48 )"],"associatedColumns":["All"],"associatedMergedColumns":[]},{"number":"23.4","isBolded":false,"associatedRows":["Detic [ 53 ] ( reproduced )","RN50 - FPN","RN50 - C4","-","COCO Base ( 48 )","COCO Base ( 48 )","-"],"associatedColumns":["COCO Generalized ( 48+17 )","Base"],"associatedMergedColumns":[]},{"number":"32.2","isBolded":true,"associatedRows":["MEDet ( Ours )","RN50 - C4","COCO Base ( 48 )"],"associatedColumns":["Novel"],"associatedMergedColumns":[]},{"number":"?0.2|","isBolded":true,"associatedRows":["MEDet ( Ours )","RN50 - C4","COCO Base ( 48 )"],"associatedColumns":["COCO Generalized ( 48+17 )","Base"],"associatedMergedColumns":[]},{"number":"47.5","isBolded":false,"associatedRows":["Detic [ 53 ] ( reproduced )","RN50 - C4","LVIS ( 1203 )"],"associatedColumns":["All"],"associatedMergedColumns":[]},{"number":"48.7","isBolded":false,"associatedRows":["Detic [ 53 ] ( reproduced )","RN50 - FPN","RN50 - C4","-","COCO Base ( 48 )","COCO Base ( 48 )","-"],"associatedColumns":["COCO Generalized ( 48+17 )","Base"],"associatedMergedColumns":[]},{"number":"?0.4|","isBolded":true,"associatedRows":["MEDet ( Ours )","RN50 - C4","COCO Base ( 48 )"],"associatedColumns":["Novel"],"associatedMergedColumns":[]},{"number":"48.0","isBolded":false,"associatedRows":["MEDet ( Ours )","RN50 - C4","COCO Base ( 48 )"],"associatedColumns":["All"],"associatedMergedColumns":[]},{"number":"?0.4|","isBolded":true,"associatedRows":["Detic [ 53 ] ( reproduced )","RN50 - C4","COCO Base ( 48 )"],"associatedColumns":["COCO Generalized ( 48+17 )","Base"],"associatedMergedColumns":[]},{"number":"52.0","isBolded":false,"associatedRows":["Detic [ 53 ] ( reproduced )","RN50 - C4","COCO Base ( 48 )"],"associatedColumns":["COCO Generalized ( 48+17 )"],"associatedMergedColumns":[]},{"number":"1.3","isBolded":false,"associatedRows":["Detic [ 53 ] ( reproduced )","RN50 - FPN","RN50 - C4","-","COCO Base ( 48 )","COCO Base ( 48 )","-"],"associatedColumns":["Novel"],"associatedMergedColumns":[]},{"number":"46.0","isBolded":false,"associatedRows":["Detic [ 53 ] ( reproduced )","RN50 - FPN","RN50 - C4","COCO Base ( 48 )"],"associatedColumns":["COCO Generalized ( 48+17 )","Base"],"associatedMergedColumns":[]},{"number":"?0.3|","isBolded":true,"associatedRows":["Detic [ 53 ] ( reproduced )","RN50 - C4","COCO Base ( 48 )"],"associatedColumns":["All"],"associatedMergedColumns":[]},{"number":"51.3","isBolded":false,"associatedRows":["Detic [ 53 ] ( reproduced )","RN50 - C4","COCO Base ( 48 )"],"associatedColumns":["COCO Generalized ( 48+17 )","Base"],"associatedMergedColumns":[]},{"number":"45.9","isBolded":false,"associatedRows":["Detic [ 53 ] ( reproduced )","RN50 - C4","COCO Base ( 48 )"],"associatedColumns":["COCO Generalized ( 48+17 )"],"associatedMergedColumns":[]},{"number":"?0.4|","isBolded":true,"associatedRows":["Detic [ 53 ] ( reproduced )","RN50 - C4","COCO Base ( 48 )"],"associatedColumns":["Novel"],"associatedMergedColumns":[]},{"number":"29.1","isBolded":false,"associatedRows":["Detic [ 53 ] ( reproduced )","RN50 - C4","COCO Base ( 48 )"],"associatedColumns":["COCO Generalized ( 48+17 )"],"associatedMergedColumns":[]},{"number":"39.3","isBolded":false,"associatedRows":["Detic [ 53 ] ( reproduced )","RN50 - FPN","RN50 - C4","-","COCO Base ( 48 )","COCO Base ( 48 )","-"],"associatedColumns":["All"],"associatedMergedColumns":[]},{"number":"24.6","isBolded":false,"associatedRows":["Detic [ 53 ] ( reproduced )","RN50 - FPN","-","COCO Base ( 48 )","COCO Base ( 48 )","-"],"associatedColumns":["All"],"associatedMergedColumns":[]},{"number":"22.8","isBolded":false,"associatedRows":["Detic [ 53 ] ( reproduced )","RN50 - FPN","RN50 - C4","COCO Base ( 48 )"],"associatedColumns":["Novel"],"associatedMergedColumns":[]},{"number":"59.5","isBolded":false,"associatedRows":["Detic [ 53 ] ( reproduced )","RN50 - FPN","COCO Base ( 48 )"],"associatedColumns":["COCO Generalized ( 48+17 )","Base"],"associatedMergedColumns":[]},{"number":"4.12","isBolded":false,"associatedRows":["Detic [ 53 ] ( reproduced )","RN50 - FPN","COCO Base ( 48 )","COCO Base ( 48 )"],"associatedColumns":["Novel"],"associatedMergedColumns":[]},{"number":"54.8","isBolded":false,"associatedRows":["Detic [ 53 ] ( reproduced )","RN50 - C4","LVIS ( 1203 )"],"associatedColumns":["COCO Generalized ( 48+17 )","Base"],"associatedMergedColumns":[]},{"number":"53.3","isBolded":false,"associatedRows":["MEDet ( Ours )","RN50 - C4","COCO Base ( 48 )"],"associatedColumns":["COCO Generalized ( 48+17 )"],"associatedMergedColumns":[]},{"number":"27.6","isBolded":false,"associatedRows":["Detic [ 53 ] ( reproduced )","RN50 - FPN","COCO Base ( 48 )"],"associatedColumns":["Novel"],"associatedMergedColumns":[]},{"number":"20.1","isBolded":false,"associatedRows":["Detic [ 53 ] ( reproduced )","RN50 - FPN","-","COCO Base ( 48 )","-"],"associatedColumns":["COCO Generalized ( 48+17 )","Base"],"associatedMergedColumns":[]},{"number":"32.6","isBolded":true,"associatedRows":["MEDet ( Ours )","RN50 - C4","COCO Base ( 48 )"],"associatedColumns":["COCO Generalized ( 48+17 )"],"associatedMergedColumns":[]},{"number":"47.8","isBolded":false,"associatedRows":["MEDet ( Ours )","RN50 - C4","COCO Base ( 48 )"],"associatedColumns":["COCO Generalized ( 48+17 )"],"associatedMergedColumns":[]},{"number":"20.3","isBolded":false,"associatedRows":["Detic [ 53 ] ( reproduced )","RN50 - C4","COCO Base ( 48 )"],"associatedColumns":["Novel"],"associatedMergedColumns":[]},{"number":"51.3","isBolded":false,"associatedRows":["Detic [ 53 ] ( reproduced )","RN50 - FPN","COCO Base ( 48 )"],"associatedColumns":["All"],"associatedMergedColumns":[]},{"number":"52.4","isBolded":false,"associatedRows":["Detic [ 53 ] ( reproduced )","RN50 - C4","COCO Base ( 48 )"],"associatedColumns":["COCO Generalized ( 48+17 )"],"associatedMergedColumns":[]},{"number":"53.5","isBolded":false,"associatedRows":["MEDet ( Ours )","RN50 - C4","COCO Base ( 48 )"],"associatedColumns":["COCO Generalized ( 48+17 )"],"associatedMergedColumns":[]},{"number":"35.9","isBolded":false,"associatedRows":["Detic [ 53 ] ( reproduced )","RN50 - FPN","COCO Base ( 48 )","COCO Base ( 48 )"],"associatedColumns":["COCO Generalized ( 48+17 )","Base"],"associatedMergedColumns":[]},{"number":"43.2","isBolded":false,"associatedRows":["Detic [ 53 ] ( reproduced )","RN50 - C4","COCO Base ( 48 )"],"associatedColumns":["All"],"associatedMergedColumns":[]},{"number":"?0.2|","isBolded":true,"associatedRows":["MEDet ( Ours )","RN50 - C4","COCO Base ( 48 )"],"associatedColumns":["All"],"associatedMergedColumns":[]},{"number":"27.9","isBolded":false,"associatedRows":["Detic [ 53 ] ( reproduced )","RN50 - FPN","COCO Base ( 48 )","COCO Base ( 48 )"],"associatedColumns":["All"],"associatedMergedColumns":[]},{"number":"20.3","isBolded":false,"associatedRows":["Detic [ 53 ] ( reproduced )","RN50 - FPN","-","COCO Base ( 48 )","-"],"associatedColumns":["Novel"],"associatedMergedColumns":[]}]},{"caption":"Table 2: Generalization on novel class. \n\n","rows":["Detic - 65 [ 53 ]","MEDet ( ours )"],"columns":["All","Novel","Retain"],"mergedAllColumns":[],"numberCells":[{"number":"27.3","isBolded":false,"associatedRows":["Detic - 65 [ 53 ]"],"associatedColumns":["Novel"],"associatedMergedColumns":[]},{"number":"5.2","isBolded":false,"associatedRows":["Detic - 65 [ 53 ]"],"associatedColumns":["Retain"],"associatedMergedColumns":[]},{"number":"22.9","isBolded":false,"associatedRows":["Detic - 65 [ 53 ]"],"associatedColumns":["Novel"],"associatedMergedColumns":[]},{"number":"11.5","isBolded":false,"associatedRows":["Detic - 65 [ 53 ]"],"associatedColumns":["Retain"],"associatedMergedColumns":[]},{"number":"9.2","isBolded":false,"associatedRows":["Detic - 65 [ 53 ]"],"associatedColumns":["Novel"],"associatedMergedColumns":[]},{"number":"42.4","isBolded":false,"associatedRows":["MEDet ( ours )"],"associatedColumns":["All"],"associatedMergedColumns":[]},{"number":"11.5","isBolded":false,"associatedRows":["Detic - 65 [ 53 ]"],"associatedColumns":["Retain"],"associatedMergedColumns":[]},{"number":"34.1","isBolded":false,"associatedRows":["Detic - 65 [ 53 ]"],"associatedColumns":["All"],"associatedMergedColumns":[]},{"number":"38.1","isBolded":false,"associatedRows":["Detic - 65 [ 53 ]"],"associatedColumns":["All"],"associatedMergedColumns":[]},{"number":"38.3","isBolded":false,"associatedRows":["MEDet ( ours )"],"associatedColumns":["All"],"associatedMergedColumns":[]},{"number":"18.6","isBolded":true,"associatedRows":["MEDet ( ours )"],"associatedColumns":["Retain"],"associatedMergedColumns":[]},{"number":"32.6","isBolded":true,"associatedRows":["MEDet ( ours )"],"associatedColumns":["Novel"],"associatedMergedColumns":[]}]},{"caption":"Table 3: Results on LVIS [15] dataset. \n\n","rows":["MEDet","Detic [ 53 ] ( reproduced )"],"columns":["All","Novel"],"mergedAllColumns":[],"numberCells":[{"number":"30.0","isBolded":false,"associatedRows":["Detic [ 53 ] ( reproduced )"],"associatedColumns":["All"],"associatedMergedColumns":[]},{"number":"28.2","isBolded":false,"associatedRows":["Detic [ 53 ] ( reproduced )"],"associatedColumns":["All"],"associatedMergedColumns":[]},{"number":"21.0","isBolded":false,"associatedRows":["Detic [ 53 ] ( reproduced )"],"associatedColumns":["Novel"],"associatedMergedColumns":[]},{"number":"34.4","isBolded":false,"associatedRows":["MEDet"],"associatedColumns":["All"],"associatedMergedColumns":[]},{"number":"25.2","isBolded":false,"associatedRows":["Detic [ 53 ] ( reproduced )"],"associatedColumns":["All"],"associatedMergedColumns":[]},{"number":"30.9","isBolded":false,"associatedRows":["Detic [ 53 ] ( reproduced )"],"associatedColumns":["All"],"associatedMergedColumns":[]},{"number":"16.8","isBolded":false,"associatedRows":["Detic [ 53 ] ( reproduced )"],"associatedColumns":["Novel"],"associatedMergedColumns":[]},{"number":"25.9","isBolded":false,"associatedRows":["Detic [ 53 ] ( reproduced )"],"associatedColumns":["All"],"associatedMergedColumns":[]},{"number":"22.4","isBolded":true,"associatedRows":["MEDet"],"associatedColumns":["Novel"],"associatedMergedColumns":[]},{"number":"17.1","isBolded":false,"associatedRows":["Detic [ 53 ] ( reproduced )"],"associatedColumns":["Novel"],"associatedMergedColumns":[]},{"number":"19.8","isBolded":false,"associatedRows":["Detic [ 53 ] ( reproduced )"],"associatedColumns":["Novel"],"associatedMergedColumns":[]},{"number":"16.5","isBolded":false,"associatedRows":["Detic [ 53 ] ( reproduced )"],"associatedColumns":["Novel"],"associatedMergedColumns":[]}]},{"caption":"Table 4: (a) Ablation studies of MEDet. The Line2-4 show the increase in accuracy after the addition of our \nproposed OPM, CAug, and CBA modules. For \u0027MEDet w/o L ramcl \u0027 we use a cross-modal attention used in \nOVR ","rows":["OPM w / o ?se","MEDet","Top - 100 Obj","MEDet w / o L ramcl","+ OPM + CBA ( MEDet )","OPM w / o merge","OPM"],"columns":["All","Novel","Base"],"mergedAllColumns":[],"numberCells":[{"number":"52.3","isBolded":false,"associatedRows":["+ OPM + CBA ( MEDet )","OPM w / o merge"],"associatedColumns":["Base"],"associatedMergedColumns":[]},{"number":"30.2","isBolded":false,"associatedRows":["+ OPM + CBA ( MEDet )","OPM w / o ?se"],"associatedColumns":["Novel"],"associatedMergedColumns":[]},{"number":"47.5","isBolded":false,"associatedRows":["+ OPM + CBA ( MEDet )"],"associatedColumns":["All"],"associatedMergedColumns":[]},{"number":"46.5","isBolded":false,"associatedRows":["+ OPM + CBA ( MEDet )","Top - 100 Obj"],"associatedColumns":["All"],"associatedMergedColumns":[]},{"number":"52.9","isBolded":false,"associatedRows":["MEDet","OPM"],"associatedColumns":["Base"],"associatedMergedColumns":[]},{"number":"32.0","isBolded":false,"associatedRows":["+ OPM + CBA ( MEDet )"],"associatedColumns":["Novel"],"associatedMergedColumns":[]},{"number":"30.8","isBolded":false,"associatedRows":["MEDet w / o L ramcl"],"associatedColumns":["Novel"],"associatedMergedColumns":[]},{"number":"47.2","isBolded":false,"associatedRows":["+ OPM + CBA ( MEDet )"],"associatedColumns":["All"],"associatedMergedColumns":[]},{"number":"27.8","isBolded":false,"associatedRows":["+ OPM + CBA ( MEDet )","Top - 100 Obj"],"associatedColumns":["Novel"],"associatedMergedColumns":[]},{"number":"47.0","isBolded":false,"associatedRows":["MEDet w / o L ramcl"],"associatedColumns":["All"],"associatedMergedColumns":[]},{"number":"47.9","isBolded":false,"associatedRows":["MEDet"],"associatedColumns":["All"],"associatedMergedColumns":[]},{"number":"47.9","isBolded":false,"associatedRows":["+ OPM + CBA ( MEDet )"],"associatedColumns":["All"],"associatedMergedColumns":[]},{"number":"52.4","isBolded":false,"associatedRows":["+ OPM + CBA ( MEDet )","Top - 100 Obj"],"associatedColumns":["Base"],"associatedMergedColumns":[]},{"number":"43.3","isBolded":false,"associatedRows":["+ OPM + CBA ( MEDet )"],"associatedColumns":["Base"],"associatedMergedColumns":[]},{"number":"53.4","isBolded":false,"associatedRows":["MEDet"],"associatedColumns":["Base"],"associatedMergedColumns":[]},{"number":"52.9","isBolded":false,"associatedRows":["+ OPM + CBA ( MEDet )"],"associatedColumns":["Base"],"associatedMergedColumns":[]},{"number":"29.3","isBolded":false,"associatedRows":["+ OPM + CBA ( MEDet )","Top - 100 Obj"],"associatedColumns":["Novel"],"associatedMergedColumns":[]},{"number":"30.4","isBolded":false,"associatedRows":["MEDet w / o L ramcl","OPM w / o merge"],"associatedColumns":["Novel"],"associatedMergedColumns":[]},{"number":"28.7","isBolded":false,"associatedRows":["+ OPM + CBA ( MEDet )","OPM w / o merge"],"associatedColumns":["Novel"],"associatedMergedColumns":[]},{"number":"32.6","isBolded":false,"associatedRows":["MEDet"],"associatedColumns":["Novel"],"associatedMergedColumns":[]},{"number":"47.0","isBolded":false,"associatedRows":["MEDet w / o L ramcl","OPM w / o merge"],"associatedColumns":["All"],"associatedMergedColumns":[]},{"number":"52.8","isBolded":false,"associatedRows":["MEDet w / o L ramcl"],"associatedColumns":["Base"],"associatedMergedColumns":[]},{"number":"52.6","isBolded":false,"associatedRows":["+ OPM + CBA ( MEDet )","OPM w / o merge"],"associatedColumns":["Base"],"associatedMergedColumns":[]},{"number":"53.2","isBolded":false,"associatedRows":["+ OPM + CBA ( MEDet )","OPM w / o ?se"],"associatedColumns":["Base"],"associatedMergedColumns":[]},{"number":"53.4","isBolded":false,"associatedRows":["+ OPM + CBA ( MEDet )"],"associatedColumns":["Base"],"associatedMergedColumns":[]},{"number":"47.2","isBolded":false,"associatedRows":["MEDet","OPM"],"associatedColumns":["All"],"associatedMergedColumns":[]},{"number":"17.6","isBolded":false,"associatedRows":["+ OPM + CBA ( MEDet )"],"associatedColumns":["Novel"],"associatedMergedColumns":[]},{"number":"46.1","isBolded":false,"associatedRows":["+ OPM + CBA ( MEDet )","OPM w / o merge"],"associatedColumns":["All"],"associatedMergedColumns":[]},{"number":"31.0","isBolded":false,"associatedRows":["+ OPM + CBA ( MEDet )"],"associatedColumns":["Novel"],"associatedMergedColumns":[]},{"number":"32.6","isBolded":false,"associatedRows":["+ OPM + CBA ( MEDet )"],"associatedColumns":["Novel"],"associatedMergedColumns":[]},{"number":"53.1","isBolded":false,"associatedRows":["+ OPM + CBA ( MEDet )"],"associatedColumns":["Base"],"associatedMergedColumns":[]},{"number":"47.2","isBolded":false,"associatedRows":["+ OPM + CBA ( MEDet )","OPM w / o ?se"],"associatedColumns":["All"],"associatedMergedColumns":[]},{"number":"31.0","isBolded":false,"associatedRows":["MEDet","OPM"],"associatedColumns":["Novel"],"associatedMergedColumns":[]},{"number":"36.6","isBolded":false,"associatedRows":["+ OPM + CBA ( MEDet )"],"associatedColumns":["All"],"associatedMergedColumns":[]},{"number":"46.3","isBolded":false,"associatedRows":["+ OPM + CBA ( MEDet )","OPM w / o merge"],"associatedColumns":["All"],"associatedMergedColumns":[]},{"number":"52.8","isBolded":false,"associatedRows":["MEDet w / o L ramcl","OPM w / o merge"],"associatedColumns":["Base"],"associatedMergedColumns":[]}]},{"caption":"Table 5: The results of various ? in CBA. \n\n","rows":["Novel","Base"],"columns":["removes the most noise and obtains more reliable proposal - level vision - language knowledge ."],"mergedAllColumns":[],"numberCells":[{"number":"32.4","isBolded":false,"associatedRows":["Novel"],"associatedColumns":["removes the most noise and obtains more reliable proposal - level vision - language knowledge ."],"associatedMergedColumns":[]},{"number":"0.8","isBolded":false,"associatedRows":[],"associatedColumns":["removes the most noise and obtains more reliable proposal - level vision - language knowledge ."],"associatedMergedColumns":[]},{"number":"0.0","isBolded":false,"associatedRows":[],"associatedColumns":["removes the most noise and obtains more reliable proposal - level vision - language knowledge ."],"associatedMergedColumns":[]},{"number":"53.3","isBolded":false,"associatedRows":["Base"],"associatedColumns":["removes the most noise and obtains more reliable proposal - level vision - language knowledge ."],"associatedMergedColumns":[]},{"number":"53.1","isBolded":false,"associatedRows":["Base"],"associatedColumns":["removes the most noise and obtains more reliable proposal - level vision - language knowledge ."],"associatedMergedColumns":[]},{"number":"32.0","isBolded":false,"associatedRows":["Novel"],"associatedColumns":["removes the most noise and obtains more reliable proposal - level vision - language knowledge ."],"associatedMergedColumns":[]},{"number":"32.6","isBolded":false,"associatedRows":["Novel"],"associatedColumns":["removes the most noise and obtains more reliable proposal - level vision - language knowledge ."],"associatedMergedColumns":[]},{"number":"32.5","isBolded":false,"associatedRows":["Novel"],"associatedColumns":["removes the most noise and obtains more reliable proposal - level vision - language knowledge ."],"associatedMergedColumns":[]},{"number":"0.2","isBolded":false,"associatedRows":[],"associatedColumns":["removes the most noise and obtains more reliable proposal - level vision - language knowledge ."],"associatedMergedColumns":[]},{"number":"53.4","isBolded":false,"associatedRows":["Base"],"associatedColumns":["removes the most noise and obtains more reliable proposal - level vision - language knowledge ."],"associatedMergedColumns":[]},{"number":"1.0","isBolded":false,"associatedRows":[],"associatedColumns":["removes the most noise and obtains more reliable proposal - level vision - language knowledge ."],"associatedMergedColumns":[]},{"number":"32.6","isBolded":false,"associatedRows":["Novel"],"associatedColumns":["removes the most noise and obtains more reliable proposal - level vision - language knowledge ."],"associatedMergedColumns":[]},{"number":"0.6","isBolded":false,"associatedRows":[],"associatedColumns":["removes the most noise and obtains more reliable proposal - level vision - language knowledge ."],"associatedMergedColumns":[]},{"number":"32.6","isBolded":false,"associatedRows":["Novel"],"associatedColumns":["removes the most noise and obtains more reliable proposal - level vision - language knowledge ."],"associatedMergedColumns":[]},{"number":"0.4","isBolded":false,"associatedRows":[],"associatedColumns":["removes the most noise and obtains more reliable proposal - level vision - language knowledge ."],"associatedMergedColumns":[]},{"number":"53.5","isBolded":false,"associatedRows":["Base"],"associatedColumns":["removes the most noise and obtains more reliable proposal - level vision - language knowledge ."],"associatedMergedColumns":[]},{"number":"53.4","isBolded":false,"associatedRows":["Base"],"associatedColumns":["removes the most noise and obtains more reliable proposal - level vision - language knowledge ."],"associatedMergedColumns":[]},{"number":"53.3","isBolded":false,"associatedRows":["Base"],"associatedColumns":["removes the most noise and obtains more reliable proposal - level vision - language knowledge ."],"associatedMergedColumns":[]}]}]